Workbook

Sheet Chart-1
B1: Domestic Pre-Tax Profits | C1: Federal Income Taxes | D1: Effective Tax Rate | E1: Executive Pay | F1: Stock Buybacks | G1: Dividend Payouts
B2: Five-Year Total, 2018 to 2022 (millions of dollars)
A3: 35 Profitable Corporations That Paid More To Executives Than Federal Taxes | B3: ='Chart-2'!B39 -> 277426.71 | C3: ='Chart-2'!C39 -> -1718.97 | D3: =C3/B3 -> -0.0061961229 | E3: ='Chart-2'!E39 -> 9491.61 | F3: ='Chart-2'!F39 -> 86998.993 | G3: ='Chart-2'!G39 -> 147904.71
A5: 29 Profitable Corporations That Paid More To Executives Than Federal Taxes In At Least 2 Years | B5: ='Chart-3'!B33 -> 380289.31 | C5: ='Chart-3'!C33 -> 20010.68 | D5: =C5/B5 -> 0.052619623 | E5: ='Chart-3'!E33 -> 5605.1758 | F5: ='Chart-3'!F33 -> 160483.8 | G5: ='Chart-3'!G33 -> 217210.28
A7: All 64 Corporations | B7: ='Key Findings'!R3 -> 657716.02 | C7: ='Key Findings'!Y3 -> 18291.71 | D7: =C7/B7 -> 0.027810954 | E7: ='Key Findings'!D3/1000000 -> 15096.786 | F7: ='Key Findings'!AM3 -> 247482.79 | G7: ='Key Findings'!AT3 -> 365114.99

Sheet Chart-2
A1: 35 profitable corporations that paid top executives more than they paid in federal income taxes between 2018 and 2022 | B1: Domestic Pre-Tax Profits | C1: Federal Income Taxes | D1: Effective Tax Rate | E1: Executive Pay | F1: Stock Buybacks | G1: Dividend Payouts
B2: Five-Year Total, 2018 to 2022 (millions of dollars)
A3: NextEra Energy | B3: {=INDEX('Key Findings'!R:R,Match($A3,'Key Findings'!$B:$B,0))} -> 23965 | C3: {=INDEX('Key Findings'!Y:Y,Match($A3,'Key Findings'!$B:$B,0))} -> 287 | D3: =C3/B3 -> 0.011975798 | E3: {=INDEX('Key Findings'!D:D,Match($A3,'Key Findings'!$B:$B,0))/1000000} -> 324.82315 | F3: {=INDEX('Key Findings'!AM:AM,Match($A3,'Key Findings'!$B:$B,0))} -> 0 | G3: {=INDEX('Key Findings'!AT:AT,Match($A3,'Key Findings'!$B:$B,0))} -> 13628
A4: T-Mobile US | B4: {=INDEX('Key Findings'!R:R,Match($A4,'Key Findings'!$B:$B,0))} -> 17916.13 | C4: {=INDEX('Key Findings'!Y:Y,Match($A4,'Key Findings'!$B:$B,0))} -> -80 | D4: =C4/B4 -> -0.00446525 | E4: {=INDEX('Key Findings'!D:D,Match($A4,'Key Findings'!$B:$B,0))/1000000} -> 675.16 | F4: {=INDEX('Key Findings'!AM:AM,Match($A4,'Key Findings'!$B:$B,0))} -> 23607 | G4: {=INDEX('Key Findings'!AT:AT,Match($A4,'Key Findings'!$B:$B,0))} -> 0
A5: American International Group | B5: {=INDEX('Key Findings'!R:R,Match($A5,'Key Findings'!$B:$B,0))} -> 17687 | C5: {=INDEX('Key Findings'!Y:Y,Match($A5,'Key Findings'!$B:$B,0))} -> 385 | D5: =C5/B5 -> 0.0217674 | E5: {=INDEX('Key Findings'!D:D,Match($A5,'Key Findings'!$B:$B,0))/1000000} -> 406.14313 | F5: {=INDEX('Key Findings'!AM:AM,Match($A5,'Key Findings'!$B:$B,0))} -> 10037 | G5: {=INDEX('Key Findings'!AT:AT,Match($A5,'Key Findings'!$B:$B,0))} -> 5529
A6: Duke Energy | B6: {=INDEX('Key Findings'!R:R,Match($A6,'Key Findings'!$B:$B,0))} -> 15624 | C6: {=INDEX('Key Findings'!Y:Y,Match($A6,'Key Findings'!$B:$B,0))} -> -1228 | D6: =C6/B6 -> -0.07859703 | E6: {=INDEX('Key Findings'!D:D,Match($A6,'Key Findings'!$B:$B,0))/1000000} -> 180.5561 | F6: {=INDEX('Key Findings'!AM:AM,Match($A6,'Key Findings'!$B:$B,0))} -> 0 | G6: {=INDEX('Key Findings'!AT:AT,Match($A6,'Key Findings'!$B:$B,0))} -> 14244
A7: Netflix | B7: {=INDEX('Key Findings'!R:R,Match($A7,'Key Findings'!$B:$B,0))} -> 15079.54 | C7: {=INDEX('Key Findings'!Y:Y,Match($A7,'Key Findings'!$B:$B,0))} -> 235.98 | D7: =C7/B7 -> 0.015649018 | E7: {=INDEX('Key Findings'!D:D,Match($A7,'Key Findings'!$B:$B,0))/1000000} -> 651.92517 | F7: {=INDEX('Key Findings'!AM:AM,Match($A7,'Key Findings'!$B:$B,0))} -> 600.022 | G7: {=INDEX('Key Findings'!AT:AT,Match($A7,'Key Findings'!$B:$B,0))} -> 0
A8: DISH Network | B8: {=INDEX('Key Findings'!R:R,Match($A8,'Key Findings'!$B:$B,0))} -> 12782.84 | C8: {=INDEX('Key Findings'!Y:Y,Match($A8,'Key Findings'!$B:$B,0))} -> 89.71 | D8: =C8/B8 -> 0.0070180023 | E8: {=INDEX('Key Findings'!D:D,Match($A8,'Key Findings'!$B:$B,0))/1000000} -> 164.30339 | F8: {=INDEX('Key Findings'!AM:AM,Match($A8,'Key Findings'!$B:$B,0))} -> 0 | G8: {=INDEX('Key Findings'!AT:AT,Match($A8,'Key Findings'!$B:$B,0))} -> 0
A9: Principal Financial | B9: {=INDEX('Key Findings'!R:R,Match($A9,'Key Findings'!$B:$B,0))} -> 11976.3 | C9: {=INDEX('Key Findings'!Y:Y,Match($A9,'Key Findings'!$B:$B,0))} -> 45.9 | D9: =C9/B9 -> 0.0038325693 | E9: {=INDEX('Key Findings'!D:D,Match($A9,'Key Findings'!$B:$B,0))/1000000} -> 170.20218 | F9: {=INDEX('Key Findings'!AM:AM,Match($A9,'Key Findings'!$B:$B,0))} -> 3892 | G9: {=INDEX('Key Findings'!AT:AT,Match($A9,'Key Findings'!$B:$B,0))} -> 3115.5
A10: MetLife | B10: {=INDEX('Key Findings'!R:R,Match($A10,'Key Findings'!$B:$B,0))} -> 11658 | C10: {=INDEX('Key Findings'!Y:Y,Match($A10,'Key Findings'!$B:$B,0))} -> 96 | D10: =C10/B10 -> 0.0082346886 | E10: {=INDEX('Key Findings'!D:D,Match($A10,'Key Findings'!$B:$B,0))/1000000} -> 239.63619 | F10: {=INDEX('Key Findings'!AM:AM,Match($A10,'Key Findings'!$B:$B,0))} -> 15057 | G10: {=INDEX('Key Findings'!AT:AT,Match($A10,'Key Findings'!$B:$B,0))} -> 9124
A11: American Electric Power | B11: {=INDEX('Key Findings'!R:R,Match($A11,'Key Findings'!$B:$B,0))} -> 10835.6 | C11: {=INDEX('Key Findings'!Y:Y,Match($A11,'Key Findings'!$B:$B,0))} -> -92 | D11: =C11/B11 -> -0.0084905312 | E11: {=INDEX('Key Findings'!D:D,Match($A11,'Key Findings'!$B:$B,0))/1000000} -> 157.34985 | F11: {=INDEX('Key Findings'!AM:AM,Match($A11,'Key Findings'!$B:$B,0))} -> 0 | G11: {=INDEX('Key Findings'!AT:AT,Match($A11,'Key Findings'!$B:$B,0))} -> 7195.1
A12: Kinder Morgan | B12: {=INDEX('Key Findings'!R:R,Match($A12,'Key Findings'!$B:$B,0))} -> 12867.48 | C12: {=INDEX('Key Findings'!Y:Y,Match($A12,'Key Findings'!$B:$B,0))} -> -44 | D12: =C12/B12 -> -0.003419473 | E12: {=INDEX('Key Findings'!D:D,Match($A12,'Key Findings'!$B:$B,0))/1000000} -> 117.08397 | F12: {=INDEX('Key Findings'!AM:AM,Match($A12,'Key Findings'!$B:$B,0))} -> 693 | G12: {=INDEX('Key Findings'!AT:AT,Match($A12,'Key Findings'!$B:$B,0))} -> 11246
A13: Dominion Energy | B13: {=INDEX('Key Findings'!R:R,Match($A13,'Key Findings'!$B:$B,0))} -> 10200 | C13: {=INDEX('Key Findings'!Y:Y,Match($A13,'Key Findings'!$B:$B,0))} -> -482 | D13: =C13/B13 -> -0.047254902 | E13: {=INDEX('Key Findings'!D:D,Match($A13,'Key Findings'!$B:$B,0))/1000000} -> 155.72685 | F13: {=INDEX('Key Findings'!AM:AM,Match($A13,'Key Findings'!$B:$B,0))} -> 4690 | G13: {=INDEX('Key Findings'!AT:AT,Match($A13,'Key Findings'!$B:$B,0))} -> 12286
A14: Oneok | B14: {=INDEX('Key Findings'!R:R,Match($A14,'Key Findings'!$B:$B,0))} -> 8179.16 | C14: {=INDEX('Key Findings'!Y:Y,Match($A14,'Key Findings'!$B:$B,0))} -> 54.87 | D14: =C14/B14 -> 0.0067085129 | E14: {=INDEX('Key Findings'!D:D,Match($A14,'Key Findings'!$B:$B,0))/1000000} -> 107.19934 | F14: {=INDEX('Key Findings'!AM:AM,Match($A14,'Key Findings'!$B:$B,0))} -> 0 | G14: {=INDEX('Key Findings'!AT:AT,Match($A14,'Key Findings'!$B:$B,0))} -> 7737.07
... A37: Agilent Technologies | B37: {=INDEX('Key Findings'!R:R,Match($A37,'Key Findings'!$B:$B,0))} -> 2097 | C37: {=INDEX('Key Findings'!Y:Y,Match($A37,'Key Findings'!$B:$B,0))} -> 130 | D37: =C37/B37 -> 0.061993324 | E37: {=INDEX('Key Findings'!D:D,Match($A37,'Key Findings'!$B:$B,0))/1000000} -> 149.78778 | F37: {=INDEX('Key Findings'!AM:AM,Match($A37,'Key Findings'!$B:$B,0))} -> 3541 | G37: {=INDEX('Key Findings'!AT:AT,Match($A37,'Key Findings'!$B:$B,0))} -> 1105
A39: TOTAL | B39: =SUM(B3:B37) -> 277426.71 | C39: =SUM(C3:C37) -> -1718.97 | D39: =C39/B39 -> -0.0061961229 | E39: =SUM(E3:E37) -> 9491.61 | F39: =SUM(F3:F37) -> 86998.993 | G39: =SUM(G3:G37) -> 147904.71

Sheet Chart-3
A1: 29 profitable corporations that paid top executives more than they paid in federal income taxes in at least 2 of the 5 years between 2018 and 2022 | B1: Domestic Pre-Tax Profits | C1: Federal Income Taxes | D1: Effective Tax Rate | E1: Executive Pay | F1: Stock Buybacks | G1: Dividend Payouts
B2: Five-Year Total, 2018 to 2022 (millions of dollars)
A3: AT&T | B3: {=INDEX('Key Findings'!R:R,Match($A3,'Key Findings'!$B:$B,0))} -> 96279.52 | C3: {=INDEX('Key Findings'!Y:Y,Match($A3,'Key Findings'!$B:$B,0))} -> 2536 | D3: =C3/B3 -> 0.026339973 | E3: {=INDEX('Key Findings'!D:D,Match($A3,'Key Findings'!$B:$B,0))/1000000} -> 506.15635 | F3: {=INDEX('Key Findings'!AM:AM,Match($A3,'Key Findings'!$B:$B,0))} -> 9616 | G3: {=INDEX('Key Findings'!AT:AT,Match($A3,'Key Findings'!$B:$B,0))} -> 68181
A4: General Motors | B4: {=INDEX('Key Findings'!R:R,Match($A4,'Key Findings'!$B:$B,0))} -> 33110 | C4: {=INDEX('Key Findings'!Y:Y,Match($A4,'Key Findings'!$B:$B,0))} -> 431 | D4: =C4/B4 -> 0.013017215 | E4: {=INDEX('Key Findings'!D:D,Match($A4,'Key Findings'!$B:$B,0))/1000000} -> 317.60625 | F4: {=INDEX('Key Findings'!AM:AM,Match($A4,'Key Findings'!$B:$B,0))} -> 2690 | G4: {=INDEX('Key Findings'!AT:AT,Match($A4,'Key Findings'!$B:$B,0))} -> 5844
A5: Chevron | B5: {=INDEX('Key Findings'!R:R,Match($A5,'Key Findings'!$B:$B,0))} -> 23121 | C5: {=INDEX('Key Findings'!Y:Y,Match($A5,'Key Findings'!$B:$B,0))} -> 1461 | D5: =C5/B5 -> 0.063189308 | E5: {=INDEX('Key Findings'!D:D,Match($A5,'Key Findings'!$B:$B,0))/1000000} -> 325.6514 | F5: {=INDEX('Key Findings'!AM:AM,Match($A5,'Key Findings'!$B:$B,0))} -> 10487 | G5: {=INDEX('Key Findings'!AT:AT,Match($A5,'Key Findings'!$B:$B,0))} -> 48259
A6: Marathon Petroleum | B6: {=INDEX('Key Findings'!R:R,Match($A6,'Key Findings'!$B:$B,0))} -> 22394 | C6: {=INDEX('Key Findings'!Y:Y,Match($A6,'Key Findings'!$B:$B,0))} -> 2390 | D6: =C6/B6 -> 0.10672502 | E6: {=INDEX('Key Findings'!D:D,Match($A6,'Key Findings'!$B:$B,0))/1000000} -> 271.47507 | F6: {=INDEX('Key Findings'!AM:AM,Match($A6,'Key Findings'!$B:$B,0))} -> 21813 | G6: {=INDEX('Key Findings'!AT:AT,Match($A6,'Key Findings'!$B:$B,0))} -> 6625
A7: Southern | B7: {=INDEX('Key Findings'!R:R,Match($A7,'Key Findings'!$B:$B,0))} -> 19021 | C7: {=INDEX('Key Findings'!Y:Y,Match($A7,'Key Findings'!$B:$B,0))} -> 582 | D7: =C7/B7 -> 0.03059776 | E7: {=INDEX('Key Findings'!D:D,Match($A7,'Key Findings'!$B:$B,0))/1000000} -> 251.67606 | F7: {=INDEX('Key Findings'!AM:AM,Match($A7,'Key Findings'!$B:$B,0))} -> 0 | G7: {=INDEX('Key Findings'!AT:AT,Match($A7,'Key Findings'!$B:$B,0))} -> 13364
A8: Charter Communications | B8: {=INDEX('Key Findings'!R:R,Match($A8,'Key Findings'!$B:$B,0))} -> 18849 | C8: {=INDEX('Key Findings'!Y:Y,Match($A8,'Key Findings'!$B:$B,0))} -> 1212 | D8: =C8/B8 -> 0.064300493 | E8: {=INDEX('Key Findings'!D:D,Match($A8,'Key Findings'!$B:$B,0))/1000000} -> 313.41352 | F8: {=INDEX('Key Findings'!AM:AM,Match($A8,'Key Findings'!$B:$B,0))} -> 48197 | G8: {=INDEX('Key Findings'!AT:AT,Match($A8,'Key Findings'!$B:$B,0))} -> 0
A9: Honeywell International | B9: {=INDEX('Key Findings'!R:R,Match($A9,'Key Findings'!$B:$B,0))} -> 17194 | C9: {=INDEX('Key Findings'!Y:Y,Match($A9,'Key Findings'!$B:$B,0))} -> 1480 | D9: =C9/B9 -> 0.086076538 | E9: {=INDEX('Key Findings'!D:D,Match($A9,'Key Findings'!$B:$B,0))/1000000} -> 275.60004 | F9: {=INDEX('Key Findings'!AM:AM,Match($A9,'Key Findings'!$B:$B,0))} -> 19694 | G9: {=INDEX('Key Findings'!AT:AT,Match($A9,'Key Findings'!$B:$B,0))} -> 12651
A10: FedEx | B10: {=INDEX('Key Findings'!R:R,Match($A10,'Key Findings'!$B:$B,0))} -> 16228.85 | C10: {=INDEX('Key Findings'!Y:Y,Match($A10,'Key Findings'!$B:$B,0))} -> 752 | D10: =C10/B10 -> 0.046337233 | E10: {=INDEX('Key Findings'!D:D,Match($A10,'Key Findings'!$B:$B,0))/1000000} -> 193.76712 | F10: {=INDEX('Key Findings'!AM:AM,Match($A10,'Key Findings'!$B:$B,0))} -> 5231 | G10: {=INDEX('Key Findings'!AT:AT,Match($A10,'Key Findings'!$B:$B,0))} -> 4018
A11: Pioneer Natural Resources | B11: {=INDEX('Key Findings'!R:R,Match($A11,'Key Findings'!$B:$B,0))} -> 14583 | C11: {=INDEX('Key Findings'!Y:Y,Match($A11,'Key Findings'!$B:$B,0))} -> 241 | D11: =C11/B11 -> 0.016526092 | E11: {=INDEX('Key Findings'!D:D,Match($A11,'Key Findings'!$B:$B,0))/1000000} -> 165.47204 | F11: {=INDEX('Key Findings'!AM:AM,Match($A11,'Key Findings'!$B:$B,0))} -> 2964 | G11: {=INDEX('Key Findings'!AT:AT,Match($A11,'Key Findings'!$B:$B,0))} -> 8391
A12: Exelon | B12: {=INDEX('Key Findings'!R:R,Match($A12,'Key Findings'!$B:$B,0))} -> 13096 | C12: {=INDEX('Key Findings'!Y:Y,Match($A12,'Key Findings'!$B:$B,0))} -> 635 | D12: =C12/B12 -> 0.048488088 | E12: {=INDEX('Key Findings'!D:D,Match($A12,'Key Findings'!$B:$B,0))/1000000} -> 220.54916 | F12: {=INDEX('Key Findings'!AM:AM,Match($A12,'Key Findings'!$B:$B,0))} -> 0 | G12: {=INDEX('Key Findings'!AT:AT,Match($A12,'Key Findings'!$B:$B,0))} -> 7063
A13: Hartford Financial Services | B13: {=INDEX('Key Findings'!R:R,Match($A13,'Key Findings'!$B:$B,0))} -> 11761 | C13: {=INDEX('Key Findings'!Y:Y,Match($A13,'Key Findings'!$B:$B,0))} -> 1436 | D13: =C13/B13 -> 0.12209846 | E13: {=INDEX('Key Findings'!D:D,Match($A13,'Key Findings'!$B:$B,0))/1000000} -> 180.32519 | F13: {=INDEX('Key Findings'!AM:AM,Match($A13,'Key Findings'!$B:$B,0))} -> 3602 | G13: {=INDEX('Key Findings'!AT:AT,Match($A13,'Key Findings'!$B:$B,0))} -> 2344
A14: Ally Financial | B14: {=INDEX('Key Findings'!R:R,Match($A14,'Key Findings'!$B:$B,0))} -> 13278 | C14: {=INDEX('Key Findings'!Y:Y,Match($A14,'Key Findings'!$B:$B,0))} -> 489 | D14: =C14/B14 -> 0.036827836 | E14: {=INDEX('Key Findings'!D:D,Match($A14,'Key Findings'!$B:$B,0))/1000000} -> 142.90713 | F14: {=INDEX('Key Findings'!AM:AM,Match($A14,'Key Findings'!$B:$B,0))} -> 5728 | G14: {=INDEX('Key Findings'!AT:AT,Match($A14,'Key Findings'!$B:$B,0))} -> 1679
... A31: Ecolab | B31: {=INDEX('Key Findings'!R:R,Match($A31,'Key Findings'!$B:$B,0))} -> 2045.29 | C31: {=INDEX('Key Findings'!Y:Y,Match($A31,'Key Findings'!$B:$B,0))} -> 199.29 | D31: =C31/B31 -> 0.097438505 | E31: {=INDEX('Key Findings'!D:D,Match($A31,'Key Findings'!$B:$B,0))/1000000} -> 155.69031 | F31: {=INDEX('Key Findings'!AM:AM,Match($A31,'Key Findings'!$B:$B,0))} -> 1687 | G31: {=INDEX('Key Findings'!AT:AT,Match($A31,'Key Findings'!$B:$B,0))} -> 2777.7
A33: TOTAL | B33: =SUM(B1:B31) -> 380289.31 | C33: =SUM(C3:C31) -> 20010.68 | D33: =C33/B33 -> 0.052619623 | E33: =SUM(E1:E31) -> 5605.1758 | F33: =SUM(F1:F31) -> 160483.8 | G33: =SUM(G1:G31) -> 217210.28

Sheet Chart-4
A1: Billionaires | B1: 20 Highest Paid Executives | C1: Corporation | D1: Five-Year Corporate Tax Rate | E1: Five-Year Executive Pay | F1: Five-Year Median Employee Pay | G1: Five-Year Pay Ratio | H1: 2022 | I1: 2021 | J1: 2020 | K1: 2019 | L1: 2018
H2: Executive Pay by Year
A3: Yes | B3: Elon Musk | C3: Tesla | D3: {=INDEX('Key Findings'!AF:AF,MATCH(C3,'Key Findings'!B:B,0))} -> -0.00022593764 | E3: =SUMIF('Executive Pay Breakdown'!K:K,$B3,'Executive Pay Breakdown'!M:M)+SUMIF('Executive Pay Breakdown'!O:O,$B3,'Executive Pay Breakdown'!Q:Q)+SUMIF('Executive Pay Breakdown'!S:S,$B3,'Executive Pay Breakdown'!U:U)+SUMIF('Executive Pay Breakdown'!W:W,$B3,'Executive Pay Breakdown'!Y:Y)+SUMIF('Executive Pay Breakdown'!AA:AA,$B3,'Executive Pay Breakdown'!AC:AC) -> 2284068644 | F3: {=INDEX('Key Findings'!BB:BB,MATCH(C3,'Key Findings'!B:B,0))} -> 235575 | G3: 9,696-to-1 | H3: =SUMIF('Executive Pay Breakdown'!K:K,$B3,'Executive Pay Breakdown'!M:M) -> 0 | I3: =SUMIF('Executive Pay Breakdown'!O:O,$B3,'Executive Pay Breakdown'!Q:Q) -> 0 | J3: =SUMIF('Executive Pay Breakdown'!S:S,$B3,'Executive Pay Breakdown'!U:U) -> 0 | K3: =SUMIF('Executive Pay Breakdown'!W:W,$B3,'Executive Pay Breakdown'!Y:Y) -> 23760 | L3: =SUMIF('Executive Pay Breakdown'!AA:AA,$B3,'Executive Pay Breakdown'!AC:AC) -> 2284044884
B4: John J. Legere | C4: T-Mobile US | D4: {=INDEX('Key Findings'!AF:AF,MATCH(C4,'Key Findings'!B:B,0))} -> -0.00446525 | E4: =SUMIF('Executive Pay Breakdown'!K:K,$B4,'Executive Pay Breakdown'!M:M)+SUMIF('Executive Pay Breakdown'!O:O,$B4,'Executive Pay Breakdown'!Q:Q)+SUMIF('Executive Pay Breakdown'!S:S,$B4,'Executive Pay Breakdown'!U:U)+SUMIF('Executive Pay Breakdown'!W:W,$B4,'Executive Pay Breakdown'!Y:Y)+SUMIF('Executive Pay Breakdown'!AA:AA,$B4,'Executive Pay Breakdown'!AC:AC) -> 231490784 | F4: {=INDEX('Key Findings'!BB:BB,MATCH(C4,'Key Findings'!B:B,0))} -> 329702 | G4: 702-to-1 | H4: =SUMIF('Executive Pay Breakdown'!K:K,$B4,'Executive Pay Breakdown'!M:M) -> 0 | I4: =SUMIF('Executive Pay Breakdown'!O:O,$B4,'Executive Pay Breakdown'!Q:Q) -> 0 | J4: =SUMIF('Executive Pay Breakdown'!S:S,$B4,'Executive Pay Breakdown'!U:U) -> 137195887 | K4: =SUMIF('Executive Pay Breakdown'!W:W,$B4,'Executive Pay Breakdown'!Y:Y) -> 27756690 | L4: =SUMIF('Executive Pay Breakdown'!AA:AA,$B4,'Executive Pay Breakdown'!AC:AC) -> 66538207
A5: Yes | B5: Reed Hastings | C5: Netflix | D5: {=INDEX('Key Findings'!AF:AF,MATCH(C5,'Key Findings'!B:B,0))} -> 0.015649018 | E5: =SUMIF('Executive Pay Breakdown'!K:K,$B5,'Executive Pay Breakdown'!M:M)+SUMIF('Executive Pay Breakdown'!O:O,$B5,'Executive Pay Breakdown'!Q:Q)+SUMIF('Executive Pay Breakdown'!S:S,$B5,'Executive Pay Breakdown'!U:U)+SUMIF('Executive Pay Breakdown'!W:W,$B5,'Executive Pay Breakdown'!Y:Y)+SUMIF('Executive Pay Breakdown'!AA:AA,$B5,'Executive Pay Breakdown'!AC:AC) -> 209780532 | F5: {=INDEX('Key Findings'!BB:BB,MATCH(C5,'Key Findings'!B:B,0))} -> 1044986 | G5: 201-to-1 | H5: =SUMIF('Executive Pay Breakdown'!K:K,$B5,'Executive Pay Breakdown'!M:M) -> 51073237 | I5: =SUMIF('Executive Pay Breakdown'!O:O,$B5,'Executive Pay Breakdown'!Q:Q) -> 40823725 | J5: =SUMIF('Executive Pay Breakdown'!S:S,$B5,'Executive Pay Breakdown'!U:U) -> 43226024 | K5: =SUMIF('Executive Pay Breakdown'!W:W,$B5,'Executive Pay Breakdown'!Y:Y) -> 38577129 | L5: =SUMIF('Executive Pay Breakdown'!AA:AA,$B5,'Executive Pay Breakdown'!AC:AC) -> 36080417
B6: Ted Sarandos | C6: Netflix | D6: {=INDEX('Key Findings'!AF:AF,MATCH(C6,'Key Findings'!B:B,0))} -> 0.015649018 | E6: =SUMIF('Executive Pay Breakdown'!K:K,$B6,'Executive Pay Breakdown'!M:M)+SUMIF('Executive Pay Breakdown'!O:O,$B6,'Executive Pay Breakdown'!Q:Q)+SUMIF('Executive Pay Breakdown'!S:S,$B6,'Executive Pay Breakdown'!U:U)+SUMIF('Executive Pay Breakdown'!W:W,$B6,'Executive Pay Breakdown'!Y:Y)+SUMIF('Executive Pay Breakdown'!AA:AA,$B6,'Executive Pay Breakdown'!AC:AC) -> 192171581 | F6: {=INDEX('Key Findings'!BB:BB,MATCH(C6,'Key Findings'!B:B,0))} -> 1044986 | G6: 184-to-1 | H6: =SUMIF('Executive Pay Breakdown'!K:K,$B6,'Executive Pay Breakdown'!M:M) -> 50299296 | I6: =SUMIF('Executive Pay Breakdown'!O:O,$B6,'Executive Pay Breakdown'!Q:Q) -> 38232164 | J6: =SUMIF('Executive Pay Breakdown'!S:S,$B6,'Executive Pay Breakdown'!U:U) -> 39318251 | K6: =SUMIF('Executive Pay Breakdown'!W:W,$B6,'Executive Pay Breakdown'!Y:Y) -> 34674399 | L6: =SUMIF('Executive Pay Breakdown'!AA:AA,$B6,'Executive Pay Breakdown'!AC:AC) -> 29647471
B7: G. Michael Sievert | C7: T-Mobile US | D7: {=INDEX('Key Findings'!AF:AF,MATCH(C7,'Key Findings'!B:B,0))} -> -0.00446525 | E7: =SUMIF('Executive Pay Breakdown'!K:K,$B7,'Executive Pay Breakdown'!M:M)+SUMIF('Executive Pay Breakdown'!O:O,$B7,'Executive Pay Breakdown'!Q:Q)+SUMIF('Executive Pay Breakdown'!S:S,$B7,'Executive Pay Breakdown'!U:U)+SUMIF('Executive Pay Breakdown'!W:W,$B7,'Executive Pay Breakdown'!Y:Y)+SUMIF('Executive Pay Breakdown'!AA:AA,$B7,'Executive Pay Breakdown'!AC:AC) -> 158603797 | F7: {=INDEX('Key Findings'!BB:BB,MATCH(C7,'Key Findings'!B:B,0))} -> 329702 | G7: 481-to-1 | H7: =SUMIF('Executive Pay Breakdown'!K:K,$B7,'Executive Pay Breakdown'!M:M) -> 29060048 | I7: =SUMIF('Executive Pay Breakdown'!O:O,$B7,'Executive Pay Breakdown'!Q:Q) -> 22610659 | J7: =SUMIF('Executive Pay Breakdown'!S:S,$B7,'Executive Pay Breakdown'!U:U) -> 54914014 | K7: =SUMIF('Executive Pay Breakdown'!W:W,$B7,'Executive Pay Breakdown'!Y:Y) -> 16369704 | L7: =SUMIF('Executive Pay Breakdown'!AA:AA,$B7,'Executive Pay Breakdown'!AC:AC) -> 35649372
B8: Peter Zaffino | C8: American International Group | D8: {=INDEX('Key Findings'!AF:AF,MATCH(C8,'Key Findings'!B:B,0))} -> 0.0217674 | E8: =SUMIF('Executive Pay Breakdown'!K:K,$B8,'Executive Pay Breakdown'!M:M)+SUMIF('Executive Pay Breakdown'!O:O,$B8,'Executive Pay Breakdown'!Q:Q)+SUMIF('Executive Pay Breakdown'!S:S,$B8,'Executive Pay Breakdown'!U:U)+SUMIF('Executive Pay Breakdown'!W:W,$B8,'Executive Pay Breakdown'!Y:Y)+SUMIF('Executive Pay Breakdown'!AA:AA,$B8,'Executive Pay Breakdown'!AC:AC) -> 152295198 | F8: {=INDEX('Key Findings'!BB:BB,MATCH(C8,'Key Findings'!B:B,0))} -> 360945 | G8: 422-to-1 | H8: =SUMIF('Executive Pay Breakdown'!K:K,$B8,'Executive Pay Breakdown'!M:M) -> 75314199 | I8: =SUMIF('Executive Pay Breakdown'!O:O,$B8,'Executive Pay Breakdown'!Q:Q) -> 21905220 | J8: =SUMIF('Executive Pay Breakdown'!S:S,$B8,'Executive Pay Breakdown'!U:U) -> 24066986 | K8: =SUMIF('Executive Pay Breakdown'!W:W,$B8,'Executive Pay Breakdown'!Y:Y) -> 18388334 | L8: =SUMIF('Executive Pay Breakdown'!AA:AA,$B8,'Executive Pay Breakdown'!AC:AC) -> 12620459
A9: Yes | B9: Marc Benioff | C9: Salesforce | D9: {=INDEX('Key Findings'!AF:AF,MATCH(C9,'Key Findings'!B:B,0))} -> 0.029013235 | E9: =SUMIF('Executive Pay Breakdown'!K:K,$B9,'Executive Pay Breakdown'!M:M)+SUMIF('Executive Pay Breakdown'!O:O,$B9,'Executive Pay Breakdown'!Q:Q)+SUMIF('Executive Pay Breakdown'!S:S,$B9,'Executive Pay Breakdown'!U:U)+SUMIF('Executive Pay Breakdown'!W:W,$B9,'Executive Pay Breakdown'!Y:Y)+SUMIF('Executive Pay Breakdown'!AA:AA,$B9,'Executive Pay Breakdown'!AC:AC) -> 138573120 | F9: {=INDEX('Key Findings'!BB:BB,MATCH(C9,'Key Findings'!B:B,0))} -> 855246 | G9: 162-to-1 | H9: =SUMIF('Executive Pay Breakdown'!K:K,$B9,'Executive Pay Breakdown'!M:M) -> 29868893 | I9: =SUMIF('Executive Pay Breakdown'!O:O,$B9,'Executive Pay Breakdown'!Q:Q) -> 28602112 | J9: =SUMIF('Executive Pay Breakdown'!S:S,$B9,'Executive Pay Breakdown'!U:U) -> 25740775 | K9: =SUMIF('Executive Pay Breakdown'!W:W,$B9,'Executive Pay Breakdown'!Y:Y) -> 25969494 | L9: =SUMIF('Executive Pay Breakdown'!AA:AA,$B9,'Executive Pay Breakdown'!AC:AC) -> 28391846
B10: Thomas M. Rutledge | C10: Charter Communications | D10: {=INDEX('Key Findings'!AF:AF,MATCH(C10,'Key Findings'!B:B,0))} -> 0.064300493 | E10: =SUMIF('Executive Pay Breakdown'!K:K,$B10,'Executive Pay Breakdown'!M:M)+SUMIF('Executive Pay Breakdown'!O:O,$B10,'Executive Pay Breakdown'!Q:Q)+SUMIF('Executive Pay Breakdown'!S:S,$B10,'Executive Pay Breakdown'!U:U)+SUMIF('Executive Pay Breakdown'!W:W,$B10,'Executive Pay Breakdown'!Y:Y)+SUMIF('Executive Pay Breakdown'!AA:AA,$B10,'Executive Pay Breakdown'!AC:AC) -> 136821183 | F10: {=INDEX('Key Findings'!BB:BB,MATCH(C10,'Key Findings'!B:B,0))} -> 285189 | G10: 480-to-1 | H10: =SUMIF('Executive Pay Breakdown'!K:K,$B10,'Executive Pay Breakdown'!M:M) -> 39213350 | I10: =SUMIF('Executive Pay Breakdown'!O:O,$B10,'Executive Pay Breakdown'!Q:Q) -> 41860263 | J10: =SUMIF('Executive Pay Breakdown'!S:S,$B10,'Executive Pay Breakdown'!U:U) -> 38846705 | K10: =SUMIF('Executive Pay Breakdown'!W:W,$B10,'Executive Pay Breakdown'!Y:Y) -> 8743601 | L10: =SUMIF('Executive Pay Breakdown'!AA:AA,$B10,'Executive Pay Breakdown'!AC:AC) -> 8157264
B11: James L. Robo | C11: NextEra Energy | D11: {=INDEX('Key Findings'!AF:AF,MATCH(C11,'Key Findings'!B:B,0))} -> 0.011975798 | E11: =SUMIF('Executive Pay Breakdown'!K:K,$B11,'Executive Pay Breakdown'!M:M)+SUMIF('Executive Pay Breakdown'!O:O,$B11,'Executive Pay Breakdown'!Q:Q)+SUMIF('Executive Pay Breakdown'!S:S,$B11,'Executive Pay Breakdown'!U:U)+SUMIF('Executive Pay Breakdown'!W:W,$B11,'Executive Pay Breakdown'!Y:Y)+SUMIF('Executive Pay Breakdown'!AA:AA,$B11,'Executive Pay Breakdown'!AC:AC) -> 132699000 | F11: {=INDEX('Key Findings'!BB:BB,MATCH(C11,'Key Findings'!B:B,0))} -> 664263 | G11: 200-to-1 | H11: =SUMIF('Executive Pay Breakdown'!K:K,$B11,'Executive Pay Breakdown'!M:M) -> 40406018 | I11: =SUMIF('Executive Pay Breakdown'!O:O,$B11,'Executive Pay Breakdown'!Q:Q) -> 25335936 | J11: =SUMIF('Executive Pay Breakdown'!S:S,$B11,'Executive Pay Breakdown'!U:U) -> 23720707 | K11: =SUMIF('Executive Pay Breakdown'!W:W,$B11,'Executive Pay Breakdown'!Y:Y) -> 21877597 | L11: =SUMIF('Executive Pay Breakdown'!AA:AA,$B11,'Executive Pay Breakdown'!AC:AC) -> 21358742
B12: Michael K. Wirth | C12: Chevron | D12: {=INDEX('Key Findings'!AF:AF,MATCH(C12,'Key Findings'!B:B,0))} -> 0.063189308 | E12: =SUMIF('Executive Pay Breakdown'!K:K,$B12,'Executive Pay Breakdown'!M:M)+SUMIF('Executive Pay Breakdown'!O:O,$B12,'Executive Pay Breakdown'!Q:Q)+SUMIF('Executive Pay Breakdown'!S:S,$B12,'Executive Pay Breakdown'!U:U)+SUMIF('Executive Pay Breakdown'!W:W,$B12,'Executive Pay Breakdown'!Y:Y)+SUMIF('Executive Pay Breakdown'!AA:AA,$B12,'Executive Pay Breakdown'!AC:AC) -> 128912181 | F12: {=INDEX('Key Findings'!BB:BB,MATCH(C12,'Key Findings'!B:B,0))} -> 785016 | G12: 164-to-1 | H12: =SUMIF('Executive Pay Breakdown'!K:K,$B12,'Executive Pay Breakdown'!M:M) -> 23573925 | I12: =SUMIF('Executive Pay Breakdown'!O:O,$B12,'Executive Pay Breakdown'!Q:Q) -> 22610285 | J12: =SUMIF('Executive Pay Breakdown'!S:S,$B12,'Executive Pay Breakdown'!U:U) -> 29016686 | K12: =SUMIF('Executive Pay Breakdown'!W:W,$B12,'Executive Pay Breakdown'!Y:Y) -> 33070662 | L12: =SUMIF('Executive Pay Breakdown'!AA:AA,$B12,'Executive Pay Breakdown'!AC:AC) -> 20640623
B13: Mary T. Barra | C13: General Motors | D13: {=INDEX('Key Findings'!AF:AF,MATCH(C13,'Key Findings'!B:B,0))} -> 0.013017215 | E13: =SUMIF('Executive Pay Breakdown'!K:K,$B13,'Executive Pay Breakdown'!M:M)+SUMIF('Executive Pay Breakdown'!O:O,$B13,'Executive Pay Breakdown'!Q:Q)+SUMIF('Executive Pay Breakdown'!S:S,$B13,'Executive Pay Breakdown'!U:U)+SUMIF('Executive Pay Breakdown'!W:W,$B13,'Executive Pay Breakdown'!Y:Y)+SUMIF('Executive Pay Breakdown'!AA:AA,$B13,'Executive Pay Breakdown'!AC:AC) -> 125275654 | F13: {=INDEX('Key Findings'!BB:BB,MATCH(C13,'Key Findings'!B:B,0))} -> 451597 | G13: 277-to-1 | H13: =SUMIF('Executive Pay Breakdown'!K:K,$B13,'Executive Pay Breakdown'!M:M) -> 28979570 | I13: =SUMIF('Executive Pay Breakdown'!O:O,$B13,'Executive Pay Breakdown'!Q:Q) -> 29136780 | J13: =SUMIF('Executive Pay Breakdown'!S:S,$B13,'Executive Pay Breakdown'!U:U) -> 23657987 | K13: =SUMIF('Executive Pay Breakdown'!W:W,$B13,'Executive Pay Breakdown'!Y:Y) -> 21630867 | L13: =SUMIF('Executive Pay Breakdown'!AA:AA,$B13,'Executive Pay Breakdown'!AC:AC) -> 21870450
B14: Jeffrey K. Storey | C14: Lumen Technologies | D14: {=INDEX('Key Findings'!AF:AF,MATCH(C14,'Key Findings'!B:B,0))} -> 0.031863865 | E14: =SUMIF('Executive Pay Breakdown'!K:K,$B14,'Executive Pay Breakdown'!M:M)+SUMIF('Executive Pay Breakdown'!O:O,$B14,'Executive Pay Breakdown'!Q:Q)+SUMIF('Executive Pay Breakdown'!S:S,$B14,'Executive Pay Breakdown'!U:U)+SUMIF('Executive Pay Breakdown'!W:W,$B14,'Executive Pay Breakdown'!Y:Y)+SUMIF('Executive Pay Breakdown'!AA:AA,$B14,'Executive Pay Breakdown'!AC:AC) -> 112321574 | F14: {=INDEX('Key Findings'!BB:BB,MATCH(C14,'Key Findings'!B:B,0))} -> 368248 | G14: 305-to-1 | H14: =SUMIF('Executive Pay Breakdown'!K:K,$B14,'Executive Pay Breakdown'!M:M) -> 19816806 | I14: =SUMIF('Executive Pay Breakdown'!O:O,$B14,'Executive Pay Breakdown'!Q:Q) -> 22654781 | J14: =SUMIF('Executive Pay Breakdown'!S:S,$B14,'Executive Pay Breakdown'!U:U) -> 16959233 | K14: =SUMIF('Executive Pay Breakdown'!W:W,$B14,'Executive Pay Breakdown'!Y:Y) -> 17235108 | L14: =SUMIF('Executive Pay Breakdown'!AA:AA,$B14,'Executive Pay Breakdown'!AC:AC) -> 35655646
B15: Darius Adamczyk | C15: Honeywell International | D15: {=INDEX('Key Findings'!AF:AF,MATCH(C15,'Key Findings'!B:B,0))} -> 0.086076538 | E15: =SUMIF('Executive Pay Breakdown'!K:K,$B15,'Executive Pay Breakdown'!M:M)+SUMIF('Executive Pay Breakdown'!O:O,$B15,'Executive Pay Breakdown'!Q:Q)+SUMIF('Executive Pay Breakdown'!S:S,$B15,'Executive Pay Breakdown'!U:U)+SUMIF('Executive Pay Breakdown'!W:W,$B15,'Executive Pay Breakdown'!Y:Y)+SUMIF('Executive Pay Breakdown'!AA:AA,$B15,'Executive Pay Breakdown'!AC:AC) -> 110384707 | F15: {=INDEX('Key Findings'!BB:BB,MATCH(C15,'Key Findings'!B:B,0))} -> 354324 | G15: 312-to-1 | H15: =SUMIF('Executive Pay Breakdown'!K:K,$B15,'Executive Pay Breakdown'!M:M) -> 25437598 | I15: =SUMIF('Executive Pay Breakdown'!O:O,$B15,'Executive Pay Breakdown'!Q:Q) -> 26100120 | J15: =SUMIF('Executive Pay Breakdown'!S:S,$B15,'Executive Pay Breakdown'!U:U) -> 19075281 | K15: =SUMIF('Executive Pay Breakdown'!W:W,$B15,'Executive Pay Breakdown'!Y:Y) -> 20525104 | L15: =SUMIF('Executive Pay Breakdown'!AA:AA,$B15,'Executive Pay Breakdown'!AC:AC) -> 19246604
B16: Thomas A. Fanning | C16: Southern | D16: {=INDEX('Key Findings'!AF:AF,MATCH(C16,'Key Findings'!B:B,0))} -> 0.03059776 | E16: =SUMIF('Executive Pay Breakdown'!K:K,$B16,'Executive Pay Breakdown'!M:M)+SUMIF('Executive Pay Breakdown'!O:O,$B16,'Executive Pay Breakdown'!Q:Q)+SUMIF('Executive Pay Breakdown'!S:S,$B16,'Executive Pay Breakdown'!U:U)+SUMIF('Executive Pay Breakdown'!W:W,$B16,'Executive Pay Breakdown'!Y:Y)+SUMIF('Executive Pay Breakdown'!AA:AA,$B16,'Executive Pay Breakdown'!AC:AC) -> 108579955 | F16: {=INDEX('Key Findings'!BB:BB,MATCH(C16,'Key Findings'!B:B,0))} -> 679620 | G16: 160-to-1 | H16: =SUMIF('Executive Pay Breakdown'!K:K,$B16,'Executive Pay Breakdown'!M:M) -> 24006670 | I16: =SUMIF('Executive Pay Breakdown'!O:O,$B16,'Executive Pay Breakdown'!Q:Q) -> 21243559 | J16: =SUMIF('Executive Pay Breakdown'!S:S,$B16,'Executive Pay Breakdown'!U:U) -> 22366850 | K16: =SUMIF('Executive Pay Breakdown'!W:W,$B16,'Executive Pay Breakdown'!Y:Y) -> 27865185 | L16: =SUMIF('Executive Pay Breakdown'!AA:AA,$B16,'Executive Pay Breakdown'!AC:AC) -> 13097691
B17: Juan Ricardo Luciano | C17: Archer Daniels Midland | D17: {=INDEX('Key Findings'!AF:AF,MATCH(C17,'Key Findings'!B:B,0))} -> 0.09336413 | E17: =SUMIF('Executive Pay Breakdown'!K:K,$B17,'Executive Pay Breakdown'!M:M)+SUMIF('Executive Pay Breakdown'!O:O,$B17,'Executive Pay Breakdown'!Q:Q)+SUMIF('Executive Pay Breakdown'!S:S,$B17,'Executive Pay Breakdown'!U:U)+SUMIF('Executive Pay Breakdown'!W:W,$B17,'Executive Pay Breakdown'!Y:Y)+SUMIF('Executive Pay Breakdown'!AA:AA,$B17,'Executive Pay Breakdown'!AC:AC) -> 108030407 | F17: {=INDEX('Key Findings'!BB:BB,MATCH(C17,'Key Findings'!B:B,0))} -> 329904 | G17: 327-to-1 | H17: =SUMIF('Executive Pay Breakdown'!K:K,$B17,'Executive Pay Breakdown'!M:M) -> 24749178 | I17: =SUMIF('Executive Pay Breakdown'!O:O,$B17,'Executive Pay Breakdown'!Q:Q) -> 23508841 | J17: =SUMIF('Executive Pay Breakdown'!S:S,$B17,'Executive Pay Breakdown'!U:U) -> 21994433 | K17: =SUMIF('Executive Pay Breakdown'!W:W,$B17,'Executive Pay Breakdown'!Y:Y) -> 18140421 | L17: =SUMIF('Executive Pay Breakdown'!AA:AA,$B17,'Executive Pay Breakdown'!AC:AC) -> 19637534
B18: John T. Stankey | C18: AT&T | D18: {=INDEX('Key Findings'!AF:AF,MATCH(C18,'Key Findings'!B:B,0))} -> 0.026339973 | E18: =SUMIF('Executive Pay Breakdown'!K:K,$B18,'Executive Pay Breakdown'!M:M)+SUMIF('Executive Pay Breakdown'!O:O,$B18,'Executive Pay Breakdown'!Q:Q)+SUMIF('Executive Pay Breakdown'!S:S,$B18,'Executive Pay Breakdown'!U:U)+SUMIF('Executive Pay Breakdown'!W:W,$B18,'Executive Pay Breakdown'!Y:Y)+SUMIF('Executive Pay Breakdown'!AA:AA,$B18,'Executive Pay Breakdown'!AC:AC) -> 107783233 | F18: {=INDEX('Key Findings'!BB:BB,MATCH(C18,'Key Findings'!B:B,0))} -> 495922 | G18: 217-to-1 | H18: =SUMIF('Executive Pay Breakdown'!K:K,$B18,'Executive Pay Breakdown'!M:M) -> 22915526 | I18: =SUMIF('Executive Pay Breakdown'!O:O,$B18,'Executive Pay Breakdown'!Q:Q) -> 24820879 | J18: =SUMIF('Executive Pay Breakdown'!S:S,$B18,'Executive Pay Breakdown'!U:U) -> 21020917 | K18: =SUMIF('Executive Pay Breakdown'!W:W,$B18,'Executive Pay Breakdown'!Y:Y) -> 22473006 | L18: =SUMIF('Executive Pay Breakdown'!AA:AA,$B18,'Executive Pay Breakdown'!AC:AC) -> 16552905
B19: Randall L. Stephenson | C19: AT&T | D19: {=INDEX('Key Findings'!AF:AF,MATCH(C19,'Key Findings'!B:B,0))} -> 0.026339973 | E19: =SUMIF('Executive Pay Breakdown'!K:K,$B19,'Executive Pay Breakdown'!M:M)+SUMIF('Executive Pay Breakdown'!O:O,$B19,'Executive Pay Breakdown'!Q:Q)+SUMIF('Executive Pay Breakdown'!S:S,$B19,'Executive Pay Breakdown'!U:U)+SUMIF('Executive Pay Breakdown'!W:W,$B19,'Executive Pay Breakdown'!Y:Y)+SUMIF('Executive Pay Breakdown'!AA:AA,$B19,'Executive Pay Breakdown'!AC:AC) -> 106651170 | F19: {=INDEX('Key Findings'!BB:BB,MATCH(C19,'Key Findings'!B:B,0))} -> 495922 | G19: 215-to-1 | H19: =SUMIF('Executive Pay Breakdown'!K:K,$B19,'Executive Pay Breakdown'!M:M) -> 0 | I19: =SUMIF('Executive Pay Breakdown'!O:O,$B19,'Executive Pay Breakdown'!Q:Q) -> 16345499 | J19: =SUMIF('Executive Pay Breakdown'!S:S,$B19,'Executive Pay Breakdown'!U:U) -> 29154628 | K19: =SUMIF('Executive Pay Breakdown'!W:W,$B19,'Executive Pay Breakdown'!Y:Y) -> 32032925 | L19: =SUMIF('Executive Pay Breakdown'!AA:AA,$B19,'Executive Pay Breakdown'!AC:AC) -> 29118118
A20: Yes | B20: Charles W. Ergen | C20: DISH Network | D20: {=INDEX('Key Findings'!AF:AF,MATCH(C20,'Key Findings'!B:B,0))} -> 0.0070180023 | E20: =SUMIF('Executive Pay Breakdown'!K:K,$B20,'Executive Pay Breakdown'!M:M)+SUMIF('Executive Pay Breakdown'!O:O,$B20,'Executive Pay Breakdown'!Q:Q)+SUMIF('Executive Pay Breakdown'!S:S,$B20,'Executive Pay Breakdown'!U:U)+SUMIF('Executive Pay Breakdown'!W:W,$B20,'Executive Pay Breakdown'!Y:Y)+SUMIF('Executive Pay Breakdown'!AA:AA,$B20,'Executive Pay Breakdown'!AC:AC) -> 106511754 | F20: {=INDEX('Key Findings'!BB:BB,MATCH(C20,'Key Findings'!B:B,0))} -> 296500 | G20: 359-to-1 | H20: =SUMIF('Executive Pay Breakdown'!K:K,$B20,'Executive Pay Breakdown'!M:M) -> 3219778 | I20: =SUMIF('Executive Pay Breakdown'!O:O,$B20,'Executive Pay Breakdown'!Q:Q) -> 3060317 | J20: =SUMIF('Executive Pay Breakdown'!S:S,$B20,'Executive Pay Breakdown'!U:U) -> 94761246 | K20: =SUMIF('Executive Pay Breakdown'!W:W,$B20,'Executive Pay Breakdown'!Y:Y) -> 2357756 | L20: =SUMIF('Executive Pay Breakdown'!AA:AA,$B20,'Executive Pay Breakdown'!AC:AC) -> 3112657
B21: Greg Peters | C21: Netflix | D21: {=INDEX('Key Findings'!AF:AF,MATCH(C21,'Key Findings'!B:B,0))} -> 0.015649018 | E21: =SUMIF('Executive Pay Breakdown'!K:K,$B21,'Executive Pay Breakdown'!M:M)+SUMIF('Executive Pay Breakdown'!O:O,$B21,'Executive Pay Breakdown'!Q:Q)+SUMIF('Executive Pay Breakdown'!S:S,$B21,'Executive Pay Breakdown'!U:U)+SUMIF('Executive Pay Breakdown'!W:W,$B21,'Executive Pay Breakdown'!Y:Y)+SUMIF('Executive Pay Breakdown'!AA:AA,$B21,'Executive Pay Breakdown'!AC:AC) -> 102753950 | F21: {=INDEX('Key Findings'!BB:BB,MATCH(C21,'Key Findings'!B:B,0))} -> 1044986 | G21: 98-to-1 | H21: =SUMIF('Executive Pay Breakdown'!K:K,$B21,'Executive Pay Breakdown'!M:M) -> 28129263 | I21: =SUMIF('Executive Pay Breakdown'!O:O,$B21,'Executive Pay Breakdown'!Q:Q) -> 20371393 | J21: =SUMIF('Executive Pay Breakdown'!S:S,$B21,'Executive Pay Breakdown'!U:U) -> 20805995 | K21: =SUMIF('Executive Pay Breakdown'!W:W,$B21,'Executive Pay Breakdown'!Y:Y) -> 18628710 | L21: =SUMIF('Executive Pay Breakdown'!AA:AA,$B21,'Executive Pay Breakdown'!AC:AC) -> 14818589
B22: Jeffrey W. Martin | C22: Sempra Energy | D22: {=INDEX('Key Findings'!AF:AF,MATCH(C22,'Key Findings'!B:B,0))} -> 0.001160389 | E22: =SUMIF('Executive Pay Breakdown'!K:K,$B22,'Executive Pay Breakdown'!M:M)+SUMIF('Executive Pay Breakdown'!O:O,$B22,'Executive Pay Breakdown'!Q:Q)+SUMIF('Executive Pay Breakdown'!S:S,$B22,'Executive Pay Breakdown'!U:U)+SUMIF('Executive Pay Breakdown'!W:W,$B22,'Executive Pay Breakdown'!Y:Y)+SUMIF('Executive Pay Breakdown'!AA:AA,$B22,'Executive Pay Breakdown'!AC:AC) -> 95596632 | F22: {=INDEX('Key Findings'!BB:BB,MATCH(C22,'Key Findings'!B:B,0))} -> 685315 | G22: 139-to-1 | H22: =SUMIF('Executive Pay Breakdown'!K:K,$B22,'Executive Pay Breakdown'!M:M) -> 18608094 | I22: =SUMIF('Executive Pay Breakdown'!O:O,$B22,'Executive Pay Breakdown'!Q:Q) -> 24675982 | J22: =SUMIF('Executive Pay Breakdown'!S:S,$B22,'Executive Pay Breakdown'!U:U) -> 23181719 | K22: =SUMIF('Executive Pay Breakdown'!W:W,$B22,'Executive Pay Breakdown'!Y:Y) -> 19806346 | L22: =SUMIF('Executive Pay Breakdown'!AA:AA,$B22,'Executive Pay Breakdown'!AC:AC) -> 9324491

Sheet Chart-5
A1: Billionaires | B1: Fastest Growing Executive Pay | C1: Corporate Allegiance | D1: Executive 5-Year Wage Growth | F1: Median Worker 5-Year Wage Growth | I1: Five-Year Executive Pay | K1: 2022 | L1: 2021 | M1: 2020 | N1: 2019 | O1: 2018
D2: ($) | E2: (%) | F2: ($) | G2: (%) | K2: Executive Pay by Year
B3: Christopher L. Winfrey | C3: Charter Communications | D3: =K3-O3 -> 13495699 | E3: =K3/O3-1 -> 6.3322393 | F3: {=INDEX('Key Findings'!BC:BC,MATCH(C3,'Key Findings'!B:B,0))-INDEX('Key Findings'!BG:BG,MATCH(C3,'Key Findings'!B:B,0))} -> -131 | G3: {=INDEX('Key Findings'!BC:BC,MATCH(C3,'Key Findings'!B:B,0))/INDEX('Key Findings'!BG:BG,MATCH(C3,'Key Findings'!B:B,0))-1} -> -0.0023578114 | I3: =SUMIF('Executive Pay Breakdown'!K:K,$B3,'Executive Pay Breakdown'!M:M)+SUMIF('Executive Pay Breakdown'!O:O,$B3,'Executive Pay Breakdown'!Q:Q)+SUMIF('Executive Pay Breakdown'!S:S,$B3,'Executive Pay Breakdown'!U:U)+SUMIF('Executive Pay Breakdown'!W:W,$B3,'Executive Pay Breakdown'!Y:Y)+SUMIF('Executive Pay Breakdown'!AA:AA,$B3,'Executive Pay Breakdown'!AC:AC) -> 43654124 | K3: =SUMIF('Executive Pay Breakdown'!K:K,$B3,'Executive Pay Breakdown'!M:M) -> 15626967 | L3: =SUMIF('Executive Pay Breakdown'!O:O,$B3,'Executive Pay Breakdown'!Q:Q) -> 11685716 | M3: =SUMIF('Executive Pay Breakdown'!S:S,$B3,'Executive Pay Breakdown'!U:U) -> 11737410 | N3: =SUMIF('Executive Pay Breakdown'!W:W,$B3,'Executive Pay Breakdown'!Y:Y) -> 2472763 | O3: =SUMIF('Executive Pay Breakdown'!AA:AA,$B3,'Executive Pay Breakdown'!AC:AC) -> 2131268
B4: Peter Zaffino | C4: American International Group | D4: =K4-O4 -> 62693740 | E4: =K4/O4-1 -> 4.9676276 | F4: {=INDEX('Key Findings'!BC:BC,MATCH(C4,'Key Findings'!B:B,0))-INDEX('Key Findings'!BG:BG,MATCH(C4,'Key Findings'!B:B,0))} -> 17800 | G4: {=INDEX('Key Findings'!BC:BC,MATCH(C4,'Key Findings'!B:B,0))/INDEX('Key Findings'!BG:BG,MATCH(C4,'Key Findings'!B:B,0))-1} -> 0.2679109 | I4: =SUMIF('Executive Pay Breakdown'!K:K,$B4,'Executive Pay Breakdown'!M:M)+SUMIF('Executive Pay Breakdown'!O:O,$B4,'Executive Pay Breakdown'!Q:Q)+SUMIF('Executive Pay Breakdown'!S:S,$B4,'Executive Pay Breakdown'!U:U)+SUMIF('Executive Pay Breakdown'!W:W,$B4,'Executive Pay Breakdown'!Y:Y)+SUMIF('Executive Pay Breakdown'!AA:AA,$B4,'Executive Pay Breakdown'!AC:AC) -> 152295198 | K4: =SUMIF('Executive Pay Breakdown'!K:K,$B4,'Executive Pay Breakdown'!M:M) -> 75314199 | L4: =SUMIF('Executive Pay Breakdown'!O:O,$B4,'Executive Pay Breakdown'!Q:Q) -> 21905220 | M4: =SUMIF('Executive Pay Breakdown'!S:S,$B4,'Executive Pay Breakdown'!U:U) -> 24066986 | N4: =SUMIF('Executive Pay Breakdown'!W:W,$B4,'Executive Pay Breakdown'!Y:Y) -> 18388334 | O4: =SUMIF('Executive Pay Breakdown'!AA:AA,$B4,'Executive Pay Breakdown'!AC:AC) -> 12620459
B5: Thomas M. Rutledge | C5: Charter Communications | D5: =K5-O5 -> 31056086 | E5: =K5/O5-1 -> 3.8071694 | F5: {=INDEX('Key Findings'!BC:BC,MATCH(C5,'Key Findings'!B:B,0))-INDEX('Key Findings'!BG:BG,MATCH(C5,'Key Findings'!B:B,0))} -> -131 | G5: {=INDEX('Key Findings'!BC:BC,MATCH(C5,'Key Findings'!B:B,0))/INDEX('Key Findings'!BG:BG,MATCH(C5,'Key Findings'!B:B,0))-1} -> -0.0023578114 | I5: =SUMIF('Executive Pay Breakdown'!K:K,$B5,'Executive Pay Breakdown'!M:M)+SUMIF('Executive Pay Breakdown'!O:O,$B5,'Executive Pay Breakdown'!Q:Q)+SUMIF('Executive Pay Breakdown'!S:S,$B5,'Executive Pay Breakdown'!U:U)+SUMIF('Executive Pay Breakdown'!W:W,$B5,'Executive Pay Breakdown'!Y:Y)+SUMIF('Executive Pay Breakdown'!AA:AA,$B5,'Executive Pay Breakdown'!AC:AC) -> 136821183 | K5: =SUMIF('Executive Pay Breakdown'!K:K,$B5,'Executive Pay Breakdown'!M:M) -> 39213350 | L5: =SUMIF('Executive Pay Breakdown'!O:O,$B5,'Executive Pay Breakdown'!Q:Q) -> 41860263 | M5: =SUMIF('Executive Pay Breakdown'!S:S,$B5,'Executive Pay Breakdown'!U:U) -> 38846705 | N5: =SUMIF('Executive Pay Breakdown'!W:W,$B5,'Executive Pay Breakdown'!Y:Y) -> 8743601 | O5: =SUMIF('Executive Pay Breakdown'!AA:AA,$B5,'Executive Pay Breakdown'!AC:AC) -> 8157264
B6: Garrick J. Rochow | C6: CMS Energy | D6: =K6-O6 -> 6851282 | E6: =K6/O6-1 -> 3.6935887 | F6: {=INDEX('Key Findings'!BC:BC,MATCH(C6,'Key Findings'!B:B,0))-INDEX('Key Findings'!BG:BG,MATCH(C6,'Key Findings'!B:B,0))} -> 16864 | G6: {=INDEX('Key Findings'!BC:BC,MATCH(C6,'Key Findings'!B:B,0))/INDEX('Key Findings'!BG:BG,MATCH(C6,'Key Findings'!B:B,0))-1} -> 0.15890695 | I6: =SUMIF('Executive Pay Breakdown'!K:K,$B6,'Executive Pay Breakdown'!M:M)+SUMIF('Executive Pay Breakdown'!O:O,$B6,'Executive Pay Breakdown'!Q:Q)+SUMIF('Executive Pay Breakdown'!S:S,$B6,'Executive Pay Breakdown'!U:U)+SUMIF('Executive Pay Breakdown'!W:W,$B6,'Executive Pay Breakdown'!Y:Y)+SUMIF('Executive Pay Breakdown'!AA:AA,$B6,'Executive Pay Breakdown'!AC:AC) -> 22050819 | K6: =SUMIF('Executive Pay Breakdown'!K:K,$B6,'Executive Pay Breakdown'!M:M) -> 8706194 | L6: =SUMIF('Executive Pay Breakdown'!O:O,$B6,'Executive Pay Breakdown'!Q:Q) -> 6871068 | M6: =SUMIF('Executive Pay Breakdown'!S:S,$B6,'Executive Pay Breakdown'!U:U) -> 2615131 | N6: =SUMIF('Executive Pay Breakdown'!W:W,$B6,'Executive Pay Breakdown'!Y:Y) -> 2003514 | O6: =SUMIF('Executive Pay Breakdown'!AA:AA,$B6,'Executive Pay Breakdown'!AC:AC) -> 1854912
B7: Bob Frenzel | C7: Xcel Energy | D7: =K7-O7 -> 7994414 | E7: =K7/O7-1 -> 3.439693 | F7: {=INDEX('Key Findings'!BC:BC,MATCH(C7,'Key Findings'!B:B,0))-INDEX('Key Findings'!BG:BG,MATCH(C7,'Key Findings'!B:B,0))} -> 10905 | G7: {=INDEX('Key Findings'!BC:BC,MATCH(C7,'Key Findings'!B:B,0))/INDEX('Key Findings'!BG:BG,MATCH(C7,'Key Findings'!B:B,0))-1} -> 0.10009546 | I7: =SUMIF('Executive Pay Breakdown'!K:K,$B7,'Executive Pay Breakdown'!M:M)+SUMIF('Executive Pay Breakdown'!O:O,$B7,'Executive Pay Breakdown'!Q:Q)+SUMIF('Executive Pay Breakdown'!S:S,$B7,'Executive Pay Breakdown'!U:U)+SUMIF('Executive Pay Breakdown'!W:W,$B7,'Executive Pay Breakdown'!Y:Y)+SUMIF('Executive Pay Breakdown'!AA:AA,$B7,'Executive Pay Breakdown'!AC:AC) -> 28150026 | K7: =SUMIF('Executive Pay Breakdown'!K:K,$B7,'Executive Pay Breakdown'!M:M) -> 10318579 | L7: =SUMIF('Executive Pay Breakdown'!O:O,$B7,'Executive Pay Breakdown'!Q:Q) -> 8350364 | M7: =SUMIF('Executive Pay Breakdown'!S:S,$B7,'Executive Pay Breakdown'!U:U) -> 4052934 | N7: =SUMIF('Executive Pay Breakdown'!W:W,$B7,'Executive Pay Breakdown'!Y:Y) -> 3103984 | O7: =SUMIF('Executive Pay Breakdown'!AA:AA,$B7,'Executive Pay Breakdown'!AC:AC) -> 2324165
B8: Brian D. Chambers | C8: Owens Corning | D8: =K8-O8 -> 8329464 | E8: =K8/O8-1 -> 3.1427314 | F8: {=INDEX('Key Findings'!BC:BC,MATCH(C8,'Key Findings'!B:B,0))-INDEX('Key Findings'!BG:BG,MATCH(C8,'Key Findings'!B:B,0))} -> -191 | G8: {=INDEX('Key Findings'!BC:BC,MATCH(C8,'Key Findings'!B:B,0))/INDEX('Key Findings'!BG:BG,MATCH(C8,'Key Findings'!B:B,0))-1} -> -0.0031524915 | I8: =SUMIF('Executive Pay Breakdown'!K:K,$B8,'Executive Pay Breakdown'!M:M)+SUMIF('Executive Pay Breakdown'!O:O,$B8,'Executive Pay Breakdown'!Q:Q)+SUMIF('Executive Pay Breakdown'!S:S,$B8,'Executive Pay Breakdown'!U:U)+SUMIF('Executive Pay Breakdown'!W:W,$B8,'Executive Pay Breakdown'!Y:Y)+SUMIF('Executive Pay Breakdown'!AA:AA,$B8,'Executive Pay Breakdown'!AC:AC) -> 37048505 | K8: =SUMIF('Executive Pay Breakdown'!K:K,$B8,'Executive Pay Breakdown'!M:M) -> 10979854 | L8: =SUMIF('Executive Pay Breakdown'!O:O,$B8,'Executive Pay Breakdown'!Q:Q) -> 9782143 | M8: =SUMIF('Executive Pay Breakdown'!S:S,$B8,'Executive Pay Breakdown'!U:U) -> 7549789 | N8: =SUMIF('Executive Pay Breakdown'!W:W,$B8,'Executive Pay Breakdown'!Y:Y) -> 6086329 | O8: =SUMIF('Executive Pay Breakdown'!AA:AA,$B8,'Executive Pay Breakdown'!AC:AC) -> 2650390
B9: Timothy P. Cawley | C9: Consolidated Edison | D9: =K9-O9 -> 7206643 | E9: =K9/O9-1 -> 3.0208249 | F9: {=INDEX('Key Findings'!BC:BC,MATCH(C9,'Key Findings'!B:B,0))-INDEX('Key Findings'!BG:BG,MATCH(C9,'Key Findings'!B:B,0))} -> 30439 | G9: {=INDEX('Key Findings'!BC:BC,MATCH(C9,'Key Findings'!B:B,0))/INDEX('Key Findings'!BG:BG,MATCH(C9,'Key Findings'!B:B,0))-1} -> 0.2859384 | I9: =SUMIF('Executive Pay Breakdown'!K:K,$B9,'Executive Pay Breakdown'!M:M)+SUMIF('Executive Pay Breakdown'!O:O,$B9,'Executive Pay Breakdown'!Q:Q)+SUMIF('Executive Pay Breakdown'!S:S,$B9,'Executive Pay Breakdown'!U:U)+SUMIF('Executive Pay Breakdown'!W:W,$B9,'Executive Pay Breakdown'!Y:Y)+SUMIF('Executive Pay Breakdown'!AA:AA,$B9,'Executive Pay Breakdown'!AC:AC) -> 26212426 | K9: =SUMIF('Executive Pay Breakdown'!K:K,$B9,'Executive Pay Breakdown'!M:M) -> 9592297 | L9: =SUMIF('Executive Pay Breakdown'!O:O,$B9,'Executive Pay Breakdown'!Q:Q) -> 8841587 | M9: =SUMIF('Executive Pay Breakdown'!S:S,$B9,'Executive Pay Breakdown'!U:U) -> 2766656 | N9: =SUMIF('Executive Pay Breakdown'!W:W,$B9,'Executive Pay Breakdown'!Y:Y) -> 2626232 | O9: =SUMIF('Executive Pay Breakdown'!AA:AA,$B9,'Executive Pay Breakdown'!AC:AC) -> 2385654
B10: Christophe Beck | C10: Ecolab | D10: =K10-O10 -> 6335022 | E10: =K10/O10-1 -> 2.6557516 | F10: {=INDEX('Key Findings'!BC:BC,MATCH(C10,'Key Findings'!B:B,0))-INDEX('Key Findings'!BG:BG,MATCH(C10,'Key Findings'!B:B,0))} -> 1444 | G10: {=INDEX('Key Findings'!BC:BC,MATCH(C10,'Key Findings'!B:B,0))/INDEX('Key Findings'!BG:BG,MATCH(C10,'Key Findings'!B:B,0))-1} -> 0.02660035 | I10: =SUMIF('Executive Pay Breakdown'!K:K,$B10,'Executive Pay Breakdown'!M:M)+SUMIF('Executive Pay Breakdown'!O:O,$B10,'Executive Pay Breakdown'!Q:Q)+SUMIF('Executive Pay Breakdown'!S:S,$B10,'Executive Pay Breakdown'!U:U)+SUMIF('Executive Pay Breakdown'!W:W,$B10,'Executive Pay Breakdown'!Y:Y)+SUMIF('Executive Pay Breakdown'!AA:AA,$B10,'Executive Pay Breakdown'!AC:AC) -> 30815796 | K10: =SUMIF('Executive Pay Breakdown'!K:K,$B10,'Executive Pay Breakdown'!M:M) -> 8720419 | L10: =SUMIF('Executive Pay Breakdown'!O:O,$B10,'Executive Pay Breakdown'!Q:Q) -> 8365888 | M10: =SUMIF('Executive Pay Breakdown'!S:S,$B10,'Executive Pay Breakdown'!U:U) -> 6445060 | N10: =SUMIF('Executive Pay Breakdown'!W:W,$B10,'Executive Pay Breakdown'!Y:Y) -> 4899032 | O10: =SUMIF('Executive Pay Breakdown'!AA:AA,$B10,'Executive Pay Breakdown'!AC:AC) -> 2385397
B11: James D. Farley Jr. | C11: Ford Motor | D11: =K11-O11 -> 15135558 | E11: =K11/O11-1 -> 2.5826006 | F11: {=INDEX('Key Findings'!BC:BC,MATCH(C11,'Key Findings'!B:B,0))-INDEX('Key Findings'!BG:BG,MATCH(C11,'Key Findings'!B:B,0))} -> 10375 | G11: {=INDEX('Key Findings'!BC:BC,MATCH(C11,'Key Findings'!B:B,0))/INDEX('Key Findings'!BG:BG,MATCH(C11,'Key Findings'!B:B,0))-1} -> 0.16131289 | I11: =SUMIF('Executive Pay Breakdown'!K:K,$B11,'Executive Pay Breakdown'!M:M)+SUMIF('Executive Pay Breakdown'!O:O,$B11,'Executive Pay Breakdown'!Q:Q)+SUMIF('Executive Pay Breakdown'!S:S,$B11,'Executive Pay Breakdown'!U:U)+SUMIF('Executive Pay Breakdown'!W:W,$B11,'Executive Pay Breakdown'!Y:Y)+SUMIF('Executive Pay Breakdown'!AA:AA,$B11,'Executive Pay Breakdown'!AC:AC) -> 69833441 | K11: =SUMIF('Executive Pay Breakdown'!K:K,$B11,'Executive Pay Breakdown'!M:M) -> 20996146 | L11: =SUMIF('Executive Pay Breakdown'!O:O,$B11,'Executive Pay Breakdown'!Q:Q) -> 22813174 | M11: =SUMIF('Executive Pay Breakdown'!S:S,$B11,'Executive Pay Breakdown'!U:U) -> 11802054 | N11: =SUMIF('Executive Pay Breakdown'!W:W,$B11,'Executive Pay Breakdown'!Y:Y) -> 8361479 | O11: =SUMIF('Executive Pay Breakdown'!AA:AA,$B11,'Executive Pay Breakdown'!AC:AC) -> 5860588
B12: John W. Ketchum | C12: NextEra Energy | D12: =K12-O12 -> 12436260 | E12: =K12/O12-1 -> 2.4982096 | F12: {=INDEX('Key Findings'!BC:BC,MATCH(C12,'Key Findings'!B:B,0))-INDEX('Key Findings'!BG:BG,MATCH(C12,'Key Findings'!B:B,0))} -> 16081 | G12: {=INDEX('Key Findings'!BC:BC,MATCH(C12,'Key Findings'!B:B,0))/INDEX('Key Findings'!BG:BG,MATCH(C12,'Key Findings'!B:B,0))-1} -> 0.12827344 | I12: =SUMIF('Executive Pay Breakdown'!K:K,$B12,'Executive Pay Breakdown'!M:M)+SUMIF('Executive Pay Breakdown'!O:O,$B12,'Executive Pay Breakdown'!Q:Q)+SUMIF('Executive Pay Breakdown'!S:S,$B12,'Executive Pay Breakdown'!U:U)+SUMIF('Executive Pay Breakdown'!W:W,$B12,'Executive Pay Breakdown'!Y:Y)+SUMIF('Executive Pay Breakdown'!AA:AA,$B12,'Executive Pay Breakdown'!AC:AC) -> 51569148 | K12: =SUMIF('Executive Pay Breakdown'!K:K,$B12,'Executive Pay Breakdown'!M:M) -> 17414329 | L12: =SUMIF('Executive Pay Breakdown'!O:O,$B12,'Executive Pay Breakdown'!Q:Q) -> 15507153 | M12: =SUMIF('Executive Pay Breakdown'!S:S,$B12,'Executive Pay Breakdown'!U:U) -> 7518782 | N12: =SUMIF('Executive Pay Breakdown'!W:W,$B12,'Executive Pay Breakdown'!Y:Y) -> 6150815 | O12: =SUMIF('Executive Pay Breakdown'!AA:AA,$B12,'Executive Pay Breakdown'!AC:AC) -> 4978069
B15: Gary Swidler | C15: Match Group | I15: =SUMIF('Executive Pay Breakdown'!K:K,$B15,'Executive Pay Breakdown'!M:M)+SUMIF('Executive Pay Breakdown'!O:O,$B15,'Executive Pay Breakdown'!Q:Q)+SUMIF('Executive Pay Breakdown'!S:S,$B15,'Executive Pay Breakdown'!U:U)+SUMIF('Executive Pay Breakdown'!W:W,$B15,'Executive Pay Breakdown'!Y:Y)+SUMIF('Executive Pay Breakdown'!AA:AA,$B15,'Executive Pay Breakdown'!AC:AC) -> 56837602 | K15: =SUMIF('Executive Pay Breakdown'!K:K,$B15,'Executive Pay Breakdown'!M:M) -> 23677633 | L15: =SUMIF('Executive Pay Breakdown'!O:O,$B15,'Executive Pay Breakdown'!Q:Q) -> 15367669 | M15: =SUMIF('Executive Pay Breakdown'!S:S,$B15,'Executive Pay Breakdown'!U:U) -> 8730701 | N15: =SUMIF('Executive Pay Breakdown'!W:W,$B15,'Executive Pay Breakdown'!Y:Y) -> 5404149 | O15: =SUMIF('Executive Pay Breakdown'!AA:AA,$B15,'Executive Pay Breakdown'!AC:AC) -> 3657450
B16: Jared F. Sine | C16: Match Group | I16: =SUMIF('Executive Pay Breakdown'!K:K,$B16,'Executive Pay Breakdown'!M:M)+SUMIF('Executive Pay Breakdown'!O:O,$B16,'Executive Pay Breakdown'!Q:Q)+SUMIF('Executive Pay Breakdown'!S:S,$B16,'Executive Pay Breakdown'!U:U)+SUMIF('Executive Pay Breakdown'!W:W,$B16,'Executive Pay Breakdown'!Y:Y)+SUMIF('Executive Pay Breakdown'!AA:AA,$B16,'Executive Pay Breakdown'!AC:AC) -> 33531913 | K16: =SUMIF('Executive Pay Breakdown'!K:K,$B16,'Executive Pay Breakdown'!M:M) -> 8565840 | L16: =SUMIF('Executive Pay Breakdown'!O:O,$B16,'Executive Pay Breakdown'!Q:Q) -> 16993744 | M16: =SUMIF('Executive Pay Breakdown'!S:S,$B16,'Executive Pay Breakdown'!U:U) -> 3609960 | N16: =SUMIF('Executive Pay Breakdown'!W:W,$B16,'Executive Pay Breakdown'!Y:Y) -> 2504122 | O16: =SUMIF('Executive Pay Breakdown'!AA:AA,$B16,'Executive Pay Breakdown'!AC:AC) -> 1858247
B17: R. Perreault | C17: UGI | I17: =SUMIF('Executive Pay Breakdown'!K:K,$B17,'Executive Pay Breakdown'!M:M)+SUMIF('Executive Pay Breakdown'!O:O,$B17,'Executive Pay Breakdown'!Q:Q)+SUMIF('Executive Pay Breakdown'!S:S,$B17,'Executive Pay Breakdown'!U:U)+SUMIF('Executive Pay Breakdown'!W:W,$B17,'Executive Pay Breakdown'!Y:Y)+SUMIF('Executive Pay Breakdown'!AA:AA,$B17,'Executive Pay Breakdown'!AC:AC) -> 16723757 | K17: =SUMIF('Executive Pay Breakdown'!K:K,$B17,'Executive Pay Breakdown'!M:M) -> 6060694 | L17: =SUMIF('Executive Pay Breakdown'!O:O,$B17,'Executive Pay Breakdown'!Q:Q) -> 4107789 | M17: =SUMIF('Executive Pay Breakdown'!S:S,$B17,'Executive Pay Breakdown'!U:U) -> 2385873 | N17: =SUMIF('Executive Pay Breakdown'!W:W,$B17,'Executive Pay Breakdown'!Y:Y) -> 2272717 | O17: =SUMIF('Executive Pay Breakdown'!AA:AA,$B17,'Executive Pay Breakdown'!AC:AC) -> 1896684
B18: Vincent Sorgi | C18: PPL | I18: =SUMIF('Executive Pay Breakdown'!K:K,$B18,'Executive Pay Breakdown'!M:M)+SUMIF('Executive Pay Breakdown'!O:O,$B18,'Executive Pay Breakdown'!Q:Q)+SUMIF('Executive Pay Breakdown'!S:S,$B18,'Executive Pay Breakdown'!U:U)+SUMIF('Executive Pay Breakdown'!W:W,$B18,'Executive Pay Breakdown'!Y:Y)+SUMIF('Executive Pay Breakdown'!AA:AA,$B18,'Executive Pay Breakdown'!AC:AC) -> 35944103 | K18: =SUMIF('Executive Pay Breakdown'!K:K,$B18,'Executive Pay Breakdown'!M:M) -> 9146575 | L18: =SUMIF('Executive Pay Breakdown'!O:O,$B18,'Executive Pay Breakdown'!Q:Q) -> 11356481 | M18: =SUMIF('Executive Pay Breakdown'!S:S,$B18,'Executive Pay Breakdown'!U:U) -> 7774443 | N18: =SUMIF('Executive Pay Breakdown'!W:W,$B18,'Executive Pay Breakdown'!Y:Y) -> 4731409 | O18: =SUMIF('Executive Pay Breakdown'!AA:AA,$B18,'Executive Pay Breakdown'!AC:AC) -> 2935195
B19: Gregory P. Lewis | C19: Honeywell International | I19: =SUMIF('Executive Pay Breakdown'!K:K,$B19,'Executive Pay Breakdown'!M:M)+SUMIF('Executive Pay Breakdown'!O:O,$B19,'Executive Pay Breakdown'!Q:Q)+SUMIF('Executive Pay Breakdown'!S:S,$B19,'Executive Pay Breakdown'!U:U)+SUMIF('Executive Pay Breakdown'!W:W,$B19,'Executive Pay Breakdown'!Y:Y)+SUMIF('Executive Pay Breakdown'!AA:AA,$B19,'Executive Pay Breakdown'!AC:AC) -> 32441237 | K19: =SUMIF('Executive Pay Breakdown'!K:K,$B19,'Executive Pay Breakdown'!M:M) -> 7979076 | L19: =SUMIF('Executive Pay Breakdown'!O:O,$B19,'Executive Pay Breakdown'!Q:Q) -> 8379703 | M19: =SUMIF('Executive Pay Breakdown'!S:S,$B19,'Executive Pay Breakdown'!U:U) -> 6831332 | N19: =SUMIF('Executive Pay Breakdown'!W:W,$B19,'Executive Pay Breakdown'!Y:Y) -> 6644633 | O19: =SUMIF('Executive Pay Breakdown'!AA:AA,$B19,'Executive Pay Breakdown'!AC:AC) -> 2606493
B20: Steven E. Strah | C20: FirstEnergy | I20: =SUMIF('Executive Pay Breakdown'!K:K,$B20,'Executive Pay Breakdown'!M:M)+SUMIF('Executive Pay Breakdown'!O:O,$B20,'Executive Pay Breakdown'!Q:Q)+SUMIF('Executive Pay Breakdown'!S:S,$B20,'Executive Pay Breakdown'!U:U)+SUMIF('Executive Pay Breakdown'!W:W,$B20,'Executive Pay Breakdown'!Y:Y)+SUMIF('Executive Pay Breakdown'!AA:AA,$B20,'Executive Pay Breakdown'!AC:AC) -> 26298713 | K20: =SUMIF('Executive Pay Breakdown'!K:K,$B20,'Executive Pay Breakdown'!M:M) -> 8553297 | L20: =SUMIF('Executive Pay Breakdown'!O:O,$B20,'Executive Pay Breakdown'!Q:Q) -> 8837858 | M20: =SUMIF('Executive Pay Breakdown'!S:S,$B20,'Executive Pay Breakdown'!U:U) -> 3264629 | N20: =SUMIF('Executive Pay Breakdown'!W:W,$B20,'Executive Pay Breakdown'!Y:Y) -> 2844406 | O20: =SUMIF('Executive Pay Breakdown'!AA:AA,$B20,'Executive Pay Breakdown'!AC:AC) -> 2798523
B21: John O. Larsen | C21: Alliant Energy | I21: =SUMIF('Executive Pay Breakdown'!K:K,$B21,'Executive Pay Breakdown'!M:M)+SUMIF('Executive Pay Breakdown'!O:O,$B21,'Executive Pay Breakdown'!Q:Q)+SUMIF('Executive Pay Breakdown'!S:S,$B21,'Executive Pay Breakdown'!U:U)+SUMIF('Executive Pay Breakdown'!W:W,$B21,'Executive Pay Breakdown'!Y:Y)+SUMIF('Executive Pay Breakdown'!AA:AA,$B21,'Executive Pay Breakdown'!AC:AC) -> 38829320 | K21: =SUMIF('Executive Pay Breakdown'!K:K,$B21,'Executive Pay Breakdown'!M:M) -> 7286977 | L21: =SUMIF('Executive Pay Breakdown'!O:O,$B21,'Executive Pay Breakdown'!Q:Q) -> 10449260 | M21: =SUMIF('Executive Pay Breakdown'!S:S,$B21,'Executive Pay Breakdown'!U:U) -> 11020134 | N21: =SUMIF('Executive Pay Breakdown'!W:W,$B21,'Executive Pay Breakdown'!Y:Y) -> 7619999 | O21: =SUMIF('Executive Pay Breakdown'!AA:AA,$B21,'Executive Pay Breakdown'!AC:AC) -> 2452950
B22: Stuart A. Arbuckle | C22: Vertex Pharmaceuticals | I22: =SUMIF('Executive Pay Breakdown'!K:K,$B22,'Executive Pay Breakdown'!M:M)+SUMIF('Executive Pay Breakdown'!O:O,$B22,'Executive Pay Breakdown'!Q:Q)+SUMIF('Executive Pay Breakdown'!S:S,$B22,'Executive Pay Breakdown'!U:U)+SUMIF('Executive Pay Breakdown'!W:W,$B22,'Executive Pay Breakdown'!Y:Y)+SUMIF('Executive Pay Breakdown'!AA:AA,$B22,'Executive Pay Breakdown'!AC:AC) -> 42298850 | K22: =SUMIF('Executive Pay Breakdown'!K:K,$B22,'Executive Pay Breakdown'!M:M) -> 14999106 | L22: =SUMIF('Executive Pay Breakdown'!O:O,$B22,'Executive Pay Breakdown'!Q:Q) -> 7810141 | M22: =SUMIF('Executive Pay Breakdown'!S:S,$B22,'Executive Pay Breakdown'!U:U) -> 7282978 | N22: =SUMIF('Executive Pay Breakdown'!W:W,$B22,'Executive Pay Breakdown'!Y:Y) -> 6859533 | O22: =SUMIF('Executive Pay Breakdown'!AA:AA,$B22,'Executive Pay Breakdown'!AC:AC) -> 5347092
B23: J. Kevin Akers | C23: Atmos Energy | I23: =SUMIF('Executive Pay Breakdown'!K:K,$B23,'Executive Pay Breakdown'!M:M)+SUMIF('Executive Pay Breakdown'!O:O,$B23,'Executive Pay Breakdown'!Q:Q)+SUMIF('Executive Pay Breakdown'!S:S,$B23,'Executive Pay Breakdown'!U:U)+SUMIF('Executive Pay Breakdown'!W:W,$B23,'Executive Pay Breakdown'!Y:Y)+SUMIF('Executive Pay Breakdown'!AA:AA,$B23,'Executive Pay Breakdown'!AC:AC) -> 30725684 | K23: =SUMIF('Executive Pay Breakdown'!K:K,$B23,'Executive Pay Breakdown'!M:M) -> 4839562 | L23: =SUMIF('Executive Pay Breakdown'!O:O,$B23,'Executive Pay Breakdown'!Q:Q) -> 6467314 | M23: =SUMIF('Executive Pay Breakdown'!S:S,$B23,'Executive Pay Breakdown'!U:U) -> 9826659 | N23: =SUMIF('Executive Pay Breakdown'!W:W,$B23,'Executive Pay Breakdown'!Y:Y) -> 7855539 | O23: =SUMIF('Executive Pay Breakdown'!AA:AA,$B23,'Executive Pay Breakdown'!AC:AC) -> 1736610
B24: James H. Gallegos | C24: Alliant Energy American Water Works | I24: =SUMIF('Executive Pay Breakdown'!K:K,$B24,'Executive Pay Breakdown'!M:M)+SUMIF('Executive Pay Breakdown'!O:O,$B24,'Executive Pay Breakdown'!Q:Q)+SUMIF('Executive Pay Breakdown'!S:S,$B24,'Executive Pay Breakdown'!U:U)+SUMIF('Executive Pay Breakdown'!W:W,$B24,'Executive Pay Breakdown'!Y:Y)+SUMIF('Executive Pay Breakdown'!AA:AA,$B24,'Executive Pay Breakdown'!AC:AC) -> 12826091 | K24: =SUMIF('Executive Pay Breakdown'!K:K,$B24,'Executive Pay Breakdown'!M:M) -> 4916509 | L24: =SUMIF('Executive Pay Breakdown'!O:O,$B24,'Executive Pay Breakdown'!Q:Q) -> 2129552 | M24: =SUMIF('Executive Pay Breakdown'!S:S,$B24,'Executive Pay Breakdown'!U:U) -> 2062273 | N24: =SUMIF('Executive Pay Breakdown'!W:W,$B24,'Executive Pay Breakdown'!Y:Y) -> 1928911 | O24: =SUMIF('Executive Pay Breakdown'!AA:AA,$B24,'Executive Pay Breakdown'!AC:AC) -> 1788846
B25: John W. Swieringa | C25: DISH Network | I25: =SUMIF('Executive Pay Breakdown'!K:K,$B25,'Executive Pay Breakdown'!M:M)+SUMIF('Executive Pay Breakdown'!O:O,$B25,'Executive Pay Breakdown'!Q:Q)+SUMIF('Executive Pay Breakdown'!S:S,$B25,'Executive Pay Breakdown'!U:U)+SUMIF('Executive Pay Breakdown'!W:W,$B25,'Executive Pay Breakdown'!Y:Y)+SUMIF('Executive Pay Breakdown'!AA:AA,$B25,'Executive Pay Breakdown'!AC:AC) -> 14593228 | K25: =SUMIF('Executive Pay Breakdown'!K:K,$B25,'Executive Pay Breakdown'!M:M) -> 7926917 | L25: =SUMIF('Executive Pay Breakdown'!O:O,$B25,'Executive Pay Breakdown'!Q:Q) -> 1724889 | M25: =SUMIF('Executive Pay Breakdown'!S:S,$B25,'Executive Pay Breakdown'!U:U) -> 1000290 | N25: =SUMIF('Executive Pay Breakdown'!W:W,$B25,'Executive Pay Breakdown'!Y:Y) -> 1018673 | O25: =SUMIF('Executive Pay Breakdown'!AA:AA,$B25,'Executive Pay Breakdown'!AC:AC) -> 2922459
B26: Andrew S. Marsh | C26: Entergy | I26: =SUMIF('Executive Pay Breakdown'!K:K,$B26,'Executive Pay Breakdown'!M:M)+SUMIF('Executive Pay Breakdown'!O:O,$B26,'Executive Pay Breakdown'!Q:Q)+SUMIF('Executive Pay Breakdown'!S:S,$B26,'Executive Pay Breakdown'!U:U)+SUMIF('Executive Pay Breakdown'!W:W,$B26,'Executive Pay Breakdown'!Y:Y)+SUMIF('Executive Pay Breakdown'!AA:AA,$B26,'Executive Pay Breakdown'!AC:AC) -> 24296290 | K26: =SUMIF('Executive Pay Breakdown'!K:K,$B26,'Executive Pay Breakdown'!M:M) -> 6861760 | L26: =SUMIF('Executive Pay Breakdown'!O:O,$B26,'Executive Pay Breakdown'!Q:Q) -> 3889327 | M26: =SUMIF('Executive Pay Breakdown'!S:S,$B26,'Executive Pay Breakdown'!U:U) -> 6007055 | N26: =SUMIF('Executive Pay Breakdown'!W:W,$B26,'Executive Pay Breakdown'!Y:Y) -> 4934063 | O26: =SUMIF('Executive Pay Breakdown'!AA:AA,$B26,'Executive Pay Breakdown'!AC:AC) -> 2604085
... B74: Robert Hoglund | C74: Consolidated Edison | I74: =SUMIF('Executive Pay Breakdown'!K:K,$B74,'Executive Pay Breakdown'!M:M)+SUMIF('Executive Pay Breakdown'!O:O,$B74,'Executive Pay Breakdown'!Q:Q)+SUMIF('Executive Pay Breakdown'!S:S,$B74,'Executive Pay Breakdown'!U:U)+SUMIF('Executive Pay Breakdown'!W:W,$B74,'Executive Pay Breakdown'!Y:Y)+SUMIF('Executive Pay Breakdown'!AA:AA,$B74,'Executive Pay Breakdown'!AC:AC) -> 16166691 | K74: =SUMIF('Executive Pay Breakdown'!K:K,$B74,'Executive Pay Breakdown'!M:M) -> 3643718 | L74: =SUMIF('Executive Pay Breakdown'!O:O,$B74,'Executive Pay Breakdown'!Q:Q) -> 3449763 | M74: =SUMIF('Executive Pay Breakdown'!S:S,$B74,'Executive Pay Breakdown'!U:U) -> 3061602 | N74: =SUMIF('Executive Pay Breakdown'!W:W,$B74,'Executive Pay Breakdown'!Y:Y) -> 3443888 | O74: =SUMIF('Executive Pay Breakdown'!AA:AA,$B74,'Executive Pay Breakdown'!AC:AC) -> 2567720
A75: Yes | B75: Reed Hastings | C75: Netflix | I75: =SUMIF('Executive Pay Breakdown'!K:K,$B75,'Executive Pay Breakdown'!M:M)+SUMIF('Executive Pay Breakdown'!O:O,$B75,'Executive Pay Breakdown'!Q:Q)+SUMIF('Executive Pay Breakdown'!S:S,$B75,'Executive Pay Breakdown'!U:U)+SUMIF('Executive Pay Breakdown'!W:W,$B75,'Executive Pay Breakdown'!Y:Y)+SUMIF('Executive Pay Breakdown'!AA:AA,$B75,'Executive Pay Breakdown'!AC:AC) -> 209780532 | K75: =SUMIF('Executive Pay Breakdown'!K:K,$B75,'Executive Pay Breakdown'!M:M) -> 51073237 | L75: =SUMIF('Executive Pay Breakdown'!O:O,$B75,'Executive Pay Breakdown'!Q:Q) -> 40823725 | M75: =SUMIF('Executive Pay Breakdown'!S:S,$B75,'Executive Pay Breakdown'!U:U) -> 43226024 | N75: =SUMIF('Executive Pay Breakdown'!W:W,$B75,'Executive Pay Breakdown'!Y:Y) -> 38577129 | O75: =SUMIF('Executive Pay Breakdown'!AA:AA,$B75,'Executive Pay Breakdown'!AC:AC) -> 36080417
B76: Robert J. Durian | C76: Alliant Energy | I76: =SUMIF('Executive Pay Breakdown'!K:K,$B76,'Executive Pay Breakdown'!M:M)+SUMIF('Executive Pay Breakdown'!O:O,$B76,'Executive Pay Breakdown'!Q:Q)+SUMIF('Executive Pay Breakdown'!S:S,$B76,'Executive Pay Breakdown'!U:U)+SUMIF('Executive Pay Breakdown'!W:W,$B76,'Executive Pay Breakdown'!Y:Y)+SUMIF('Executive Pay Breakdown'!AA:AA,$B76,'Executive Pay Breakdown'!AC:AC) -> 11169128 | K76: =SUMIF('Executive Pay Breakdown'!K:K,$B76,'Executive Pay Breakdown'!M:M) -> 2580416 | L76: =SUMIF('Executive Pay Breakdown'!O:O,$B76,'Executive Pay Breakdown'!Q:Q) -> 2329735 | M76: =SUMIF('Executive Pay Breakdown'!S:S,$B76,'Executive Pay Breakdown'!U:U) -> 2332855 | N76: =SUMIF('Executive Pay Breakdown'!W:W,$B76,'Executive Pay Breakdown'!Y:Y) -> 2088964 | O76: =SUMIF('Executive Pay Breakdown'!AA:AA,$B76,'Executive Pay Breakdown'!AC:AC) -> 1837158
B77: Trevor I. Mihalik | C77: Sempra Energy | I77: =SUMIF('Executive Pay Breakdown'!K:K,$B77,'Executive Pay Breakdown'!M:M)+SUMIF('Executive Pay Breakdown'!O:O,$B77,'Executive Pay Breakdown'!Q:Q)+SUMIF('Executive Pay Breakdown'!S:S,$B77,'Executive Pay Breakdown'!U:U)+SUMIF('Executive Pay Breakdown'!W:W,$B77,'Executive Pay Breakdown'!Y:Y)+SUMIF('Executive Pay Breakdown'!AA:AA,$B77,'Executive Pay Breakdown'!AC:AC) -> 28778152 | K77: =SUMIF('Executive Pay Breakdown'!K:K,$B77,'Executive Pay Breakdown'!M:M) -> 5299024 | L77: =SUMIF('Executive Pay Breakdown'!O:O,$B77,'Executive Pay Breakdown'!Q:Q) -> 7255881 | M77: =SUMIF('Executive Pay Breakdown'!S:S,$B77,'Executive Pay Breakdown'!U:U) -> 7199722 | N77: =SUMIF('Executive Pay Breakdown'!W:W,$B77,'Executive Pay Breakdown'!Y:Y) -> 5239307 | O77: =SUMIF('Executive Pay Breakdown'!AA:AA,$B77,'Executive Pay Breakdown'!AC:AC) -> 3784218
B78: Scott A. Trezise | C78: Lumen Technologies | I78: =SUMIF('Executive Pay Breakdown'!K:K,$B78,'Executive Pay Breakdown'!M:M)+SUMIF('Executive Pay Breakdown'!O:O,$B78,'Executive Pay Breakdown'!Q:Q)+SUMIF('Executive Pay Breakdown'!S:S,$B78,'Executive Pay Breakdown'!U:U)+SUMIF('Executive Pay Breakdown'!W:W,$B78,'Executive Pay Breakdown'!Y:Y)+SUMIF('Executive Pay Breakdown'!AA:AA,$B78,'Executive Pay Breakdown'!AC:AC) -> 10505161 | K78: =SUMIF('Executive Pay Breakdown'!K:K,$B78,'Executive Pay Breakdown'!M:M) -> 2586614 | L78: =SUMIF('Executive Pay Breakdown'!O:O,$B78,'Executive Pay Breakdown'!Q:Q) -> 2477083 | M78: =SUMIF('Executive Pay Breakdown'!S:S,$B78,'Executive Pay Breakdown'!U:U) -> 1849005 | N78: =SUMIF('Executive Pay Breakdown'!W:W,$B78,'Executive Pay Breakdown'!Y:Y) -> 1731155 | O78: =SUMIF('Executive Pay Breakdown'!AA:AA,$B78,'Executive Pay Breakdown'!AC:AC) -> 1861304
B79: Gregory N. Dudkin | C79: PPL | I79: =SUMIF('Executive Pay Breakdown'!K:K,$B79,'Executive Pay Breakdown'!M:M)+SUMIF('Executive Pay Breakdown'!O:O,$B79,'Executive Pay Breakdown'!Q:Q)+SUMIF('Executive Pay Breakdown'!S:S,$B79,'Executive Pay Breakdown'!U:U)+SUMIF('Executive Pay Breakdown'!W:W,$B79,'Executive Pay Breakdown'!Y:Y)+SUMIF('Executive Pay Breakdown'!AA:AA,$B79,'Executive Pay Breakdown'!AC:AC) -> 16567144 | K79: =SUMIF('Executive Pay Breakdown'!K:K,$B79,'Executive Pay Breakdown'!M:M) -> 3606120 | L79: =SUMIF('Executive Pay Breakdown'!O:O,$B79,'Executive Pay Breakdown'!Q:Q) -> 4041484 | M79: =SUMIF('Executive Pay Breakdown'!S:S,$B79,'Executive Pay Breakdown'!U:U) -> 3062093 | N79: =SUMIF('Executive Pay Breakdown'!W:W,$B79,'Executive Pay Breakdown'!Y:Y) -> 3260761 | O79: =SUMIF('Executive Pay Breakdown'!AA:AA,$B79,'Executive Pay Breakdown'!AC:AC) -> 2596686
B80: John T. Stankey | C80: AT&T | I80: =SUMIF('Executive Pay Breakdown'!K:K,$B80,'Executive Pay Breakdown'!M:M)+SUMIF('Executive Pay Breakdown'!O:O,$B80,'Executive Pay Breakdown'!Q:Q)+SUMIF('Executive Pay Breakdown'!S:S,$B80,'Executive Pay Breakdown'!U:U)+SUMIF('Executive Pay Breakdown'!W:W,$B80,'Executive Pay Breakdown'!Y:Y)+SUMIF('Executive Pay Breakdown'!AA:AA,$B80,'Executive Pay Breakdown'!AC:AC) -> 107783233 | K80: =SUMIF('Executive Pay Breakdown'!K:K,$B80,'Executive Pay Breakdown'!M:M) -> 22915526 | L80: =SUMIF('Executive Pay Breakdown'!O:O,$B80,'Executive Pay Breakdown'!Q:Q) -> 24820879 | M80: =SUMIF('Executive Pay Breakdown'!S:S,$B80,'Executive Pay Breakdown'!U:U) -> 21020917 | N80: =SUMIF('Executive Pay Breakdown'!W:W,$B80,'Executive Pay Breakdown'!Y:Y) -> 22473006 | O80: =SUMIF('Executive Pay Breakdown'!AA:AA,$B80,'Executive Pay Breakdown'!AC:AC) -> 16552905
B81: Dhiaa M. Jamil | C81: Duke Energy | I81: =SUMIF('Executive Pay Breakdown'!K:K,$B81,'Executive Pay Breakdown'!M:M)+SUMIF('Executive Pay Breakdown'!O:O,$B81,'Executive Pay Breakdown'!Q:Q)+SUMIF('Executive Pay Breakdown'!S:S,$B81,'Executive Pay Breakdown'!U:U)+SUMIF('Executive Pay Breakdown'!W:W,$B81,'Executive Pay Breakdown'!Y:Y)+SUMIF('Executive Pay Breakdown'!AA:AA,$B81,'Executive Pay Breakdown'!AC:AC) -> 23826703 | K81: =SUMIF('Executive Pay Breakdown'!K:K,$B81,'Executive Pay Breakdown'!M:M) -> 5487720 | L81: =SUMIF('Executive Pay Breakdown'!O:O,$B81,'Executive Pay Breakdown'!Q:Q) -> 5098569 | M81: =SUMIF('Executive Pay Breakdown'!S:S,$B81,'Executive Pay Breakdown'!U:U) -> 4587700 | N81: =SUMIF('Executive Pay Breakdown'!W:W,$B81,'Executive Pay Breakdown'!Y:Y) -> 4658314 | O81: =SUMIF('Executive Pay Breakdown'!AA:AA,$B81,'Executive Pay Breakdown'!AC:AC) -> 3994400
B82: Sheridan C. Swords | C82: Oneok | I82: =SUMIF('Executive Pay Breakdown'!K:K,$B82,'Executive Pay Breakdown'!M:M)+SUMIF('Executive Pay Breakdown'!O:O,$B82,'Executive Pay Breakdown'!Q:Q)+SUMIF('Executive Pay Breakdown'!S:S,$B82,'Executive Pay Breakdown'!U:U)+SUMIF('Executive Pay Breakdown'!W:W,$B82,'Executive Pay Breakdown'!Y:Y)+SUMIF('Executive Pay Breakdown'!AA:AA,$B82,'Executive Pay Breakdown'!AC:AC) -> 13047889 | K82: =SUMIF('Executive Pay Breakdown'!K:K,$B82,'Executive Pay Breakdown'!M:M) -> 2749806 | L82: =SUMIF('Executive Pay Breakdown'!O:O,$B82,'Executive Pay Breakdown'!Q:Q) -> 2952624 | M82: =SUMIF('Executive Pay Breakdown'!S:S,$B82,'Executive Pay Breakdown'!U:U) -> 2989300 | N82: =SUMIF('Executive Pay Breakdown'!W:W,$B82,'Executive Pay Breakdown'!Y:Y) -> 2351341 | O82: =SUMIF('Executive Pay Breakdown'!AA:AA,$B82,'Executive Pay Breakdown'!AC:AC) -> 2004818
B83: Albert Chao | C83: Westlake Chemical | I83: =SUMIF('Executive Pay Breakdown'!K:K,$B83,'Executive Pay Breakdown'!M:M)+SUMIF('Executive Pay Breakdown'!O:O,$B83,'Executive Pay Breakdown'!Q:Q)+SUMIF('Executive Pay Breakdown'!S:S,$B83,'Executive Pay Breakdown'!U:U)+SUMIF('Executive Pay Breakdown'!W:W,$B83,'Executive Pay Breakdown'!Y:Y)+SUMIF('Executive Pay Breakdown'!AA:AA,$B83,'Executive Pay Breakdown'!AC:AC) -> 53466338 | K83: =SUMIF('Executive Pay Breakdown'!K:K,$B83,'Executive Pay Breakdown'!M:M) -> 12242340 | L83: =SUMIF('Executive Pay Breakdown'!O:O,$B83,'Executive Pay Breakdown'!Q:Q) -> 10401407 | M83: =SUMIF('Executive Pay Breakdown'!S:S,$B83,'Executive Pay Breakdown'!U:U) -> 10927684 | N83: =SUMIF('Executive Pay Breakdown'!W:W,$B83,'Executive Pay Breakdown'!Y:Y) -> 10880451 | O83: =SUMIF('Executive Pay Breakdown'!AA:AA,$B83,'Executive Pay Breakdown'!AC:AC) -> 9014456
B84: Michael L. Moehn | C84: Ameren | I84: =SUMIF('Executive Pay Breakdown'!K:K,$B84,'Executive Pay Breakdown'!M:M)+SUMIF('Executive Pay Breakdown'!O:O,$B84,'Executive Pay Breakdown'!Q:Q)+SUMIF('Executive Pay Breakdown'!S:S,$B84,'Executive Pay Breakdown'!U:U)+SUMIF('Executive Pay Breakdown'!W:W,$B84,'Executive Pay Breakdown'!Y:Y)+SUMIF('Executive Pay Breakdown'!AA:AA,$B84,'Executive Pay Breakdown'!AC:AC) -> 20188126 | K84: =SUMIF('Executive Pay Breakdown'!K:K,$B84,'Executive Pay Breakdown'!M:M) -> 4303166 | L84: =SUMIF('Executive Pay Breakdown'!O:O,$B84,'Executive Pay Breakdown'!Q:Q) -> 4061881 | M84: =SUMIF('Executive Pay Breakdown'!S:S,$B84,'Executive Pay Breakdown'!U:U) -> 5667754 | N84: =SUMIF('Executive Pay Breakdown'!W:W,$B84,'Executive Pay Breakdown'!Y:Y) -> 2972537 | O84: =SUMIF('Executive Pay Breakdown'!AA:AA,$B84,'Executive Pay Breakdown'!AC:AC) -> 3182788
B85: Marcus V. Brown | C85: Entergy | I85: =SUMIF('Executive Pay Breakdown'!K:K,$B85,'Executive Pay Breakdown'!M:M)+SUMIF('Executive Pay Breakdown'!O:O,$B85,'Executive Pay Breakdown'!Q:Q)+SUMIF('Executive Pay Breakdown'!S:S,$B85,'Executive Pay Breakdown'!U:U)+SUMIF('Executive Pay Breakdown'!W:W,$B85,'Executive Pay Breakdown'!Y:Y)+SUMIF('Executive Pay Breakdown'!AA:AA,$B85,'Executive Pay Breakdown'!AC:AC) -> 21609120 | K85: =SUMIF('Executive Pay Breakdown'!K:K,$B85,'Executive Pay Breakdown'!M:M) -> 3975754 | L85: =SUMIF('Executive Pay Breakdown'!O:O,$B85,'Executive Pay Breakdown'!Q:Q) -> 5117061 | M85: =SUMIF('Executive Pay Breakdown'!S:S,$B85,'Executive Pay Breakdown'!U:U) -> 5150403 | N85: =SUMIF('Executive Pay Breakdown'!W:W,$B85,'Executive Pay Breakdown'!Y:Y) -> 4417412 | O85: =SUMIF('Executive Pay Breakdown'!AA:AA,$B85,'Executive Pay Breakdown'!AC:AC) -> 2948490
B86: Jacob Thaysen | C86: Agilent Technologies | I86: =SUMIF('Executive Pay Breakdown'!K:K,$B86,'Executive Pay Breakdown'!M:M)+SUMIF('Executive Pay Breakdown'!O:O,$B86,'Executive Pay Breakdown'!Q:Q)+SUMIF('Executive Pay Breakdown'!S:S,$B86,'Executive Pay Breakdown'!U:U)+SUMIF('Executive Pay Breakdown'!W:W,$B86,'Executive Pay Breakdown'!Y:Y)+SUMIF('Executive Pay Breakdown'!AA:AA,$B86,'Executive Pay Breakdown'!AC:AC) -> 16849870 | K86: =SUMIF('Executive Pay Breakdown'!K:K,$B86,'Executive Pay Breakdown'!M:M) -> 4060081 | L86: =SUMIF('Executive Pay Breakdown'!O:O,$B86,'Executive Pay Breakdown'!Q:Q) -> 3802349 | M86: =SUMIF('Executive Pay Breakdown'!S:S,$B86,'Executive Pay Breakdown'!U:U) -> 3074102 | N86: =SUMIF('Executive Pay Breakdown'!W:W,$B86,'Executive Pay Breakdown'!Y:Y) -> 2897546 | O86: =SUMIF('Executive Pay Breakdown'!AA:AA,$B86,'Executive Pay Breakdown'!AC:AC) -> 3015792
B87: Nicholas K. Akins | C87: American Electric Power | I87: =SUMIF('Executive Pay Breakdown'!K:K,$B87,'Executive Pay Breakdown'!M:M)+SUMIF('Executive Pay Breakdown'!O:O,$B87,'Executive Pay Breakdown'!Q:Q)+SUMIF('Executive Pay Breakdown'!S:S,$B87,'Executive Pay Breakdown'!U:U)+SUMIF('Executive Pay Breakdown'!W:W,$B87,'Executive Pay Breakdown'!Y:Y)+SUMIF('Executive Pay Breakdown'!AA:AA,$B87,'Executive Pay Breakdown'!AC:AC) -> 73624621 | K87: =SUMIF('Executive Pay Breakdown'!K:K,$B87,'Executive Pay Breakdown'!M:M) -> 16375508 | L87: =SUMIF('Executive Pay Breakdown'!O:O,$B87,'Executive Pay Breakdown'!Q:Q) -> 15051215 | M87: =SUMIF('Executive Pay Breakdown'!S:S,$B87,'Executive Pay Breakdown'!U:U) -> 15503434 | N87: =SUMIF('Executive Pay Breakdown'!W:W,$B87,'Executive Pay Breakdown'!Y:Y) -> 14492436 | O87: =SUMIF('Executive Pay Breakdown'!AA:AA,$B87,'Executive Pay Breakdown'!AC:AC) -> 12202028
... B103: Christopher T. Forsythe | C103: Atmos Energy | I103: =SUMIF('Executive Pay Breakdown'!K:K,$B103,'Executive Pay Breakdown'!M:M)+SUMIF('Executive Pay Breakdown'!O:O,$B103,'Executive Pay Breakdown'!Q:Q)+SUMIF('Executive Pay Breakdown'!S:S,$B103,'Executive Pay Breakdown'!U:U)+SUMIF('Executive Pay Breakdown'!W:W,$B103,'Executive Pay Breakdown'!Y:Y)+SUMIF('Executive Pay Breakdown'!AA:AA,$B103,'Executive Pay Breakdown'!AC:AC) -> 9719390 | K103: =SUMIF('Executive Pay Breakdown'!K:K,$B103,'Executive Pay Breakdown'!M:M) -> 1959099 | L103: =SUMIF('Executive Pay Breakdown'!O:O,$B103,'Executive Pay Breakdown'!Q:Q) -> 2022245 | M103: =SUMIF('Executive Pay Breakdown'!S:S,$B103,'Executive Pay Breakdown'!U:U) -> 2009733 | N103: =SUMIF('Executive Pay Breakdown'!W:W,$B103,'Executive Pay Breakdown'!Y:Y) -> 2161275 | O103: =SUMIF('Executive Pay Breakdown'!AA:AA,$B103,'Executive Pay Breakdown'!AC:AC) -> 1567038
A104: Yes | B104: William Clay Ford Jr. | C104: Ford Motor | I104: =SUMIF('Executive Pay Breakdown'!K:K,$B104,'Executive Pay Breakdown'!M:M)+SUMIF('Executive Pay Breakdown'!O:O,$B104,'Executive Pay Breakdown'!Q:Q)+SUMIF('Executive Pay Breakdown'!S:S,$B104,'Executive Pay Breakdown'!U:U)+SUMIF('Executive Pay Breakdown'!W:W,$B104,'Executive Pay Breakdown'!Y:Y)+SUMIF('Executive Pay Breakdown'!AA:AA,$B104,'Executive Pay Breakdown'!AC:AC) -> 82608490 | K104: =SUMIF('Executive Pay Breakdown'!K:K,$B104,'Executive Pay Breakdown'!M:M) -> 17302266 | L104: =SUMIF('Executive Pay Breakdown'!O:O,$B104,'Executive Pay Breakdown'!Q:Q) -> 18662706 | M104: =SUMIF('Executive Pay Breakdown'!S:S,$B104,'Executive Pay Breakdown'!U:U) -> 16046542 | N104: =SUMIF('Executive Pay Breakdown'!W:W,$B104,'Executive Pay Breakdown'!Y:Y) -> 16757250 | O104: =SUMIF('Executive Pay Breakdown'!AA:AA,$B104,'Executive Pay Breakdown'!AC:AC) -> 13839726
B105: Deanna D. Strable-Soethout | C105: Principal Financial | I105: =SUMIF('Executive Pay Breakdown'!K:K,$B105,'Executive Pay Breakdown'!M:M)+SUMIF('Executive Pay Breakdown'!O:O,$B105,'Executive Pay Breakdown'!Q:Q)+SUMIF('Executive Pay Breakdown'!S:S,$B105,'Executive Pay Breakdown'!U:U)+SUMIF('Executive Pay Breakdown'!W:W,$B105,'Executive Pay Breakdown'!Y:Y)+SUMIF('Executive Pay Breakdown'!AA:AA,$B105,'Executive Pay Breakdown'!AC:AC) -> 23286564 | K105: =SUMIF('Executive Pay Breakdown'!K:K,$B105,'Executive Pay Breakdown'!M:M) -> 4215598 | L105: =SUMIF('Executive Pay Breakdown'!O:O,$B105,'Executive Pay Breakdown'!Q:Q) -> 5690706 | M105: =SUMIF('Executive Pay Breakdown'!S:S,$B105,'Executive Pay Breakdown'!U:U) -> 5234424 | N105: =SUMIF('Executive Pay Breakdown'!W:W,$B105,'Executive Pay Breakdown'!Y:Y) -> 4692005 | O105: =SUMIF('Executive Pay Breakdown'!AA:AA,$B105,'Executive Pay Breakdown'!AC:AC) -> 3453831
B106: Chad J. Zamarin | C106: Williams | I106: =SUMIF('Executive Pay Breakdown'!K:K,$B106,'Executive Pay Breakdown'!M:M)+SUMIF('Executive Pay Breakdown'!O:O,$B106,'Executive Pay Breakdown'!Q:Q)+SUMIF('Executive Pay Breakdown'!S:S,$B106,'Executive Pay Breakdown'!U:U)+SUMIF('Executive Pay Breakdown'!W:W,$B106,'Executive Pay Breakdown'!Y:Y)+SUMIF('Executive Pay Breakdown'!AA:AA,$B106,'Executive Pay Breakdown'!AC:AC) -> 21631238 | K106: =SUMIF('Executive Pay Breakdown'!K:K,$B106,'Executive Pay Breakdown'!M:M) -> 4528608 | L106: =SUMIF('Executive Pay Breakdown'!O:O,$B106,'Executive Pay Breakdown'!Q:Q) -> 4122715 | M106: =SUMIF('Executive Pay Breakdown'!S:S,$B106,'Executive Pay Breakdown'!U:U) -> 3995728 | N106: =SUMIF('Executive Pay Breakdown'!W:W,$B106,'Executive Pay Breakdown'!Y:Y) -> 5268657 | O106: =SUMIF('Executive Pay Breakdown'!AA:AA,$B106,'Executive Pay Breakdown'!AC:AC) -> 3715530
B107: Kevin L. Burdick | C107: Oneok | I107: =SUMIF('Executive Pay Breakdown'!K:K,$B107,'Executive Pay Breakdown'!M:M)+SUMIF('Executive Pay Breakdown'!O:O,$B107,'Executive Pay Breakdown'!Q:Q)+SUMIF('Executive Pay Breakdown'!S:S,$B107,'Executive Pay Breakdown'!U:U)+SUMIF('Executive Pay Breakdown'!W:W,$B107,'Executive Pay Breakdown'!Y:Y)+SUMIF('Executive Pay Breakdown'!AA:AA,$B107,'Executive Pay Breakdown'!AC:AC) -> 14653961 | K107: =SUMIF('Executive Pay Breakdown'!K:K,$B107,'Executive Pay Breakdown'!M:M) -> 3269613 | L107: =SUMIF('Executive Pay Breakdown'!O:O,$B107,'Executive Pay Breakdown'!Q:Q) -> 3416525 | M107: =SUMIF('Executive Pay Breakdown'!S:S,$B107,'Executive Pay Breakdown'!U:U) -> 2593460 | N107: =SUMIF('Executive Pay Breakdown'!W:W,$B107,'Executive Pay Breakdown'!Y:Y) -> 2656819 | O107: =SUMIF('Executive Pay Breakdown'!AA:AA,$B107,'Executive Pay Breakdown'!AC:AC) -> 2717544
B108: Beth Costello | C108: Hartford Financial Services | I108: =SUMIF('Executive Pay Breakdown'!K:K,$B108,'Executive Pay Breakdown'!M:M)+SUMIF('Executive Pay Breakdown'!O:O,$B108,'Executive Pay Breakdown'!Q:Q)+SUMIF('Executive Pay Breakdown'!S:S,$B108,'Executive Pay Breakdown'!U:U)+SUMIF('Executive Pay Breakdown'!W:W,$B108,'Executive Pay Breakdown'!Y:Y)+SUMIF('Executive Pay Breakdown'!AA:AA,$B108,'Executive Pay Breakdown'!AC:AC) -> 22782713 | K108: =SUMIF('Executive Pay Breakdown'!K:K,$B108,'Executive Pay Breakdown'!M:M) -> 5290975 | L108: =SUMIF('Executive Pay Breakdown'!O:O,$B108,'Executive Pay Breakdown'!Q:Q) -> 4926200 | M108: =SUMIF('Executive Pay Breakdown'!S:S,$B108,'Executive Pay Breakdown'!U:U) -> 3572472 | N108: =SUMIF('Executive Pay Breakdown'!W:W,$B108,'Executive Pay Breakdown'!Y:Y) -> 4567391 | O108: =SUMIF('Executive Pay Breakdown'!AA:AA,$B108,'Executive Pay Breakdown'!AC:AC) -> 4425675
B109: Charles P. Nelson | C109: Voya Financial | I109: =SUMIF('Executive Pay Breakdown'!K:K,$B109,'Executive Pay Breakdown'!M:M)+SUMIF('Executive Pay Breakdown'!O:O,$B109,'Executive Pay Breakdown'!Q:Q)+SUMIF('Executive Pay Breakdown'!S:S,$B109,'Executive Pay Breakdown'!U:U)+SUMIF('Executive Pay Breakdown'!W:W,$B109,'Executive Pay Breakdown'!Y:Y)+SUMIF('Executive Pay Breakdown'!AA:AA,$B109,'Executive Pay Breakdown'!AC:AC) -> 25754919 | K109: =SUMIF('Executive Pay Breakdown'!K:K,$B109,'Executive Pay Breakdown'!M:M) -> 5588971 | L109: =SUMIF('Executive Pay Breakdown'!O:O,$B109,'Executive Pay Breakdown'!Q:Q) -> 5757689 | M109: =SUMIF('Executive Pay Breakdown'!S:S,$B109,'Executive Pay Breakdown'!U:U) -> 4702504 | N109: =SUMIF('Executive Pay Breakdown'!W:W,$B109,'Executive Pay Breakdown'!Y:Y) -> 5001396 | O109: =SUMIF('Executive Pay Breakdown'!AA:AA,$B109,'Executive Pay Breakdown'!AC:AC) -> 4704359
B110: Micheal G. Dunn | C110: Williams | I110: =SUMIF('Executive Pay Breakdown'!K:K,$B110,'Executive Pay Breakdown'!M:M)+SUMIF('Executive Pay Breakdown'!O:O,$B110,'Executive Pay Breakdown'!Q:Q)+SUMIF('Executive Pay Breakdown'!S:S,$B110,'Executive Pay Breakdown'!U:U)+SUMIF('Executive Pay Breakdown'!W:W,$B110,'Executive Pay Breakdown'!Y:Y)+SUMIF('Executive Pay Breakdown'!AA:AA,$B110,'Executive Pay Breakdown'!AC:AC) -> 28731525 | K110: =SUMIF('Executive Pay Breakdown'!K:K,$B110,'Executive Pay Breakdown'!M:M) -> 5997568 | L110: =SUMIF('Executive Pay Breakdown'!O:O,$B110,'Executive Pay Breakdown'!Q:Q) -> 5433225 | M110: =SUMIF('Executive Pay Breakdown'!S:S,$B110,'Executive Pay Breakdown'!U:U) -> 5591351 | N110: =SUMIF('Executive Pay Breakdown'!W:W,$B110,'Executive Pay Breakdown'!Y:Y) -> 6611309 | O110: =SUMIF('Executive Pay Breakdown'!AA:AA,$B110,'Executive Pay Breakdown'!AC:AC) -> 5098072
B111: David M. Feinberg | C111: American Electric Power | I111: =SUMIF('Executive Pay Breakdown'!K:K,$B111,'Executive Pay Breakdown'!M:M)+SUMIF('Executive Pay Breakdown'!O:O,$B111,'Executive Pay Breakdown'!Q:Q)+SUMIF('Executive Pay Breakdown'!S:S,$B111,'Executive Pay Breakdown'!U:U)+SUMIF('Executive Pay Breakdown'!W:W,$B111,'Executive Pay Breakdown'!Y:Y)+SUMIF('Executive Pay Breakdown'!AA:AA,$B111,'Executive Pay Breakdown'!AC:AC) -> 15664535 | K111: =SUMIF('Executive Pay Breakdown'!K:K,$B111,'Executive Pay Breakdown'!M:M) -> 3205873 | L111: =SUMIF('Executive Pay Breakdown'!O:O,$B111,'Executive Pay Breakdown'!Q:Q) -> 3105946 | M111: =SUMIF('Executive Pay Breakdown'!S:S,$B111,'Executive Pay Breakdown'!U:U) -> 3376008 | N111: =SUMIF('Executive Pay Breakdown'!W:W,$B111,'Executive Pay Breakdown'!Y:Y) -> 3235304 | O111: =SUMIF('Executive Pay Breakdown'!AA:AA,$B111,'Executive Pay Breakdown'!AC:AC) -> 2741404
B112: A. N. Sreeram | C112: Dow | I112: =SUMIF('Executive Pay Breakdown'!K:K,$B112,'Executive Pay Breakdown'!M:M)+SUMIF('Executive Pay Breakdown'!O:O,$B112,'Executive Pay Breakdown'!Q:Q)+SUMIF('Executive Pay Breakdown'!S:S,$B112,'Executive Pay Breakdown'!U:U)+SUMIF('Executive Pay Breakdown'!W:W,$B112,'Executive Pay Breakdown'!Y:Y)+SUMIF('Executive Pay Breakdown'!AA:AA,$B112,'Executive Pay Breakdown'!AC:AC) -> 23107861 | K112: =SUMIF('Executive Pay Breakdown'!K:K,$B112,'Executive Pay Breakdown'!M:M) -> 4851673 | L112: =SUMIF('Executive Pay Breakdown'!O:O,$B112,'Executive Pay Breakdown'!Q:Q) -> 5147196 | M112: =SUMIF('Executive Pay Breakdown'!S:S,$B112,'Executive Pay Breakdown'!U:U) -> 4429217 | N112: =SUMIF('Executive Pay Breakdown'!W:W,$B112,'Executive Pay Breakdown'!Y:Y) -> 4521698 | O112: =SUMIF('Executive Pay Breakdown'!AA:AA,$B112,'Executive Pay Breakdown'!AC:AC) -> 4158077
B113: Darrell C. Sherman | C113: Taylor Morrison Home | I113: =SUMIF('Executive Pay Breakdown'!K:K,$B113,'Executive Pay Breakdown'!M:M)+SUMIF('Executive Pay Breakdown'!O:O,$B113,'Executive Pay Breakdown'!Q:Q)+SUMIF('Executive Pay Breakdown'!S:S,$B113,'Executive Pay Breakdown'!U:U)+SUMIF('Executive Pay Breakdown'!W:W,$B113,'Executive Pay Breakdown'!Y:Y)+SUMIF('Executive Pay Breakdown'!AA:AA,$B113,'Executive Pay Breakdown'!AC:AC) -> 11641848 | K113: =SUMIF('Executive Pay Breakdown'!K:K,$B113,'Executive Pay Breakdown'!M:M) -> 1996882 | L113: =SUMIF('Executive Pay Breakdown'!O:O,$B113,'Executive Pay Breakdown'!Q:Q) -> 3388186 | M113: =SUMIF('Executive Pay Breakdown'!S:S,$B113,'Executive Pay Breakdown'!U:U) -> 2127301 | N113: =SUMIF('Executive Pay Breakdown'!W:W,$B113,'Executive Pay Breakdown'!Y:Y) -> 2415874 | O113: =SUMIF('Executive Pay Breakdown'!AA:AA,$B113,'Executive Pay Breakdown'!AC:AC) -> 1713605
B114: Christopher Swift | C114: Hartford Financial Services | I114: =SUMIF('Executive Pay Breakdown'!K:K,$B114,'Executive Pay Breakdown'!M:M)+SUMIF('Executive Pay Breakdown'!O:O,$B114,'Executive Pay Breakdown'!Q:Q)+SUMIF('Executive Pay Breakdown'!S:S,$B114,'Executive Pay Breakdown'!U:U)+SUMIF('Executive Pay Breakdown'!W:W,$B114,'Executive Pay Breakdown'!Y:Y)+SUMIF('Executive Pay Breakdown'!AA:AA,$B114,'Executive Pay Breakdown'!AC:AC) -> 72161375 | K114: =SUMIF('Executive Pay Breakdown'!K:K,$B114,'Executive Pay Breakdown'!M:M) -> 16086469 | L114: =SUMIF('Executive Pay Breakdown'!O:O,$B114,'Executive Pay Breakdown'!Q:Q) -> 15824348 | M114: =SUMIF('Executive Pay Breakdown'!S:S,$B114,'Executive Pay Breakdown'!U:U) -> 11806195 | N114: =SUMIF('Executive Pay Breakdown'!W:W,$B114,'Executive Pay Breakdown'!Y:Y) -> 14560748 | O114: =SUMIF('Executive Pay Breakdown'!AA:AA,$B114,'Executive Pay Breakdown'!AC:AC) -> 13883615
B115: E. Robert Lupone | C115: Textron | I115: =SUMIF('Executive Pay Breakdown'!K:K,$B115,'Executive Pay Breakdown'!M:M)+SUMIF('Executive Pay Breakdown'!O:O,$B115,'Executive Pay Breakdown'!Q:Q)+SUMIF('Executive Pay Breakdown'!S:S,$B115,'Executive Pay Breakdown'!U:U)+SUMIF('Executive Pay Breakdown'!W:W,$B115,'Executive Pay Breakdown'!Y:Y)+SUMIF('Executive Pay Breakdown'!AA:AA,$B115,'Executive Pay Breakdown'!AC:AC) -> 15821039 | K115: =SUMIF('Executive Pay Breakdown'!K:K,$B115,'Executive Pay Breakdown'!M:M) -> 3259047 | L115: =SUMIF('Executive Pay Breakdown'!O:O,$B115,'Executive Pay Breakdown'!Q:Q) -> 3887770 | M115: =SUMIF('Executive Pay Breakdown'!S:S,$B115,'Executive Pay Breakdown'!U:U) -> 2907243 | N115: =SUMIF('Executive Pay Breakdown'!W:W,$B115,'Executive Pay Breakdown'!Y:Y) -> 2953666 | O115: =SUMIF('Executive Pay Breakdown'!AA:AA,$B115,'Executive Pay Breakdown'!AC:AC) -> 2813313
B116: James R. Chapman | C116: Dominion Energy | I116: =SUMIF('Executive Pay Breakdown'!K:K,$B116,'Executive Pay Breakdown'!M:M)+SUMIF('Executive Pay Breakdown'!O:O,$B116,'Executive Pay Breakdown'!Q:Q)+SUMIF('Executive Pay Breakdown'!S:S,$B116,'Executive Pay Breakdown'!U:U)+SUMIF('Executive Pay Breakdown'!W:W,$B116,'Executive Pay Breakdown'!Y:Y)+SUMIF('Executive Pay Breakdown'!AA:AA,$B116,'Executive Pay Breakdown'!AC:AC) -> 9980558 | K116: =SUMIF('Executive Pay Breakdown'!K:K,$B116,'Executive Pay Breakdown'!M:M) -> 1488300 | L116: =SUMIF('Executive Pay Breakdown'!O:O,$B116,'Executive Pay Breakdown'!Q:Q) -> 2839907 | M116: =SUMIF('Executive Pay Breakdown'!S:S,$B116,'Executive Pay Breakdown'!U:U) -> 2457568 | N116: =SUMIF('Executive Pay Breakdown'!W:W,$B116,'Executive Pay Breakdown'!Y:Y) -> 1907433 | O116: =SUMIF('Executive Pay Breakdown'!AA:AA,$B116,'Executive Pay Breakdown'!AC:AC) -> 1287350
... B133: Samuel L. Belcher | C133: FirstEnergy | I133: =SUMIF('Executive Pay Breakdown'!K:K,$B133,'Executive Pay Breakdown'!M:M)+SUMIF('Executive Pay Breakdown'!O:O,$B133,'Executive Pay Breakdown'!Q:Q)+SUMIF('Executive Pay Breakdown'!S:S,$B133,'Executive Pay Breakdown'!U:U)+SUMIF('Executive Pay Breakdown'!W:W,$B133,'Executive Pay Breakdown'!Y:Y)+SUMIF('Executive Pay Breakdown'!AA:AA,$B133,'Executive Pay Breakdown'!AC:AC) -> 14811611 | K133: =SUMIF('Executive Pay Breakdown'!K:K,$B133,'Executive Pay Breakdown'!M:M) -> 3162836 | L133: =SUMIF('Executive Pay Breakdown'!O:O,$B133,'Executive Pay Breakdown'!Q:Q) -> 3520949 | M133: =SUMIF('Executive Pay Breakdown'!S:S,$B133,'Executive Pay Breakdown'!U:U) -> 2638271 | N133: =SUMIF('Executive Pay Breakdown'!W:W,$B133,'Executive Pay Breakdown'!Y:Y) -> 2485536 | O133: =SUMIF('Executive Pay Breakdown'!AA:AA,$B133,'Executive Pay Breakdown'!AC:AC) -> 3004019
A134: Yes | B134: Marc Benioff | C134: Salesforce | I134: =SUMIF('Executive Pay Breakdown'!K:K,$B134,'Executive Pay Breakdown'!M:M)+SUMIF('Executive Pay Breakdown'!O:O,$B134,'Executive Pay Breakdown'!Q:Q)+SUMIF('Executive Pay Breakdown'!S:S,$B134,'Executive Pay Breakdown'!U:U)+SUMIF('Executive Pay Breakdown'!W:W,$B134,'Executive Pay Breakdown'!Y:Y)+SUMIF('Executive Pay Breakdown'!AA:AA,$B134,'Executive Pay Breakdown'!AC:AC) -> 138573120 | K134: =SUMIF('Executive Pay Breakdown'!K:K,$B134,'Executive Pay Breakdown'!M:M) -> 29868893 | L134: =SUMIF('Executive Pay Breakdown'!O:O,$B134,'Executive Pay Breakdown'!Q:Q) -> 28602112 | M134: =SUMIF('Executive Pay Breakdown'!S:S,$B134,'Executive Pay Breakdown'!U:U) -> 25740775 | N134: =SUMIF('Executive Pay Breakdown'!W:W,$B134,'Executive Pay Breakdown'!Y:Y) -> 25969494 | O134: =SUMIF('Executive Pay Breakdown'!AA:AA,$B134,'Executive Pay Breakdown'!AC:AC) -> 28391846
B135: Stacey W. Goff | C135: Lumen Technologies | I135: =SUMIF('Executive Pay Breakdown'!K:K,$B135,'Executive Pay Breakdown'!M:M)+SUMIF('Executive Pay Breakdown'!O:O,$B135,'Executive Pay Breakdown'!Q:Q)+SUMIF('Executive Pay Breakdown'!S:S,$B135,'Executive Pay Breakdown'!U:U)+SUMIF('Executive Pay Breakdown'!W:W,$B135,'Executive Pay Breakdown'!Y:Y)+SUMIF('Executive Pay Breakdown'!AA:AA,$B135,'Executive Pay Breakdown'!AC:AC) -> 17814072 | K135: =SUMIF('Executive Pay Breakdown'!K:K,$B135,'Executive Pay Breakdown'!M:M) -> 3754251 | L135: =SUMIF('Executive Pay Breakdown'!O:O,$B135,'Executive Pay Breakdown'!Q:Q) -> 3787097 | M135: =SUMIF('Executive Pay Breakdown'!S:S,$B135,'Executive Pay Breakdown'!U:U) -> 3251312 | N135: =SUMIF('Executive Pay Breakdown'!W:W,$B135,'Executive Pay Breakdown'!Y:Y) -> 3445957 | O135: =SUMIF('Executive Pay Breakdown'!AA:AA,$B135,'Executive Pay Breakdown'!AC:AC) -> 3575455
B136: Douglas Elliot | C136: Hartford Financial Services | I136: =SUMIF('Executive Pay Breakdown'!K:K,$B136,'Executive Pay Breakdown'!M:M)+SUMIF('Executive Pay Breakdown'!O:O,$B136,'Executive Pay Breakdown'!Q:Q)+SUMIF('Executive Pay Breakdown'!S:S,$B136,'Executive Pay Breakdown'!U:U)+SUMIF('Executive Pay Breakdown'!W:W,$B136,'Executive Pay Breakdown'!Y:Y)+SUMIF('Executive Pay Breakdown'!AA:AA,$B136,'Executive Pay Breakdown'!AC:AC) -> 45010141 | K136: =SUMIF('Executive Pay Breakdown'!K:K,$B136,'Executive Pay Breakdown'!M:M) -> 9426954 | L136: =SUMIF('Executive Pay Breakdown'!O:O,$B136,'Executive Pay Breakdown'!Q:Q) -> 9708693 | M136: =SUMIF('Executive Pay Breakdown'!S:S,$B136,'Executive Pay Breakdown'!U:U) -> 7542532 | N136: =SUMIF('Executive Pay Breakdown'!W:W,$B136,'Executive Pay Breakdown'!Y:Y) -> 9332849 | O136: =SUMIF('Executive Pay Breakdown'!AA:AA,$B136,'Executive Pay Breakdown'!AC:AC) -> 8999113
B137: A. Christopher Bakken III | C137: Entergy | I137: =SUMIF('Executive Pay Breakdown'!K:K,$B137,'Executive Pay Breakdown'!M:M)+SUMIF('Executive Pay Breakdown'!O:O,$B137,'Executive Pay Breakdown'!Q:Q)+SUMIF('Executive Pay Breakdown'!S:S,$B137,'Executive Pay Breakdown'!U:U)+SUMIF('Executive Pay Breakdown'!W:W,$B137,'Executive Pay Breakdown'!Y:Y)+SUMIF('Executive Pay Breakdown'!AA:AA,$B137,'Executive Pay Breakdown'!AC:AC) -> 16916973 | K137: =SUMIF('Executive Pay Breakdown'!K:K,$B137,'Executive Pay Breakdown'!M:M) -> 3369474 | L137: =SUMIF('Executive Pay Breakdown'!O:O,$B137,'Executive Pay Breakdown'!Q:Q) -> 3442338 | M137: =SUMIF('Executive Pay Breakdown'!S:S,$B137,'Executive Pay Breakdown'!U:U) -> 3674009 | N137: =SUMIF('Executive Pay Breakdown'!W:W,$B137,'Executive Pay Breakdown'!Y:Y) -> 3186440 | O137: =SUMIF('Executive Pay Breakdown'!AA:AA,$B137,'Executive Pay Breakdown'!AC:AC) -> 3244712
B138: Roger L. Kearns | C138: Westlake Chemical | I138: =SUMIF('Executive Pay Breakdown'!K:K,$B138,'Executive Pay Breakdown'!M:M)+SUMIF('Executive Pay Breakdown'!O:O,$B138,'Executive Pay Breakdown'!Q:Q)+SUMIF('Executive Pay Breakdown'!S:S,$B138,'Executive Pay Breakdown'!U:U)+SUMIF('Executive Pay Breakdown'!W:W,$B138,'Executive Pay Breakdown'!Y:Y)+SUMIF('Executive Pay Breakdown'!AA:AA,$B138,'Executive Pay Breakdown'!AC:AC) -> 20740248 | K138: =SUMIF('Executive Pay Breakdown'!K:K,$B138,'Executive Pay Breakdown'!M:M) -> 5400143 | L138: =SUMIF('Executive Pay Breakdown'!O:O,$B138,'Executive Pay Breakdown'!Q:Q) -> 6651394 | M138: =SUMIF('Executive Pay Breakdown'!S:S,$B138,'Executive Pay Breakdown'!U:U) -> 3481123 | N138: =SUMIF('Executive Pay Breakdown'!W:W,$B138,'Executive Pay Breakdown'!Y:Y) -> 0 | O138: =SUMIF('Executive Pay Breakdown'!AA:AA,$B138,'Executive Pay Breakdown'!AC:AC) -> 5207588
A139: Yes | B139: Charles W. Ergen | C139: DISH Network | I139: =SUMIF('Executive Pay Breakdown'!K:K,$B139,'Executive Pay Breakdown'!M:M)+SUMIF('Executive Pay Breakdown'!O:O,$B139,'Executive Pay Breakdown'!Q:Q)+SUMIF('Executive Pay Breakdown'!S:S,$B139,'Executive Pay Breakdown'!U:U)+SUMIF('Executive Pay Breakdown'!W:W,$B139,'Executive Pay Breakdown'!Y:Y)+SUMIF('Executive Pay Breakdown'!AA:AA,$B139,'Executive Pay Breakdown'!AC:AC) -> 106511754 | K139: =SUMIF('Executive Pay Breakdown'!K:K,$B139,'Executive Pay Breakdown'!M:M) -> 3219778 | L139: =SUMIF('Executive Pay Breakdown'!O:O,$B139,'Executive Pay Breakdown'!Q:Q) -> 3060317 | M139: =SUMIF('Executive Pay Breakdown'!S:S,$B139,'Executive Pay Breakdown'!U:U) -> 94761246 | N139: =SUMIF('Executive Pay Breakdown'!W:W,$B139,'Executive Pay Breakdown'!Y:Y) -> 2357756 | O139: =SUMIF('Executive Pay Breakdown'!AA:AA,$B139,'Executive Pay Breakdown'!AC:AC) -> 3112657
B140: Ray G. Young | C140: Archer Daniels Midland | I140: =SUMIF('Executive Pay Breakdown'!K:K,$B140,'Executive Pay Breakdown'!M:M)+SUMIF('Executive Pay Breakdown'!O:O,$B140,'Executive Pay Breakdown'!Q:Q)+SUMIF('Executive Pay Breakdown'!S:S,$B140,'Executive Pay Breakdown'!U:U)+SUMIF('Executive Pay Breakdown'!W:W,$B140,'Executive Pay Breakdown'!Y:Y)+SUMIF('Executive Pay Breakdown'!AA:AA,$B140,'Executive Pay Breakdown'!AC:AC) -> 38721367 | K140: =SUMIF('Executive Pay Breakdown'!K:K,$B140,'Executive Pay Breakdown'!M:M) -> 7755200 | L140: =SUMIF('Executive Pay Breakdown'!O:O,$B140,'Executive Pay Breakdown'!Q:Q) -> 8094974 | M140: =SUMIF('Executive Pay Breakdown'!S:S,$B140,'Executive Pay Breakdown'!U:U) -> 8548754 | N140: =SUMIF('Executive Pay Breakdown'!W:W,$B140,'Executive Pay Breakdown'!Y:Y) -> 6825067 | O140: =SUMIF('Executive Pay Breakdown'!AA:AA,$B140,'Executive Pay Breakdown'!AC:AC) -> 7497372
B141: Bud Denker | C141: Penske Automotive Group | I141: =SUMIF('Executive Pay Breakdown'!K:K,$B141,'Executive Pay Breakdown'!M:M)+SUMIF('Executive Pay Breakdown'!O:O,$B141,'Executive Pay Breakdown'!Q:Q)+SUMIF('Executive Pay Breakdown'!S:S,$B141,'Executive Pay Breakdown'!U:U)+SUMIF('Executive Pay Breakdown'!W:W,$B141,'Executive Pay Breakdown'!Y:Y)+SUMIF('Executive Pay Breakdown'!AA:AA,$B141,'Executive Pay Breakdown'!AC:AC) -> 8140662 | K141: =SUMIF('Executive Pay Breakdown'!K:K,$B141,'Executive Pay Breakdown'!M:M) -> 1789732 | L141: =SUMIF('Executive Pay Breakdown'!O:O,$B141,'Executive Pay Breakdown'!Q:Q) -> 1710752 | M141: =SUMIF('Executive Pay Breakdown'!S:S,$B141,'Executive Pay Breakdown'!U:U) -> 1468446 | N141: =SUMIF('Executive Pay Breakdown'!W:W,$B141,'Executive Pay Breakdown'!Y:Y) -> 1424649 | O141: =SUMIF('Executive Pay Breakdown'!AA:AA,$B141,'Executive Pay Breakdown'!AC:AC) -> 1747083
B142: Shane Spradlin | C142: Penske Automotive Group | I142: =SUMIF('Executive Pay Breakdown'!K:K,$B142,'Executive Pay Breakdown'!M:M)+SUMIF('Executive Pay Breakdown'!O:O,$B142,'Executive Pay Breakdown'!Q:Q)+SUMIF('Executive Pay Breakdown'!S:S,$B142,'Executive Pay Breakdown'!U:U)+SUMIF('Executive Pay Breakdown'!W:W,$B142,'Executive Pay Breakdown'!Y:Y)+SUMIF('Executive Pay Breakdown'!AA:AA,$B142,'Executive Pay Breakdown'!AC:AC) -> 8401477 | K142: =SUMIF('Executive Pay Breakdown'!K:K,$B142,'Executive Pay Breakdown'!M:M) -> 1841637 | L142: =SUMIF('Executive Pay Breakdown'!O:O,$B142,'Executive Pay Breakdown'!Q:Q) -> 1767474 | M142: =SUMIF('Executive Pay Breakdown'!S:S,$B142,'Executive Pay Breakdown'!U:U) -> 1513352 | N142: =SUMIF('Executive Pay Breakdown'!W:W,$B142,'Executive Pay Breakdown'!Y:Y) -> 1479597 | O142: =SUMIF('Executive Pay Breakdown'!AA:AA,$B142,'Executive Pay Breakdown'!AC:AC) -> 1799417
B143: James Chao | C143: Westlake Chemical | I143: =SUMIF('Executive Pay Breakdown'!K:K,$B143,'Executive Pay Breakdown'!M:M)+SUMIF('Executive Pay Breakdown'!O:O,$B143,'Executive Pay Breakdown'!Q:Q)+SUMIF('Executive Pay Breakdown'!S:S,$B143,'Executive Pay Breakdown'!U:U)+SUMIF('Executive Pay Breakdown'!W:W,$B143,'Executive Pay Breakdown'!Y:Y)+SUMIF('Executive Pay Breakdown'!AA:AA,$B143,'Executive Pay Breakdown'!AC:AC) -> 34949198 | K143: =SUMIF('Executive Pay Breakdown'!K:K,$B143,'Executive Pay Breakdown'!M:M) -> 6882920 | L143: =SUMIF('Executive Pay Breakdown'!O:O,$B143,'Executive Pay Breakdown'!Q:Q) -> 5628500 | M143: =SUMIF('Executive Pay Breakdown'!S:S,$B143,'Executive Pay Breakdown'!U:U) -> 7365266 | N143: =SUMIF('Executive Pay Breakdown'!W:W,$B143,'Executive Pay Breakdown'!Y:Y) -> 8336163 | O143: =SUMIF('Executive Pay Breakdown'!AA:AA,$B143,'Executive Pay Breakdown'!AC:AC) -> 6736349
B144: Christine Hurtsellers | C144: Voya Financial | I144: =SUMIF('Executive Pay Breakdown'!K:K,$B144,'Executive Pay Breakdown'!M:M)+SUMIF('Executive Pay Breakdown'!O:O,$B144,'Executive Pay Breakdown'!Q:Q)+SUMIF('Executive Pay Breakdown'!S:S,$B144,'Executive Pay Breakdown'!U:U)+SUMIF('Executive Pay Breakdown'!W:W,$B144,'Executive Pay Breakdown'!Y:Y)+SUMIF('Executive Pay Breakdown'!AA:AA,$B144,'Executive Pay Breakdown'!AC:AC) -> 29064937 | K144: =SUMIF('Executive Pay Breakdown'!K:K,$B144,'Executive Pay Breakdown'!M:M) -> 5751915 | L144: =SUMIF('Executive Pay Breakdown'!O:O,$B144,'Executive Pay Breakdown'!Q:Q) -> 5829452 | M144: =SUMIF('Executive Pay Breakdown'!S:S,$B144,'Executive Pay Breakdown'!U:U) -> 5414402 | N144: =SUMIF('Executive Pay Breakdown'!W:W,$B144,'Executive Pay Breakdown'!Y:Y) -> 6419295 | O144: =SUMIF('Executive Pay Breakdown'!AA:AA,$B144,'Executive Pay Breakdown'!AC:AC) -> 5649873
B145: Greg A. Greenwood | C145: Evergy | I145: =SUMIF('Executive Pay Breakdown'!K:K,$B145,'Executive Pay Breakdown'!M:M)+SUMIF('Executive Pay Breakdown'!O:O,$B145,'Executive Pay Breakdown'!Q:Q)+SUMIF('Executive Pay Breakdown'!S:S,$B145,'Executive Pay Breakdown'!U:U)+SUMIF('Executive Pay Breakdown'!W:W,$B145,'Executive Pay Breakdown'!Y:Y)+SUMIF('Executive Pay Breakdown'!AA:AA,$B145,'Executive Pay Breakdown'!AC:AC) -> 12438133 | K145: =SUMIF('Executive Pay Breakdown'!K:K,$B145,'Executive Pay Breakdown'!M:M) -> 2608121 | L145: =SUMIF('Executive Pay Breakdown'!O:O,$B145,'Executive Pay Breakdown'!Q:Q) -> 2146478 | M145: =SUMIF('Executive Pay Breakdown'!S:S,$B145,'Executive Pay Breakdown'!U:U) -> 2864429 | N145: =SUMIF('Executive Pay Breakdown'!W:W,$B145,'Executive Pay Breakdown'!Y:Y) -> 2208528 | O145: =SUMIF('Executive Pay Breakdown'!AA:AA,$B145,'Executive Pay Breakdown'!AC:AC) -> 2610577
B146: Howard Ungerleider | C146: Dow | I146: =SUMIF('Executive Pay Breakdown'!K:K,$B146,'Executive Pay Breakdown'!M:M)+SUMIF('Executive Pay Breakdown'!O:O,$B146,'Executive Pay Breakdown'!Q:Q)+SUMIF('Executive Pay Breakdown'!S:S,$B146,'Executive Pay Breakdown'!U:U)+SUMIF('Executive Pay Breakdown'!W:W,$B146,'Executive Pay Breakdown'!Y:Y)+SUMIF('Executive Pay Breakdown'!AA:AA,$B146,'Executive Pay Breakdown'!AC:AC) -> 44772975 | K146: =SUMIF('Executive Pay Breakdown'!K:K,$B146,'Executive Pay Breakdown'!M:M) -> 11618900 | L146: =SUMIF('Executive Pay Breakdown'!O:O,$B146,'Executive Pay Breakdown'!Q:Q) -> 8603097 | M146: =SUMIF('Executive Pay Breakdown'!S:S,$B146,'Executive Pay Breakdown'!U:U) -> 7427530 | N146: =SUMIF('Executive Pay Breakdown'!W:W,$B146,'Executive Pay Breakdown'!Y:Y) -> 5459670 | O146: =SUMIF('Executive Pay Breakdown'!AA:AA,$B146,'Executive Pay Breakdown'!AC:AC) -> 11663778
B147: Kevin T. Hogan | C147: American International Group | I147: =SUMIF('Executive Pay Breakdown'!K:K,$B147,'Executive Pay Breakdown'!M:M)+SUMIF('Executive Pay Breakdown'!O:O,$B147,'Executive Pay Breakdown'!Q:Q)+SUMIF('Executive Pay Breakdown'!S:S,$B147,'Executive Pay Breakdown'!U:U)+SUMIF('Executive Pay Breakdown'!W:W,$B147,'Executive Pay Breakdown'!Y:Y)+SUMIF('Executive Pay Breakdown'!AA:AA,$B147,'Executive Pay Breakdown'!AC:AC) -> 42136057 | K147: =SUMIF('Executive Pay Breakdown'!K:K,$B147,'Executive Pay Breakdown'!M:M) -> 8881597 | L147: =SUMIF('Executive Pay Breakdown'!O:O,$B147,'Executive Pay Breakdown'!Q:Q) -> 8005245 | M147: =SUMIF('Executive Pay Breakdown'!S:S,$B147,'Executive Pay Breakdown'!U:U) -> 7832913 | N147: =SUMIF('Executive Pay Breakdown'!W:W,$B147,'Executive Pay Breakdown'!Y:Y) -> 8294833 | O147: =SUMIF('Executive Pay Breakdown'!AA:AA,$B147,'Executive Pay Breakdown'!AC:AC) -> 9121469
B148: M. Gaudiosi | C148: UGI | I148: =SUMIF('Executive Pay Breakdown'!K:K,$B148,'Executive Pay Breakdown'!M:M)+SUMIF('Executive Pay Breakdown'!O:O,$B148,'Executive Pay Breakdown'!Q:Q)+SUMIF('Executive Pay Breakdown'!S:S,$B148,'Executive Pay Breakdown'!U:U)+SUMIF('Executive Pay Breakdown'!W:W,$B148,'Executive Pay Breakdown'!Y:Y)+SUMIF('Executive Pay Breakdown'!AA:AA,$B148,'Executive Pay Breakdown'!AC:AC) -> 8825572 | K148: =SUMIF('Executive Pay Breakdown'!K:K,$B148,'Executive Pay Breakdown'!M:M) -> 1792380 | L148: =SUMIF('Executive Pay Breakdown'!O:O,$B148,'Executive Pay Breakdown'!Q:Q) -> 1889278 | M148: =SUMIF('Executive Pay Breakdown'!S:S,$B148,'Executive Pay Breakdown'!U:U) -> 1690856 | N148: =SUMIF('Executive Pay Breakdown'!W:W,$B148,'Executive Pay Breakdown'!Y:Y) -> 1609101 | O148: =SUMIF('Executive Pay Breakdown'!AA:AA,$B148,'Executive Pay Breakdown'!AC:AC) -> 1843957
B149: Diane Leopold | C149: Dominion Energy | I149: =SUMIF('Executive Pay Breakdown'!K:K,$B149,'Executive Pay Breakdown'!M:M)+SUMIF('Executive Pay Breakdown'!O:O,$B149,'Executive Pay Breakdown'!Q:Q)+SUMIF('Executive Pay Breakdown'!S:S,$B149,'Executive Pay Breakdown'!U:U)+SUMIF('Executive Pay Breakdown'!W:W,$B149,'Executive Pay Breakdown'!Y:Y)+SUMIF('Executive Pay Breakdown'!AA:AA,$B149,'Executive Pay Breakdown'!AC:AC) -> 23530982 | K149: =SUMIF('Executive Pay Breakdown'!K:K,$B149,'Executive Pay Breakdown'!M:M) -> 3023465 | L149: =SUMIF('Executive Pay Breakdown'!O:O,$B149,'Executive Pay Breakdown'!Q:Q) -> 4575773 | M149: =SUMIF('Executive Pay Breakdown'!S:S,$B149,'Executive Pay Breakdown'!U:U) -> 8167332 | N149: =SUMIF('Executive Pay Breakdown'!W:W,$B149,'Executive Pay Breakdown'!Y:Y) -> 4642173 | O149: =SUMIF('Executive Pay Breakdown'!AA:AA,$B149,'Executive Pay Breakdown'!AC:AC) -> 3122239
B150: Christopher Moser | C150: NRG Energy | I150: =SUMIF('Executive Pay Breakdown'!K:K,$B150,'Executive Pay Breakdown'!M:M)+SUMIF('Executive Pay Breakdown'!O:O,$B150,'Executive Pay Breakdown'!Q:Q)+SUMIF('Executive Pay Breakdown'!S:S,$B150,'Executive Pay Breakdown'!U:U)+SUMIF('Executive Pay Breakdown'!W:W,$B150,'Executive Pay Breakdown'!Y:Y)+SUMIF('Executive Pay Breakdown'!AA:AA,$B150,'Executive Pay Breakdown'!AC:AC) -> 11527267 | K150: =SUMIF('Executive Pay Breakdown'!K:K,$B150,'Executive Pay Breakdown'!M:M) -> 2107527 | L150: =SUMIF('Executive Pay Breakdown'!O:O,$B150,'Executive Pay Breakdown'!Q:Q) -> 2567086 | M150: =SUMIF('Executive Pay Breakdown'!S:S,$B150,'Executive Pay Breakdown'!U:U) -> 2423775 | N150: =SUMIF('Executive Pay Breakdown'!W:W,$B150,'Executive Pay Breakdown'!Y:Y) -> 2233090 | O150: =SUMIF('Executive Pay Breakdown'!AA:AA,$B150,'Executive Pay Breakdown'!AC:AC) -> 2195789
B151: Robert B. Carter | C151: FedEx | I151: =SUMIF('Executive Pay Breakdown'!K:K,$B151,'Executive Pay Breakdown'!M:M)+SUMIF('Executive Pay Breakdown'!O:O,$B151,'Executive Pay Breakdown'!Q:Q)+SUMIF('Executive Pay Breakdown'!S:S,$B151,'Executive Pay Breakdown'!U:U)+SUMIF('Executive Pay Breakdown'!W:W,$B151,'Executive Pay Breakdown'!Y:Y)+SUMIF('Executive Pay Breakdown'!AA:AA,$B151,'Executive Pay Breakdown'!AC:AC) -> 24954498 | K151: =SUMIF('Executive Pay Breakdown'!K:K,$B151,'Executive Pay Breakdown'!M:M) -> 5677999 | L151: =SUMIF('Executive Pay Breakdown'!O:O,$B151,'Executive Pay Breakdown'!Q:Q) -> 3452232 | M151: =SUMIF('Executive Pay Breakdown'!S:S,$B151,'Executive Pay Breakdown'!U:U) -> 5154792 | N151: =SUMIF('Executive Pay Breakdown'!W:W,$B151,'Executive Pay Breakdown'!Y:Y) -> 4705929 | O151: =SUMIF('Executive Pay Breakdown'!AA:AA,$B151,'Executive Pay Breakdown'!AC:AC) -> 5963546
... B171: Neville R. Ray | C171: T-Mobile US | I171: =SUMIF('Executive Pay Breakdown'!K:K,$B171,'Executive Pay Breakdown'!M:M)+SUMIF('Executive Pay Breakdown'!O:O,$B171,'Executive Pay Breakdown'!Q:Q)+SUMIF('Executive Pay Breakdown'!S:S,$B171,'Executive Pay Breakdown'!U:U)+SUMIF('Executive Pay Breakdown'!W:W,$B171,'Executive Pay Breakdown'!Y:Y)+SUMIF('Executive Pay Breakdown'!AA:AA,$B171,'Executive Pay Breakdown'!AC:AC) -> 94813450 | K171: =SUMIF('Executive Pay Breakdown'!K:K,$B171,'Executive Pay Breakdown'!M:M) -> 13103145 | L171: =SUMIF('Executive Pay Breakdown'!O:O,$B171,'Executive Pay Breakdown'!Q:Q) -> 11547241 | M171: =SUMIF('Executive Pay Breakdown'!S:S,$B171,'Executive Pay Breakdown'!U:U) -> 33212469 | N171: =SUMIF('Executive Pay Breakdown'!W:W,$B171,'Executive Pay Breakdown'!Y:Y) -> 11175697 | O171: =SUMIF('Executive Pay Breakdown'!AA:AA,$B171,'Executive Pay Breakdown'!AC:AC) -> 25774898
A172: Yes | B172: Frederick W. Smith | C172: FedEx | I172: =SUMIF('Executive Pay Breakdown'!K:K,$B172,'Executive Pay Breakdown'!M:M)+SUMIF('Executive Pay Breakdown'!O:O,$B172,'Executive Pay Breakdown'!Q:Q)+SUMIF('Executive Pay Breakdown'!S:S,$B172,'Executive Pay Breakdown'!U:U)+SUMIF('Executive Pay Breakdown'!W:W,$B172,'Executive Pay Breakdown'!Y:Y)+SUMIF('Executive Pay Breakdown'!AA:AA,$B172,'Executive Pay Breakdown'!AC:AC) -> 60087202 | K172: =SUMIF('Executive Pay Breakdown'!K:K,$B172,'Executive Pay Breakdown'!M:M) -> 8077742 | L172: =SUMIF('Executive Pay Breakdown'!O:O,$B172,'Executive Pay Breakdown'!Q:Q) -> 10596150 | M172: =SUMIF('Executive Pay Breakdown'!S:S,$B172,'Executive Pay Breakdown'!U:U) -> 14325537 | N172: =SUMIF('Executive Pay Breakdown'!W:W,$B172,'Executive Pay Breakdown'!Y:Y) -> 11125799 | O172: =SUMIF('Executive Pay Breakdown'!AA:AA,$B172,'Executive Pay Breakdown'!AC:AC) -> 15961974
B173: Jeffrey M. Leiden | C173: Vertex Pharmaceuticals | I173: =SUMIF('Executive Pay Breakdown'!K:K,$B173,'Executive Pay Breakdown'!M:M)+SUMIF('Executive Pay Breakdown'!O:O,$B173,'Executive Pay Breakdown'!Q:Q)+SUMIF('Executive Pay Breakdown'!S:S,$B173,'Executive Pay Breakdown'!U:U)+SUMIF('Executive Pay Breakdown'!W:W,$B173,'Executive Pay Breakdown'!Y:Y)+SUMIF('Executive Pay Breakdown'!AA:AA,$B173,'Executive Pay Breakdown'!AC:AC) -> 70812796 | K173: =SUMIF('Executive Pay Breakdown'!K:K,$B173,'Executive Pay Breakdown'!M:M) -> 8593180 | L173: =SUMIF('Executive Pay Breakdown'!O:O,$B173,'Executive Pay Breakdown'!Q:Q) -> 8157239 | M173: =SUMIF('Executive Pay Breakdown'!S:S,$B173,'Executive Pay Breakdown'!U:U) -> 16473245 | N173: =SUMIF('Executive Pay Breakdown'!W:W,$B173,'Executive Pay Breakdown'!Y:Y) -> 18789985 | O173: =SUMIF('Executive Pay Breakdown'!AA:AA,$B173,'Executive Pay Breakdown'!AC:AC) -> 18799147
B174: Scott D. Sheffield | C174: {=INDEX('Executive Pay Breakdown'!B:B,MATCH(B174,'Executive Pay Breakdown'!K:K,0))} -> Pioneer Natural Resources | I174: =SUMIF('Executive Pay Breakdown'!K:K,$B174,'Executive Pay Breakdown'!M:M)+SUMIF('Executive Pay Breakdown'!O:O,$B174,'Executive Pay Breakdown'!Q:Q)+SUMIF('Executive Pay Breakdown'!S:S,$B174,'Executive Pay Breakdown'!U:U)+SUMIF('Executive Pay Breakdown'!W:W,$B174,'Executive Pay Breakdown'!Y:Y)+SUMIF('Executive Pay Breakdown'!AA:AA,$B174,'Executive Pay Breakdown'!AC:AC) -> 61810797 | K174: =SUMIF('Executive Pay Breakdown'!K:K,$B174,'Executive Pay Breakdown'!M:M) -> 19055854 | L174: =SUMIF('Executive Pay Breakdown'!O:O,$B174,'Executive Pay Breakdown'!Q:Q) -> 16002825 | M174: =SUMIF('Executive Pay Breakdown'!S:S,$B174,'Executive Pay Breakdown'!U:U) -> 13396571 | N174: =SUMIF('Executive Pay Breakdown'!W:W,$B174,'Executive Pay Breakdown'!Y:Y) -> 13355547 | O174: =SUMIF('Executive Pay Breakdown'!AA:AA,$B174,'Executive Pay Breakdown'!AC:AC) -> 0
B175: Richard P. Dealy | C175: {=INDEX('Executive Pay Breakdown'!B:B,MATCH(B175,'Executive Pay Breakdown'!K:K,0))} -> Pioneer Natural Resources | I175: =SUMIF('Executive Pay Breakdown'!K:K,$B175,'Executive Pay Breakdown'!M:M)+SUMIF('Executive Pay Breakdown'!O:O,$B175,'Executive Pay Breakdown'!Q:Q)+SUMIF('Executive Pay Breakdown'!S:S,$B175,'Executive Pay Breakdown'!U:U)+SUMIF('Executive Pay Breakdown'!W:W,$B175,'Executive Pay Breakdown'!Y:Y)+SUMIF('Executive Pay Breakdown'!AA:AA,$B175,'Executive Pay Breakdown'!AC:AC) -> 28401545 | K175: =SUMIF('Executive Pay Breakdown'!K:K,$B175,'Executive Pay Breakdown'!M:M) -> 9496977 | L175: =SUMIF('Executive Pay Breakdown'!O:O,$B175,'Executive Pay Breakdown'!Q:Q) -> 5837812 | M175: =SUMIF('Executive Pay Breakdown'!S:S,$B175,'Executive Pay Breakdown'!U:U) -> 3889912 | N175: =SUMIF('Executive Pay Breakdown'!W:W,$B175,'Executive Pay Breakdown'!Y:Y) -> 4511806 | O175: =SUMIF('Executive Pay Breakdown'!AA:AA,$B175,'Executive Pay Breakdown'!AC:AC) -> 4665038
B176: Donald C. Templin | C176: Marathon Petroleum Voya Financial | I176: =SUMIF('Executive Pay Breakdown'!K:K,$B176,'Executive Pay Breakdown'!M:M)+SUMIF('Executive Pay Breakdown'!O:O,$B176,'Executive Pay Breakdown'!Q:Q)+SUMIF('Executive Pay Breakdown'!S:S,$B176,'Executive Pay Breakdown'!U:U)+SUMIF('Executive Pay Breakdown'!W:W,$B176,'Executive Pay Breakdown'!Y:Y)+SUMIF('Executive Pay Breakdown'!AA:AA,$B176,'Executive Pay Breakdown'!AC:AC) -> 23131889 | K176: =SUMIF('Executive Pay Breakdown'!K:K,$B176,'Executive Pay Breakdown'!M:M) -> 313653 | L176: =SUMIF('Executive Pay Breakdown'!O:O,$B176,'Executive Pay Breakdown'!Q:Q) -> 939067 | M176: =SUMIF('Executive Pay Breakdown'!S:S,$B176,'Executive Pay Breakdown'!U:U) -> 7338642 | N176: =SUMIF('Executive Pay Breakdown'!W:W,$B176,'Executive Pay Breakdown'!Y:Y) -> 8116548 | O176: =SUMIF('Executive Pay Breakdown'!AA:AA,$B176,'Executive Pay Breakdown'!AC:AC) -> 6423979
B177: J.D. Hall | C177: {=INDEX('Executive Pay Breakdown'!B:B,MATCH(B177,'Executive Pay Breakdown'!K:K,0))} -> Pioneer Natural Resources | I177: =SUMIF('Executive Pay Breakdown'!K:K,$B177,'Executive Pay Breakdown'!M:M)+SUMIF('Executive Pay Breakdown'!O:O,$B177,'Executive Pay Breakdown'!Q:Q)+SUMIF('Executive Pay Breakdown'!S:S,$B177,'Executive Pay Breakdown'!U:U)+SUMIF('Executive Pay Breakdown'!W:W,$B177,'Executive Pay Breakdown'!Y:Y)+SUMIF('Executive Pay Breakdown'!AA:AA,$B177,'Executive Pay Breakdown'!AC:AC) -> 21216058 | K177: =SUMIF('Executive Pay Breakdown'!K:K,$B177,'Executive Pay Breakdown'!M:M) -> 5376845 | L177: =SUMIF('Executive Pay Breakdown'!O:O,$B177,'Executive Pay Breakdown'!Q:Q) -> 3979416 | M177: =SUMIF('Executive Pay Breakdown'!S:S,$B177,'Executive Pay Breakdown'!U:U) -> 3034396 | N177: =SUMIF('Executive Pay Breakdown'!W:W,$B177,'Executive Pay Breakdown'!Y:Y) -> 4251561 | O177: =SUMIF('Executive Pay Breakdown'!AA:AA,$B177,'Executive Pay Breakdown'!AC:AC) -> 4573840
B178: Mark S. Berg | C178: {=INDEX('Executive Pay Breakdown'!B:B,MATCH(B178,'Executive Pay Breakdown'!K:K,0))} -> Pioneer Natural Resources | I178: =SUMIF('Executive Pay Breakdown'!K:K,$B178,'Executive Pay Breakdown'!M:M)+SUMIF('Executive Pay Breakdown'!O:O,$B178,'Executive Pay Breakdown'!Q:Q)+SUMIF('Executive Pay Breakdown'!S:S,$B178,'Executive Pay Breakdown'!U:U)+SUMIF('Executive Pay Breakdown'!W:W,$B178,'Executive Pay Breakdown'!Y:Y)+SUMIF('Executive Pay Breakdown'!AA:AA,$B178,'Executive Pay Breakdown'!AC:AC) -> 19495109 | K178: =SUMIF('Executive Pay Breakdown'!K:K,$B178,'Executive Pay Breakdown'!M:M) -> 5375180 | L178: =SUMIF('Executive Pay Breakdown'!O:O,$B178,'Executive Pay Breakdown'!Q:Q) -> 3966376 | M178: =SUMIF('Executive Pay Breakdown'!S:S,$B178,'Executive Pay Breakdown'!U:U) -> 3050111 | N178: =SUMIF('Executive Pay Breakdown'!W:W,$B178,'Executive Pay Breakdown'!Y:Y) -> 3453323 | O178: =SUMIF('Executive Pay Breakdown'!AA:AA,$B178,'Executive Pay Breakdown'!AC:AC) -> 3650119
B179: Timothy L. Dove | C179: {=INDEX('Executive Pay Breakdown'!B:B,MATCH(B179,'Executive Pay Breakdown'!W:W,0))} -> Pioneer Natural Resources | I179: =SUMIF('Executive Pay Breakdown'!K:K,$B179,'Executive Pay Breakdown'!M:M)+SUMIF('Executive Pay Breakdown'!O:O,$B179,'Executive Pay Breakdown'!Q:Q)+SUMIF('Executive Pay Breakdown'!S:S,$B179,'Executive Pay Breakdown'!U:U)+SUMIF('Executive Pay Breakdown'!W:W,$B179,'Executive Pay Breakdown'!Y:Y)+SUMIF('Executive Pay Breakdown'!AA:AA,$B179,'Executive Pay Breakdown'!AC:AC) -> 16122659 | K179: =SUMIF('Executive Pay Breakdown'!K:K,$B179,'Executive Pay Breakdown'!M:M) -> 0 | L179: =SUMIF('Executive Pay Breakdown'!O:O,$B179,'Executive Pay Breakdown'!Q:Q) -> 0 | M179: =SUMIF('Executive Pay Breakdown'!S:S,$B179,'Executive Pay Breakdown'!U:U) -> 0 | N179: =SUMIF('Executive Pay Breakdown'!W:W,$B179,'Executive Pay Breakdown'!Y:Y) -> 4185868 | O179: =SUMIF('Executive Pay Breakdown'!AA:AA,$B179,'Executive Pay Breakdown'!AC:AC) -> 11936791
B180: Chris J. Cheatwood | C180: {=INDEX('Executive Pay Breakdown'!B:B,MATCH(B180,'Executive Pay Breakdown'!S:S,0))} -> Pioneer Natural Resources | I180: =SUMIF('Executive Pay Breakdown'!K:K,$B180,'Executive Pay Breakdown'!M:M)+SUMIF('Executive Pay Breakdown'!O:O,$B180,'Executive Pay Breakdown'!Q:Q)+SUMIF('Executive Pay Breakdown'!S:S,$B180,'Executive Pay Breakdown'!U:U)+SUMIF('Executive Pay Breakdown'!W:W,$B180,'Executive Pay Breakdown'!Y:Y)+SUMIF('Executive Pay Breakdown'!AA:AA,$B180,'Executive Pay Breakdown'!AC:AC) -> 10039613 | K180: =SUMIF('Executive Pay Breakdown'!K:K,$B180,'Executive Pay Breakdown'!M:M) -> 0 | L180: =SUMIF('Executive Pay Breakdown'!O:O,$B180,'Executive Pay Breakdown'!Q:Q) -> 0 | M180: =SUMIF('Executive Pay Breakdown'!S:S,$B180,'Executive Pay Breakdown'!U:U) -> 3034416 | N180: =SUMIF('Executive Pay Breakdown'!W:W,$B180,'Executive Pay Breakdown'!Y:Y) -> 3452058 | O180: =SUMIF('Executive Pay Breakdown'!AA:AA,$B180,'Executive Pay Breakdown'!AC:AC) -> 3553139
B181: Neal H. Shah | C181: {=INDEX('Executive Pay Breakdown'!B:B,MATCH(B181,'Executive Pay Breakdown'!K:K,0))} -> Pioneer Natural Resources | I181: =SUMIF('Executive Pay Breakdown'!K:K,$B181,'Executive Pay Breakdown'!M:M)+SUMIF('Executive Pay Breakdown'!O:O,$B181,'Executive Pay Breakdown'!Q:Q)+SUMIF('Executive Pay Breakdown'!S:S,$B181,'Executive Pay Breakdown'!U:U)+SUMIF('Executive Pay Breakdown'!W:W,$B181,'Executive Pay Breakdown'!Y:Y)+SUMIF('Executive Pay Breakdown'!AA:AA,$B181,'Executive Pay Breakdown'!AC:AC) -> 8386260 | K181: =SUMIF('Executive Pay Breakdown'!K:K,$B181,'Executive Pay Breakdown'!M:M) -> 5131346 | L181: =SUMIF('Executive Pay Breakdown'!O:O,$B181,'Executive Pay Breakdown'!Q:Q) -> 3254914 | M181: =SUMIF('Executive Pay Breakdown'!S:S,$B181,'Executive Pay Breakdown'!U:U) -> 0 | N181: =SUMIF('Executive Pay Breakdown'!W:W,$B181,'Executive Pay Breakdown'!Y:Y) -> 0 | O181: =SUMIF('Executive Pay Breakdown'!AA:AA,$B181,'Executive Pay Breakdown'!AC:AC) -> 0
A182: Yes | B182: Elon Musk | C182: Tesla | I182: =SUMIF('Executive Pay Breakdown'!K:K,$B182,'Executive Pay Breakdown'!M:M)+SUMIF('Executive Pay Breakdown'!O:O,$B182,'Executive Pay Breakdown'!Q:Q)+SUMIF('Executive Pay Breakdown'!S:S,$B182,'Executive Pay Breakdown'!U:U)+SUMIF('Executive Pay Breakdown'!W:W,$B182,'Executive Pay Breakdown'!Y:Y)+SUMIF('Executive Pay Breakdown'!AA:AA,$B182,'Executive Pay Breakdown'!AC:AC) -> 2284068644 | K182: =SUMIF('Executive Pay Breakdown'!K:K,$B182,'Executive Pay Breakdown'!M:M) -> 0 | L182: =SUMIF('Executive Pay Breakdown'!O:O,$B182,'Executive Pay Breakdown'!Q:Q) -> 0 | M182: =SUMIF('Executive Pay Breakdown'!S:S,$B182,'Executive Pay Breakdown'!U:U) -> 0 | N182: =SUMIF('Executive Pay Breakdown'!W:W,$B182,'Executive Pay Breakdown'!Y:Y) -> 23760 | O182: =SUMIF('Executive Pay Breakdown'!AA:AA,$B182,'Executive Pay Breakdown'!AC:AC) -> 2284044884
B183: John J. Legere | C183: T-Mobile US | I183: =SUMIF('Executive Pay Breakdown'!K:K,$B183,'Executive Pay Breakdown'!M:M)+SUMIF('Executive Pay Breakdown'!O:O,$B183,'Executive Pay Breakdown'!Q:Q)+SUMIF('Executive Pay Breakdown'!S:S,$B183,'Executive Pay Breakdown'!U:U)+SUMIF('Executive Pay Breakdown'!W:W,$B183,'Executive Pay Breakdown'!Y:Y)+SUMIF('Executive Pay Breakdown'!AA:AA,$B183,'Executive Pay Breakdown'!AC:AC) -> 231490784 | K183: =SUMIF('Executive Pay Breakdown'!K:K,$B183,'Executive Pay Breakdown'!M:M) -> 0 | L183: =SUMIF('Executive Pay Breakdown'!O:O,$B183,'Executive Pay Breakdown'!Q:Q) -> 0 | M183: =SUMIF('Executive Pay Breakdown'!S:S,$B183,'Executive Pay Breakdown'!U:U) -> 137195887 | N183: =SUMIF('Executive Pay Breakdown'!W:W,$B183,'Executive Pay Breakdown'!Y:Y) -> 27756690 | O183: =SUMIF('Executive Pay Breakdown'!AA:AA,$B183,'Executive Pay Breakdown'!AC:AC) -> 66538207
B184: Marc R. Bitzer | C184: {=INDEX('Executive Pay Breakdown'!B:B,MATCH(B184,'Executive Pay Breakdown'!K:K,0))} -> Whirlpool | I184: =SUMIF('Executive Pay Breakdown'!K:K,$B184,'Executive Pay Breakdown'!M:M)+SUMIF('Executive Pay Breakdown'!O:O,$B184,'Executive Pay Breakdown'!Q:Q)+SUMIF('Executive Pay Breakdown'!S:S,$B184,'Executive Pay Breakdown'!U:U)+SUMIF('Executive Pay Breakdown'!W:W,$B184,'Executive Pay Breakdown'!Y:Y)+SUMIF('Executive Pay Breakdown'!AA:AA,$B184,'Executive Pay Breakdown'!AC:AC) -> 73579112 | K184: =SUMIF('Executive Pay Breakdown'!K:K,$B184,'Executive Pay Breakdown'!M:M) -> 11940033 | L184: =SUMIF('Executive Pay Breakdown'!O:O,$B184,'Executive Pay Breakdown'!Q:Q) -> 18751901 | M184: =SUMIF('Executive Pay Breakdown'!S:S,$B184,'Executive Pay Breakdown'!U:U) -> 17051409 | N184: =SUMIF('Executive Pay Breakdown'!W:W,$B184,'Executive Pay Breakdown'!Y:Y) -> 13999494 | O184: =SUMIF('Executive Pay Breakdown'!AA:AA,$B184,'Executive Pay Breakdown'!AC:AC) -> 11836275
B185: Eugene I. Lee, Jr. | C185: {=INDEX('Executive Pay Breakdown'!B:B,MATCH(B185,'Executive Pay Breakdown'!O:O,0))} -> Darden Restaurants | I185: =SUMIF('Executive Pay Breakdown'!K:K,$B185,'Executive Pay Breakdown'!M:M)+SUMIF('Executive Pay Breakdown'!O:O,$B185,'Executive Pay Breakdown'!Q:Q)+SUMIF('Executive Pay Breakdown'!S:S,$B185,'Executive Pay Breakdown'!U:U)+SUMIF('Executive Pay Breakdown'!W:W,$B185,'Executive Pay Breakdown'!Y:Y)+SUMIF('Executive Pay Breakdown'!AA:AA,$B185,'Executive Pay Breakdown'!AC:AC) -> 41419312 | K185: =SUMIF('Executive Pay Breakdown'!K:K,$B185,'Executive Pay Breakdown'!M:M) -> 0 | L185: =SUMIF('Executive Pay Breakdown'!O:O,$B185,'Executive Pay Breakdown'!Q:Q) -> 11891841 | M185: =SUMIF('Executive Pay Breakdown'!S:S,$B185,'Executive Pay Breakdown'!U:U) -> 10128186 | N185: =SUMIF('Executive Pay Breakdown'!W:W,$B185,'Executive Pay Breakdown'!Y:Y) -> 8688707 | O185: =SUMIF('Executive Pay Breakdown'!AA:AA,$B185,'Executive Pay Breakdown'!AC:AC) -> 10710578
B186: M. H. McGarry | C186: {=INDEX('Executive Pay Breakdown'!B:B,MATCH(B186,'Executive Pay Breakdown'!K:K,0))} -> PPG Industries | I186: =SUMIF('Executive Pay Breakdown'!K:K,$B186,'Executive Pay Breakdown'!M:M)+SUMIF('Executive Pay Breakdown'!O:O,$B186,'Executive Pay Breakdown'!Q:Q)+SUMIF('Executive Pay Breakdown'!S:S,$B186,'Executive Pay Breakdown'!U:U)+SUMIF('Executive Pay Breakdown'!W:W,$B186,'Executive Pay Breakdown'!Y:Y)+SUMIF('Executive Pay Breakdown'!AA:AA,$B186,'Executive Pay Breakdown'!AC:AC) -> 64873328 | K186: =SUMIF('Executive Pay Breakdown'!K:K,$B186,'Executive Pay Breakdown'!M:M) -> 8867377 | L186: =SUMIF('Executive Pay Breakdown'!O:O,$B186,'Executive Pay Breakdown'!Q:Q) -> 13199616 | M186: =SUMIF('Executive Pay Breakdown'!S:S,$B186,'Executive Pay Breakdown'!U:U) -> 15903993 | N186: =SUMIF('Executive Pay Breakdown'!W:W,$B186,'Executive Pay Breakdown'!Y:Y) -> 15117938 | O186: =SUMIF('Executive Pay Breakdown'!AA:AA,$B186,'Executive Pay Breakdown'!AC:AC) -> 11784404
B187: Jerome Guillen | C187: Tesla | I187: =SUMIF('Executive Pay Breakdown'!K:K,$B187,'Executive Pay Breakdown'!M:M)+SUMIF('Executive Pay Breakdown'!O:O,$B187,'Executive Pay Breakdown'!Q:Q)+SUMIF('Executive Pay Breakdown'!S:S,$B187,'Executive Pay Breakdown'!U:U)+SUMIF('Executive Pay Breakdown'!W:W,$B187,'Executive Pay Breakdown'!Y:Y)+SUMIF('Executive Pay Breakdown'!AA:AA,$B187,'Executive Pay Breakdown'!AC:AC) -> 72724424 | K187: =SUMIF('Executive Pay Breakdown'!K:K,$B187,'Executive Pay Breakdown'!M:M) -> 0 | L187: =SUMIF('Executive Pay Breakdown'!O:O,$B187,'Executive Pay Breakdown'!Q:Q) -> 161538 | M187: =SUMIF('Executive Pay Breakdown'!S:S,$B187,'Executive Pay Breakdown'!U:U) -> 46544623 | N187: =SUMIF('Executive Pay Breakdown'!W:W,$B187,'Executive Pay Breakdown'!Y:Y) -> 8266212 | O187: =SUMIF('Executive Pay Breakdown'!AA:AA,$B187,'Executive Pay Breakdown'!AC:AC) -> 17752051
B188: Zachary Kirkhorn | C188: Tesla | I188: =SUMIF('Executive Pay Breakdown'!K:K,$B188,'Executive Pay Breakdown'!M:M)+SUMIF('Executive Pay Breakdown'!O:O,$B188,'Executive Pay Breakdown'!Q:Q)+SUMIF('Executive Pay Breakdown'!S:S,$B188,'Executive Pay Breakdown'!U:U)+SUMIF('Executive Pay Breakdown'!W:W,$B188,'Executive Pay Breakdown'!Y:Y)+SUMIF('Executive Pay Breakdown'!AA:AA,$B188,'Executive Pay Breakdown'!AC:AC) -> 68410227 | K188: =SUMIF('Executive Pay Breakdown'!K:K,$B188,'Executive Pay Breakdown'!M:M) -> 303000 | L188: =SUMIF('Executive Pay Breakdown'!O:O,$B188,'Executive Pay Breakdown'!Q:Q) -> 301154 | M188: =SUMIF('Executive Pay Breakdown'!S:S,$B188,'Executive Pay Breakdown'!U:U) -> 46562116 | N188: =SUMIF('Executive Pay Breakdown'!W:W,$B188,'Executive Pay Breakdown'!Y:Y) -> 21243957 | O188: =SUMIF('Executive Pay Breakdown'!AA:AA,$B188,'Executive Pay Breakdown'!AC:AC) -> 0
B189: Ricardo Cardenas | C189: {=INDEX('Executive Pay Breakdown'!B:B,MATCH(B189,'Executive Pay Breakdown'!K:K,0))} -> Darden Restaurants | I189: =SUMIF('Executive Pay Breakdown'!K:K,$B189,'Executive Pay Breakdown'!M:M)+SUMIF('Executive Pay Breakdown'!O:O,$B189,'Executive Pay Breakdown'!Q:Q)+SUMIF('Executive Pay Breakdown'!S:S,$B189,'Executive Pay Breakdown'!U:U)+SUMIF('Executive Pay Breakdown'!W:W,$B189,'Executive Pay Breakdown'!Y:Y)+SUMIF('Executive Pay Breakdown'!AA:AA,$B189,'Executive Pay Breakdown'!AC:AC) -> 23597363 | K189: =SUMIF('Executive Pay Breakdown'!K:K,$B189,'Executive Pay Breakdown'!M:M) -> 8500029 | L189: =SUMIF('Executive Pay Breakdown'!O:O,$B189,'Executive Pay Breakdown'!Q:Q) -> 4709282 | M189: =SUMIF('Executive Pay Breakdown'!S:S,$B189,'Executive Pay Breakdown'!U:U) -> 3756954 | N189: =SUMIF('Executive Pay Breakdown'!W:W,$B189,'Executive Pay Breakdown'!Y:Y) -> 3204365 | O189: =SUMIF('Executive Pay Breakdown'!AA:AA,$B189,'Executive Pay Breakdown'!AC:AC) -> 3426733
B190: Steven H. Collis | C190: {=INDEX('Executive Pay Breakdown'!B:B,MATCH(B190,'Executive Pay Breakdown'!K:K,0))} -> AmerisourceBergen | I190: =SUMIF('Executive Pay Breakdown'!K:K,$B190,'Executive Pay Breakdown'!M:M)+SUMIF('Executive Pay Breakdown'!O:O,$B190,'Executive Pay Breakdown'!Q:Q)+SUMIF('Executive Pay Breakdown'!S:S,$B190,'Executive Pay Breakdown'!U:U)+SUMIF('Executive Pay Breakdown'!W:W,$B190,'Executive Pay Breakdown'!Y:Y)+SUMIF('Executive Pay Breakdown'!AA:AA,$B190,'Executive Pay Breakdown'!AC:AC) -> 68728752 | K190: =SUMIF('Executive Pay Breakdown'!K:K,$B190,'Executive Pay Breakdown'!M:M) -> 16735752 | L190: =SUMIF('Executive Pay Breakdown'!O:O,$B190,'Executive Pay Breakdown'!Q:Q) -> 14873815 | M190: =SUMIF('Executive Pay Breakdown'!S:S,$B190,'Executive Pay Breakdown'!U:U) -> 14295140 | N190: =SUMIF('Executive Pay Breakdown'!W:W,$B190,'Executive Pay Breakdown'!Y:Y) -> 11309930 | O190: =SUMIF('Executive Pay Breakdown'!AA:AA,$B190,'Executive Pay Breakdown'!AC:AC) -> 11514115
B191: Andrew Baglino | C191: Tesla | I191: =SUMIF('Executive Pay Breakdown'!K:K,$B191,'Executive Pay Breakdown'!M:M)+SUMIF('Executive Pay Breakdown'!O:O,$B191,'Executive Pay Breakdown'!Q:Q)+SUMIF('Executive Pay Breakdown'!S:S,$B191,'Executive Pay Breakdown'!U:U)+SUMIF('Executive Pay Breakdown'!W:W,$B191,'Executive Pay Breakdown'!Y:Y)+SUMIF('Executive Pay Breakdown'!AA:AA,$B191,'Executive Pay Breakdown'!AC:AC) -> 52229011 | K191: =SUMIF('Executive Pay Breakdown'!K:K,$B191,'Executive Pay Breakdown'!M:M) -> 303000 | L191: =SUMIF('Executive Pay Breakdown'!O:O,$B191,'Executive Pay Breakdown'!Q:Q) -> 301154 | M191: =SUMIF('Executive Pay Breakdown'!S:S,$B191,'Executive Pay Breakdown'!U:U) -> 46544623 | N191: =SUMIF('Executive Pay Breakdown'!W:W,$B191,'Executive Pay Breakdown'!Y:Y) -> 5080234 | O191: =SUMIF('Executive Pay Breakdown'!AA:AA,$B191,'Executive Pay Breakdown'!AC:AC) -> 0
B192: Randall L. Stephenson | C192: AT&T | I192: =SUMIF('Executive Pay Breakdown'!K:K,$B192,'Executive Pay Breakdown'!M:M)+SUMIF('Executive Pay Breakdown'!O:O,$B192,'Executive Pay Breakdown'!Q:Q)+SUMIF('Executive Pay Breakdown'!S:S,$B192,'Executive Pay Breakdown'!U:U)+SUMIF('Executive Pay Breakdown'!W:W,$B192,'Executive Pay Breakdown'!Y:Y)+SUMIF('Executive Pay Breakdown'!AA:AA,$B192,'Executive Pay Breakdown'!AC:AC) -> 106651170 | K192: =SUMIF('Executive Pay Breakdown'!K:K,$B192,'Executive Pay Breakdown'!M:M) -> 0 | L192: =SUMIF('Executive Pay Breakdown'!O:O,$B192,'Executive Pay Breakdown'!Q:Q) -> 16345499 | M192: =SUMIF('Executive Pay Breakdown'!S:S,$B192,'Executive Pay Breakdown'!U:U) -> 29154628 | N192: =SUMIF('Executive Pay Breakdown'!W:W,$B192,'Executive Pay Breakdown'!Y:Y) -> 32032925 | O192: =SUMIF('Executive Pay Breakdown'!AA:AA,$B192,'Executive Pay Breakdown'!AC:AC) -> 29118118
B193: Joseph T. Liotine | C193: {=INDEX('Executive Pay Breakdown'!B:B,MATCH(B193,'Executive Pay Breakdown'!K:K,0))} -> Whirlpool | I193: =SUMIF('Executive Pay Breakdown'!K:K,$B193,'Executive Pay Breakdown'!M:M)+SUMIF('Executive Pay Breakdown'!O:O,$B193,'Executive Pay Breakdown'!Q:Q)+SUMIF('Executive Pay Breakdown'!S:S,$B193,'Executive Pay Breakdown'!U:U)+SUMIF('Executive Pay Breakdown'!W:W,$B193,'Executive Pay Breakdown'!Y:Y)+SUMIF('Executive Pay Breakdown'!AA:AA,$B193,'Executive Pay Breakdown'!AC:AC) -> 25556422 | K193: =SUMIF('Executive Pay Breakdown'!K:K,$B193,'Executive Pay Breakdown'!M:M) -> 4941682 | L193: =SUMIF('Executive Pay Breakdown'!O:O,$B193,'Executive Pay Breakdown'!Q:Q) -> 6869686 | M193: =SUMIF('Executive Pay Breakdown'!S:S,$B193,'Executive Pay Breakdown'!U:U) -> 6178417 | N193: =SUMIF('Executive Pay Breakdown'!W:W,$B193,'Executive Pay Breakdown'!Y:Y) -> 4796558 | O193: =SUMIF('Executive Pay Breakdown'!AA:AA,$B193,'Executive Pay Breakdown'!AC:AC) -> 2770079
B194: James W. Peters | C194: {=INDEX('Executive Pay Breakdown'!B:B,MATCH(B194,'Executive Pay Breakdown'!K:K,0))} -> Whirlpool | I194: =SUMIF('Executive Pay Breakdown'!K:K,$B194,'Executive Pay Breakdown'!M:M)+SUMIF('Executive Pay Breakdown'!O:O,$B194,'Executive Pay Breakdown'!Q:Q)+SUMIF('Executive Pay Breakdown'!S:S,$B194,'Executive Pay Breakdown'!U:U)+SUMIF('Executive Pay Breakdown'!W:W,$B194,'Executive Pay Breakdown'!Y:Y)+SUMIF('Executive Pay Breakdown'!AA:AA,$B194,'Executive Pay Breakdown'!AC:AC) -> 24488336 | K194: =SUMIF('Executive Pay Breakdown'!K:K,$B194,'Executive Pay Breakdown'!M:M) -> 3868145 | L194: =SUMIF('Executive Pay Breakdown'!O:O,$B194,'Executive Pay Breakdown'!Q:Q) -> 8331820 | M194: =SUMIF('Executive Pay Breakdown'!S:S,$B194,'Executive Pay Breakdown'!U:U) -> 5389599 | N194: =SUMIF('Executive Pay Breakdown'!W:W,$B194,'Executive Pay Breakdown'!Y:Y) -> 4007186 | O194: =SUMIF('Executive Pay Breakdown'!AA:AA,$B194,'Executive Pay Breakdown'!AC:AC) -> 2891586
B195: Brian Duperreault | C195: American International Group | I195: =SUMIF('Executive Pay Breakdown'!K:K,$B195,'Executive Pay Breakdown'!M:M)+SUMIF('Executive Pay Breakdown'!O:O,$B195,'Executive Pay Breakdown'!Q:Q)+SUMIF('Executive Pay Breakdown'!S:S,$B195,'Executive Pay Breakdown'!U:U)+SUMIF('Executive Pay Breakdown'!W:W,$B195,'Executive Pay Breakdown'!Y:Y)+SUMIF('Executive Pay Breakdown'!AA:AA,$B195,'Executive Pay Breakdown'!AC:AC) -> 73004217 | K195: =SUMIF('Executive Pay Breakdown'!K:K,$B195,'Executive Pay Breakdown'!M:M) -> 0 | L195: =SUMIF('Executive Pay Breakdown'!O:O,$B195,'Executive Pay Breakdown'!Q:Q) -> 13969537 | M195: =SUMIF('Executive Pay Breakdown'!S:S,$B195,'Executive Pay Breakdown'!U:U) -> 18810374 | N195: =SUMIF('Executive Pay Breakdown'!W:W,$B195,'Executive Pay Breakdown'!Y:Y) -> 19369637 | O195: =SUMIF('Executive Pay Breakdown'!AA:AA,$B195,'Executive Pay Breakdown'!AC:AC) -> 20854669
B196: Douglas M. Baker, Jr. | C196: Ecolab | I196: =SUMIF('Executive Pay Breakdown'!K:K,$B196,'Executive Pay Breakdown'!M:M)+SUMIF('Executive Pay Breakdown'!O:O,$B196,'Executive Pay Breakdown'!Q:Q)+SUMIF('Executive Pay Breakdown'!S:S,$B196,'Executive Pay Breakdown'!U:U)+SUMIF('Executive Pay Breakdown'!W:W,$B196,'Executive Pay Breakdown'!Y:Y)+SUMIF('Executive Pay Breakdown'!AA:AA,$B196,'Executive Pay Breakdown'!AC:AC) -> 53528145 | K196: =SUMIF('Executive Pay Breakdown'!K:K,$B196,'Executive Pay Breakdown'!M:M) -> 0 | L196: =SUMIF('Executive Pay Breakdown'!O:O,$B196,'Executive Pay Breakdown'!Q:Q) -> 2455739 | M196: =SUMIF('Executive Pay Breakdown'!S:S,$B196,'Executive Pay Breakdown'!U:U) -> 16905180 | N196: =SUMIF('Executive Pay Breakdown'!W:W,$B196,'Executive Pay Breakdown'!Y:Y) -> 19803193 | O196: =SUMIF('Executive Pay Breakdown'!AA:AA,$B196,'Executive Pay Breakdown'!AC:AC) -> 14364033
B197: John Bickham | C197: Charter Communications | I197: =SUMIF('Executive Pay Breakdown'!K:K,$B197,'Executive Pay Breakdown'!M:M)+SUMIF('Executive Pay Breakdown'!O:O,$B197,'Executive Pay Breakdown'!Q:Q)+SUMIF('Executive Pay Breakdown'!S:S,$B197,'Executive Pay Breakdown'!U:U)+SUMIF('Executive Pay Breakdown'!W:W,$B197,'Executive Pay Breakdown'!Y:Y)+SUMIF('Executive Pay Breakdown'!AA:AA,$B197,'Executive Pay Breakdown'!AC:AC) -> 53693459 | K197: =SUMIF('Executive Pay Breakdown'!K:K,$B197,'Executive Pay Breakdown'!M:M) -> 0 | L197: =SUMIF('Executive Pay Breakdown'!O:O,$B197,'Executive Pay Breakdown'!Q:Q) -> 7470953 | M197: =SUMIF('Executive Pay Breakdown'!S:S,$B197,'Executive Pay Breakdown'!U:U) -> 36455947 | N197: =SUMIF('Executive Pay Breakdown'!W:W,$B197,'Executive Pay Breakdown'!Y:Y) -> 5037405 | O197: =SUMIF('Executive Pay Breakdown'!AA:AA,$B197,'Executive Pay Breakdown'!AC:AC) -> 4729154
B198: David R. Carey | C198: T-Mobile US | I198: =SUMIF('Executive Pay Breakdown'!K:K,$B198,'Executive Pay Breakdown'!M:M)+SUMIF('Executive Pay Breakdown'!O:O,$B198,'Executive Pay Breakdown'!Q:Q)+SUMIF('Executive Pay Breakdown'!S:S,$B198,'Executive Pay Breakdown'!U:U)+SUMIF('Executive Pay Breakdown'!W:W,$B198,'Executive Pay Breakdown'!Y:Y)+SUMIF('Executive Pay Breakdown'!AA:AA,$B198,'Executive Pay Breakdown'!AC:AC) -> 53617171 | K198: =SUMIF('Executive Pay Breakdown'!K:K,$B198,'Executive Pay Breakdown'!M:M) -> 0 | L198: =SUMIF('Executive Pay Breakdown'!O:O,$B198,'Executive Pay Breakdown'!Q:Q) -> 0 | M198: =SUMIF('Executive Pay Breakdown'!S:S,$B198,'Executive Pay Breakdown'!U:U) -> 29847619 | N198: =SUMIF('Executive Pay Breakdown'!W:W,$B198,'Executive Pay Breakdown'!Y:Y) -> 7915575 | O198: =SUMIF('Executive Pay Breakdown'!AA:AA,$B198,'Executive Pay Breakdown'!AC:AC) -> 15853977
B199: Todd A. Burrowes | C199: {=INDEX('Executive Pay Breakdown'!B:B,MATCH(B199,'Executive Pay Breakdown'!K:K,0))} -> Darden Restaurants | I199: =SUMIF('Executive Pay Breakdown'!K:K,$B199,'Executive Pay Breakdown'!M:M)+SUMIF('Executive Pay Breakdown'!O:O,$B199,'Executive Pay Breakdown'!Q:Q)+SUMIF('Executive Pay Breakdown'!S:S,$B199,'Executive Pay Breakdown'!U:U)+SUMIF('Executive Pay Breakdown'!W:W,$B199,'Executive Pay Breakdown'!Y:Y)+SUMIF('Executive Pay Breakdown'!AA:AA,$B199,'Executive Pay Breakdown'!AC:AC) -> 14343110 | K199: =SUMIF('Executive Pay Breakdown'!K:K,$B199,'Executive Pay Breakdown'!M:M) -> 3026160 | L199: =SUMIF('Executive Pay Breakdown'!O:O,$B199,'Executive Pay Breakdown'!Q:Q) -> 3102699 | M199: =SUMIF('Executive Pay Breakdown'!S:S,$B199,'Executive Pay Breakdown'!U:U) -> 2693769 | N199: =SUMIF('Executive Pay Breakdown'!W:W,$B199,'Executive Pay Breakdown'!Y:Y) -> 2719627 | O199: =SUMIF('Executive Pay Breakdown'!AA:AA,$B199,'Executive Pay Breakdown'!AC:AC) -> 2800855
...

Sheet Key Findings
A1: Rank | B1: Corporate Pay 2022–2018 | C1: Home State | D1: Corporate Executive Annual Pay | K1: Corporate Pay > Federal Taxes | R1: Domestic Pre-Tax Income ($ millions) | Y1: Federal Income Tax ($ millions) | AF1: Current Federal Income Tax Rate | AM1: Stock Buybacks ($ millions) | AT1: Dividend Payouts ($ millions) | BA1: Median Worker Pay | BJ1: SEC Sources
D2: Five-Year | E2: 2022 | F2: 2021 | G2: 2020 | H2: 2019 | I2: 2018 | R2: Five-Year | S2: 2022 | T2: 2021 | U2: 2020 | V2: 2019 | W2: 2018 | Y2: Five-Year | Z2: 2022 | AA2: 2021 | AB2: 2020 | AC2: 2019 | AD2: 2018 | AF2: Five-Year | AG2: 2022 | AH2: 2021 | AI2: 2020 | AJ2: 2019 | AK2: 2018 | AM2: Five-Year | AN2: 2022 | AO2: 2021 | AP2: 2020 | AQ2: 2019 | AR2: 2018 | AT2: Five-Year | AU2: 2022 | AV2: 2021 | AW2: 2020 | AX2: 2019 | AY2: 2018 | BA2: Average | BC2: 2022 | BD2: 2021 | BE2: 2020 | BF2: 2019 | BG2: 2018
D3: =SUM(D4:D75) -> 15096785826 | E3: =SUM(E4:E75) -> 2618334094 | F3: =SUM(F4:F75) -> 2597289646 | G3: =SUM(G4:G75) -> 2884035793 | H3: =SUM(H4:H75) -> 2407324953 | I3: =SUM(I4:I75) -> 4589801340 | K3: Five-Years | L3: 2022 | M3: 2021 | N3: 2020 | O3: 2019 | P3: 2018 | R3: =SUM(R4:R75) -> 657716.02 | S3: =SUM(S4:S75) -> 203498.67 | T3: =SUM(T4:T75) -> 175895.46 | U3: =SUM(U4:U75) -> 62581.61 | V3: =SUM(V4:V75) -> 108501.69 | W3: =SUM(W4:W75) -> 107238.59 | Y3: =SUM(Y4:Y75) -> 18291.71 | Z3: =SUM(Z4:Z75) -> 15796.39 | AA3: =SUM(AA4:AA75) -> 3485.49 | AB3: =SUM(AB4:AB75) -> -4132.11 | AC3: =SUM(AC4:AC75) -> 354.02 | AD3: =SUM(AD4:AD75) -> 2787.92 | AF3: =Y3/R3 -> 0.027810954 | AG3: =Z3/S3 -> 0.077624045 | AH3: =AA3/T3 -> 0.019815691 | AI3: =AB3/U3 -> -0.066027544 | AJ3: =AC3/V3 -> 0.0032628063 | AK3: =AD3/W3 -> 0.025997358 | AM3: =SUM(AM4:AM75) -> 247482.79 | AN3: =SUM(AN4:AN75) -> 76557.852 | AO3: =SUM(AO4:AO75) -> 50163.173 | AP3: =SUM(AP4:AP75) -> 51436.268 | AQ3: =SUM(AQ4:AQ75) -> 32634.3 | AR3: =SUM(AR4:AR75) -> 36691.199 | AT3: =SUM(AT4:AT75) -> 365114.99 | AU3: =SUM(AU4:AU75) -> 79843.097 | AV3: =SUM(AV4:AV75) -> 75607.728 | AW3: =SUM(AW4:AW75) -> 72248.12 | AX3: =SUM(AX4:AX75) -> 71770.11 | AY3: =SUM(AY4:AY75) -> 65645.94 | BA3: =AVERAGE(BA4:BA57) -> 104290.48 | BC3: =AVERAGE(BC4:BC57) -> 106042.81 | BD3: =AVERAGE(BD4:BD57) -> 105473.77 | BE3: =AVERAGE(BE4:BE57) -> 106229.26 | BF3: =AVERAGE(BF4:BF57) -> 108496.48 | BG3: =AVERAGE(BG4:BG57) -> 95006.981
A4: {=INDEX('Federal Tax, Stock Buybacks, & '!D:D,match(B4,'Federal Tax, Stock Buybacks, & '!E:E,0))} -> 50 | B4: Tesla | C4: Texas | D4: =SUMIF('Executive Pay Breakdown'!B:B,$B4,'Executive Pay Breakdown'!M:M)+SUMIF('Executive Pay Breakdown'!B:B,$B4,'Executive Pay Breakdown'!Q:Q)+SUMIF('Executive Pay Breakdown'!B:B,$B4,'Executive Pay Breakdown'!U:U)+SUMIF('Executive Pay Breakdown'!B:B,$B4,'Executive Pay Breakdown'!Y:Y)+SUMIF('Executive Pay Breakdown'!B:B,$B4,'Executive Pay Breakdown'!AC:AC) -> 2495486949 | E4: =SUMIF('Executive Pay Breakdown'!B:B,$B4,'Executive Pay Breakdown'!M:M) -> 606000 | F4: =SUMIF('Executive Pay Breakdown'!B:B,$B4,'Executive Pay Breakdown'!Q:Q) -> 763846 | G4: =SUMIF('Executive Pay Breakdown'!B:B,$B4,'Executive Pay Breakdown'!U:U) -> 139651362 | H4: =SUMIF('Executive Pay Breakdown'!B:B,$B4,'Executive Pay Breakdown'!Y:Y) -> 34791033 | I4: =SUMIF('Executive Pay Breakdown'!B:B,$B4,'Executive Pay Breakdown'!AC:AC) -> 2319674708 | K4: YES | L4: =(E4/1000000)>(Z4) -> TRUE | M4: =(F4/1000000)>(AA4) -> TRUE | N4: =(G4/1000000)>(AB4) -> TRUE | O4: =(H4/1000000)>(AC4) -> TRUE | P4: =(I4/1000000)>(AD4) -> TRUE | R4: =SUM(S4:W4) -> 4426 | S4: {=INDEX('Federal Tax, Stock Buybacks, & '!U:U,MATCH($B4,'Federal Tax, Stock Buybacks, & '!$E:$E,0))} -> 5474 | T4: {=INDEX('Federal Tax, Stock Buybacks, & '!V:V,MATCH($B4,'Federal Tax, Stock Buybacks, & '!$E:$E,0))} -> -139 | U4: {=INDEX('Federal Tax, Stock Buybacks, & '!W:W,MATCH($B4,'Federal Tax, Stock Buybacks, & '!$E:$E,0))} -> -202 | V4: {=INDEX('Federal Tax, Stock Buybacks, & '!X:X,MATCH($B4,'Federal Tax, Stock Buybacks, & '!$E:$E,0))} -> -292 | W4: {=INDEX('Federal Tax, Stock Buybacks, & '!Y:Y,MATCH($B4,'Federal Tax, Stock Buybacks, & '!$E:$E,0))} -> -415 | Y4: =SUM(Z4:AD4) -> -1 | Z4: {=INDEX('Federal Tax, Stock Buybacks, & '!AB:AB,MATCH($B4,'Federal Tax, Stock Buybacks, & '!$E:$E,0))} -> 0 | AA4: {=INDEX('Federal Tax, Stock Buybacks, & '!AC:AC,MATCH($B4,'Federal Tax, Stock Buybacks, & '!$E:$E,0))} -> 0 | AB4: {=INDEX('Federal Tax, Stock Buybacks, & '!AD:AD,MATCH($B4,'Federal Tax, Stock Buybacks, & '!$E:$E,0))} -> 0 | AC4: {=INDEX('Federal Tax, Stock Buybacks, & '!AE:AE,MATCH($B4,'Federal Tax, Stock Buybacks, & '!$E:$E,0))} -> 0 | AD4: {=INDEX('Federal Tax, Stock Buybacks, & '!AF:AF,MATCH($B4,'Federal Tax, Stock Buybacks, & '!$E:$E,0))} -> -1 | AF4: =Y4/R4 -> -0.00022593764 | AG4: =Z4/S4 -> 0 | AH4: =AA4/T4 -> 0 | AI4: =AB4/U4 -> 0 | AJ4: =AC4/V4 -> 0 | AK4: =AD4/W4 -> 0.0024096386 | AM4: =SUM(AN4:AR4) -> 0 | AN4: {=INDEX('Federal Tax, Stock Buybacks, & '!AP:AP,MATCH($B4,'Federal Tax, Stock Buybacks, & '!$E:$E,0))} -> 0 | AO4: {=INDEX('Federal Tax, Stock Buybacks, & '!AQ:AQ,MATCH($B4,'Federal Tax, Stock Buybacks, & '!$E:$E,0))} -> 0 | AP4: {=INDEX('Federal Tax, Stock Buybacks, & '!AR:AR,MATCH($B4,'Federal Tax, Stock Buybacks, & '!$E:$E,0))} -> 0 | AQ4: {=INDEX('Federal Tax, Stock Buybacks, & '!AS:AS,MATCH($B4,'Federal Tax, Stock Buybacks, & '!$E:$E,0))} -> 0 | AR4: {=INDEX('Federal Tax, Stock Buybacks, & '!AT:AT,MATCH($B4,'Federal Tax, Stock Buybacks, & '!$E:$E,0))} -> 0 | AT4: =SUM(AU4:AY4) -> 0 | AU4: {=INDEX('Federal Tax, Stock Buybacks, & '!AW:AW,MATCH($B4,'Federal Tax, Stock Buybacks, & '!$E:$E,0))} -> 0 | AV4: {=INDEX('Federal Tax, Stock Buybacks, & '!AX:AX,MATCH($B4,'Federal Tax, Stock Buybacks, & '!$E:$E,0))} -> 0 | AW4: {=INDEX('Federal Tax, Stock Buybacks, & '!AY:AY,MATCH($B4,'Federal Tax, Stock Buybacks, & '!$E:$E,0))} -> 0 | AX4: {=INDEX('Federal Tax, Stock Buybacks, & '!AZ:AZ,MATCH($B4,'Federal Tax, Stock Buybacks, & '!$E:$E,0))} -> 0 | AY4: {=INDEX('Federal Tax, Stock Buybacks, & '!BA:BA,MATCH($B4,'Federal Tax, Stock Buybacks, & '!$E:$E,0))} -> 0 | BA4: =AVERAGE(BC4:BG4) -> 47115 | BB4: =sum(BC4:BG4) -> 235575 | BC4: 34084 | BD4: 40723 | BE4: 46150 | BF4: 58455 | BG4: 56163 | BJ4: Link
A5: {=INDEX('Federal Tax, Stock Buybacks, & '!D:D,match(B5,'Federal Tax, Stock Buybacks, & '!E:E,0))} -> 76 | B5: American International Group | C5: New York | D5: =SUMIF('Executive Pay Breakdown'!B:B,$B5,'Executive Pay Breakdown'!M:M)+SUMIF('Executive Pay Breakdown'!B:B,$B5,'Executive Pay Breakdown'!Q:Q)+SUMIF('Executive Pay Breakdown'!B:B,$B5,'Executive Pay Breakdown'!U:U)+SUMIF('Executive Pay Breakdown'!B:B,$B5,'Executive Pay Breakdown'!Y:Y)+SUMIF('Executive Pay Breakdown'!B:B,$B5,'Executive Pay Breakdown'!AC:AC) -> 406143128 | E5: =SUMIF('Executive Pay Breakdown'!B:B,$B5,'Executive Pay Breakdown'!M:M) -> 111662835 | F5: =SUMIF('Executive Pay Breakdown'!B:B,$B5,'Executive Pay Breakdown'!Q:Q) -> 88259311 | G5: =SUMIF('Executive Pay Breakdown'!B:B,$B5,'Executive Pay Breakdown'!U:U) -> 78205186 | H5: =SUMIF('Executive Pay Breakdown'!B:B,$B5,'Executive Pay Breakdown'!Y:Y) -> 64353553 | I5: =SUMIF('Executive Pay Breakdown'!B:B,$B5,'Executive Pay Breakdown'!AC:AC) -> 63662243 | K5: YES | M5: =(F5/1000000)>(AA5) -> TRUE | N5: =(G5/1000000)>(AB5) -> TRUE | R5: =SUM(S5:W5) -> 17687 | S5: {=INDEX('Federal Tax, Stock Buybacks, & '!U:U,MATCH($B5,'Federal Tax, Stock Buybacks, & '!$E:$E,0))} -> 12432 | T5: {=INDEX('Federal Tax, Stock Buybacks, & '!V:V,MATCH($B5,'Federal Tax, Stock Buybacks, & '!$E:$E,0))} -> 9838 | U5: {=INDEX('Federal Tax, Stock Buybacks, & '!W:W,MATCH($B5,'Federal Tax, Stock Buybacks, & '!$E:$E,0))} -> -8396 | V5: {=INDEX('Federal Tax, Stock Buybacks, & '!X:X,MATCH($B5,'Federal Tax, Stock Buybacks, & '!$E:$E,0))} -> 3825 | W5: {=INDEX('Federal Tax, Stock Buybacks, & '!Y:Y,MATCH($B5,'Federal Tax, Stock Buybacks, & '!$E:$E,0))} -> -12 | Y5: =SUM(Z5:AD5) -> 385 | Z5: {=INDEX('Federal Tax, Stock Buybacks, & '!AB:AB,MATCH($B5,'Federal Tax, Stock Buybacks, & '!$E:$E,0))} -> 246 | AA5: {=INDEX('Federal Tax, Stock Buybacks, & '!AC:AC,MATCH($B5,'Federal Tax, Stock Buybacks, & '!$E:$E,0))} -> -216 | AB5: {=INDEX('Federal Tax, Stock Buybacks, & '!AD:AD,MATCH($B5,'Federal Tax, Stock Buybacks, & '!$E:$E,0))} -> -57 | AC5: {=INDEX('Federal Tax, Stock Buybacks, & '!AE:AE,MATCH($B5,'Federal Tax, Stock Buybacks, & '!$E:$E,0))} -> 278 | AD5: {=INDEX('Federal Tax, Stock Buybacks, & '!AF:AF,MATCH($B5,'Federal Tax, Stock Buybacks, & '!$E:$E,0))} -> 134 | AF5: =Y5/R5 -> 0.0217674 | AG5: =Z5/S5 -> 0.019787645 | AH5: =AA5/T5 -> -0.021955682 | AI5: =AB5/U5 -> 0.0067889471 | AJ5: =AC5/V5 -> 0.072679739 | AK5: =AD5/W5 -> -11.166667 | AM5: =SUM(AN5:AR5) -> 10037 | AN5: {=INDEX('Federal Tax, Stock Buybacks, & '!AP:AP,MATCH($B5,'Federal Tax, Stock Buybacks, & '!$E:$E,0))} -> 5200 | AO5: {=INDEX('Federal Tax, Stock Buybacks, & '!AQ:AQ,MATCH($B5,'Federal Tax, Stock Buybacks, & '!$E:$E,0))} -> 2598 | AP5: {=INDEX('Federal Tax, Stock Buybacks, & '!AR:AR,MATCH($B5,'Federal Tax, Stock Buybacks, & '!$E:$E,0))} -> 500 | AQ5: {=INDEX('Federal Tax, Stock Buybacks, & '!AS:AS,MATCH($B5,'Federal Tax, Stock Buybacks, & '!$E:$E,0))} -> 0 | AR5: {=INDEX('Federal Tax, Stock Buybacks, & '!AT:AT,MATCH($B5,'Federal Tax, Stock Buybacks, & '!$E:$E,0))} -> 1739 | AT5: =SUM(AU5:AY5) -> 5529 | AU5: {=INDEX('Federal Tax, Stock Buybacks, & '!AW:AW,MATCH($B5,'Federal Tax, Stock Buybacks, & '!$E:$E,0))} -> 1011 | AV5: {=INDEX('Federal Tax, Stock Buybacks, & '!AX:AX,MATCH($B5,'Federal Tax, Stock Buybacks, & '!$E:$E,0))} -> 1112 | AW5: {=INDEX('Federal Tax, Stock Buybacks, & '!AY:AY,MATCH($B5,'Federal Tax, Stock Buybacks, & '!$E:$E,0))} -> 1132 | AX5: {=INDEX('Federal Tax, Stock Buybacks, & '!AZ:AZ,MATCH($B5,'Federal Tax, Stock Buybacks, & '!$E:$E,0))} -> 1136 | AY5: {=INDEX('Federal Tax, Stock Buybacks, & '!BA:BA,MATCH($B5,'Federal Tax, Stock Buybacks, & '!$E:$E,0))} -> 1138 | BA5: =AVERAGE(BC5:BG5) -> 72189 | BB5: =sum(BC5:BG5) -> 360945 | BC5: 84240 | BD5: 71936 | BE5: 70926 | BF5: 67403 | BG5: 66440 | BJ5: Link
A6: {=INDEX('Federal Tax, Stock Buybacks, & '!D:D,match(B6,'Federal Tax, Stock Buybacks, & '!E:E,0))} -> 54 | B6: MetLife | D6: =SUMIF('Executive Pay Breakdown'!B:B,$B6,'Executive Pay Breakdown'!M:M)+SUMIF('Executive Pay Breakdown'!B:B,$B6,'Executive Pay Breakdown'!Q:Q)+SUMIF('Executive Pay Breakdown'!B:B,$B6,'Executive Pay Breakdown'!U:U)+SUMIF('Executive Pay Breakdown'!B:B,$B6,'Executive Pay Breakdown'!Y:Y)+SUMIF('Executive Pay Breakdown'!B:B,$B6,'Executive Pay Breakdown'!AC:AC) -> 239636188 | E6: =SUMIF('Executive Pay Breakdown'!B:B,$B6,'Executive Pay Breakdown'!M:M) -> 47987552 | F6: =SUMIF('Executive Pay Breakdown'!B:B,$B6,'Executive Pay Breakdown'!Q:Q) -> 44131279 | G6: =SUMIF('Executive Pay Breakdown'!B:B,$B6,'Executive Pay Breakdown'!U:U) -> 41818878 | H6: =SUMIF('Executive Pay Breakdown'!B:B,$B6,'Executive Pay Breakdown'!Y:Y) -> 54688507 | I6: =SUMIF('Executive Pay Breakdown'!B:B,$B6,'Executive Pay Breakdown'!AC:AC) -> 51009972 | K6: YES | O6: =(H6/1000000)>(AC6) -> TRUE | P6: =(I6/1000000)>(AD6) -> TRUE | R6: =SUM(S6:W6) -> 11658 | S6: {=INDEX('Federal Tax, Stock Buybacks, & '!U:U,MATCH($B6,'Federal Tax, Stock Buybacks, & '!$E:$E,0))} -> 2636 | T6: {=INDEX('Federal Tax, Stock Buybacks, & '!V:V,MATCH($B6,'Federal Tax, Stock Buybacks, & '!$E:$E,0))} -> 4803 | U6: {=INDEX('Federal Tax, Stock Buybacks, & '!W:W,MATCH($B6,'Federal Tax, Stock Buybacks, & '!$E:$E,0))} -> 2943 | V6: {=INDEX('Federal Tax, Stock Buybacks, & '!X:X,MATCH($B6,'Federal Tax, Stock Buybacks, & '!$E:$E,0))} -> 2090 | W6: {=INDEX('Federal Tax, Stock Buybacks, & '!Y:Y,MATCH($B6,'Federal Tax, Stock Buybacks, & '!$E:$E,0))} -> -814 | Y6: =SUM(Z6:AD6) -> 96 | Z6: {=INDEX('Federal Tax, Stock Buybacks, & '!AB:AB,MATCH($B6,'Federal Tax, Stock Buybacks, & '!$E:$E,0))} -> 159 | AA6: {=INDEX('Federal Tax, Stock Buybacks, & '!AC:AC,MATCH($B6,'Federal Tax, Stock Buybacks, & '!$E:$E,0))} -> 62 | AB6: {=INDEX('Federal Tax, Stock Buybacks, & '!AD:AD,MATCH($B6,'Federal Tax, Stock Buybacks, & '!$E:$E,0))} -> 271 | AC6: {=INDEX('Federal Tax, Stock Buybacks, & '!AE:AE,MATCH($B6,'Federal Tax, Stock Buybacks, & '!$E:$E,0))} -> -189 | AD6: {=INDEX('Federal Tax, Stock Buybacks, & '!AF:AF,MATCH($B6,'Federal Tax, Stock Buybacks, & '!$E:$E,0))} -> -207 | AF6: =Y6/R6 -> 0.0082346886 | AG6: =Z6/S6 -> 0.060318665 | AH6: =AA6/T6 -> 0.012908599 | AI6: =AB6/U6 -> 0.092082909 | AJ6: =AC6/V6 -> -0.090430622 | AK6: =AD6/W6 -> 0.25429975 | AM6: =SUM(AN6:AR6) -> 15057 | AN6: {=INDEX('Federal Tax, Stock Buybacks, & '!AP:AP,MATCH($B6,'Federal Tax, Stock Buybacks, & '!$E:$E,0))} -> 3326 | AO6: {=INDEX('Federal Tax, Stock Buybacks, & '!AQ:AQ,MATCH($B6,'Federal Tax, Stock Buybacks, & '!$E:$E,0))} -> 4303 | AP6: {=INDEX('Federal Tax, Stock Buybacks, & '!AR:AR,MATCH($B6,'Federal Tax, Stock Buybacks, & '!$E:$E,0))} -> 1151 | AQ6: {=INDEX('Federal Tax, Stock Buybacks, & '!AS:AS,MATCH($B6,'Federal Tax, Stock Buybacks, & '!$E:$E,0))} -> 2285 | AR6: {=INDEX('Federal Tax, Stock Buybacks, & '!AT:AT,MATCH($B6,'Federal Tax, Stock Buybacks, & '!$E:$E,0))} -> 3992 | AT6: =SUM(AU6:AY6) -> 9124 | AU6: {=INDEX('Federal Tax, Stock Buybacks, & '!AW:AW,MATCH($B6,'Federal Tax, Stock Buybacks, & '!$E:$E,0))} -> 1783 | AV6: {=INDEX('Federal Tax, Stock Buybacks, & '!AX:AX,MATCH($B6,'Federal Tax, Stock Buybacks, & '!$E:$E,0))} -> 1842 | AW6: {=INDEX('Federal Tax, Stock Buybacks, & '!AY:AY,MATCH($B6,'Federal Tax, Stock Buybacks, & '!$E:$E,0))} -> 1859 | AX6: {=INDEX('Federal Tax, Stock Buybacks, & '!AZ:AZ,MATCH($B6,'Federal Tax, Stock Buybacks, & '!$E:$E,0))} -> 1821 | AY6: {=INDEX('Federal Tax, Stock Buybacks, & '!BA:BA,MATCH($B6,'Federal Tax, Stock Buybacks, & '!$E:$E,0))} -> 1819 | BA6: =AVERAGE(BC6:BG6) -> 73359.2 | BB6: =sum(BC6:BG6) -> 366796 | BC6: 64070 | BD6: 76392 | BE6: 75511 | BF6: 77359 | BG6: 73464 | BJ6: Link
A7: {=INDEX('Federal Tax, Stock Buybacks, & '!D:D,match(B7,'Federal Tax, Stock Buybacks, & '!E:E,0))} -> 579 | B7: Voya Financial | C7: New York | D7: =SUMIF('Executive Pay Breakdown'!B:B,$B7,'Executive Pay Breakdown'!M:M)+SUMIF('Executive Pay Breakdown'!B:B,$B7,'Executive Pay Breakdown'!Q:Q)+SUMIF('Executive Pay Breakdown'!B:B,$B7,'Executive Pay Breakdown'!U:U)+SUMIF('Executive Pay Breakdown'!B:B,$B7,'Executive Pay Breakdown'!Y:Y)+SUMIF('Executive Pay Breakdown'!B:B,$B7,'Executive Pay Breakdown'!AC:AC) -> 177163117 | E7: =SUMIF('Executive Pay Breakdown'!B:B,$B7,'Executive Pay Breakdown'!M:M) -> 40468871 | F7: =SUMIF('Executive Pay Breakdown'!B:B,$B7,'Executive Pay Breakdown'!Q:Q) -> 37700080 | G7: =SUMIF('Executive Pay Breakdown'!B:B,$B7,'Executive Pay Breakdown'!U:U) -> 31923174 | H7: =SUMIF('Executive Pay Breakdown'!B:B,$B7,'Executive Pay Breakdown'!Y:Y) -> 33206817 | I7: =SUMIF('Executive Pay Breakdown'!B:B,$B7,'Executive Pay Breakdown'!AC:AC) -> 33864175 | K7: YES | L7: =(E7/1000000)>(Z7) -> TRUE | M7: =(F7/1000000)>(AA7) -> TRUE | N7: =(G7/1000000)>(AB7) -> TRUE | R7: =SUM(S7:W7) -> 3684 | S7: {=INDEX('Federal Tax, Stock Buybacks, & '!U:U,MATCH($B7,'Federal Tax, Stock Buybacks, & '!$E:$E,0))} -> 508 | T7: {=INDEX('Federal Tax, Stock Buybacks, & '!V:V,MATCH($B7,'Federal Tax, Stock Buybacks, & '!$E:$E,0))} -> 1997 | U7: {=INDEX('Federal Tax, Stock Buybacks, & '!W:W,MATCH($B7,'Federal Tax, Stock Buybacks, & '!$E:$E,0))} -> 195 | V7: {=INDEX('Federal Tax, Stock Buybacks, & '!X:X,MATCH($B7,'Federal Tax, Stock Buybacks, & '!$E:$E,0))} -> 509 | W7: {=INDEX('Federal Tax, Stock Buybacks, & '!Y:Y,MATCH($B7,'Federal Tax, Stock Buybacks, & '!$E:$E,0))} -> 475 | Y7: =SUM(Z7:AD7) -> -295 | Z7: {=INDEX('Federal Tax, Stock Buybacks, & '!AB:AB,MATCH($B7,'Federal Tax, Stock Buybacks, & '!$E:$E,0))} -> -5 | AA7: {=INDEX('Federal Tax, Stock Buybacks, & '!AC:AC,MATCH($B7,'Federal Tax, Stock Buybacks, & '!$E:$E,0))} -> -463 | AB7: {=INDEX('Federal Tax, Stock Buybacks, & '!AD:AD,MATCH($B7,'Federal Tax, Stock Buybacks, & '!$E:$E,0))} -> -9 | AC7: {=INDEX('Federal Tax, Stock Buybacks, & '!AE:AE,MATCH($B7,'Federal Tax, Stock Buybacks, & '!$E:$E,0))} -> 126 | AD7: {=INDEX('Federal Tax, Stock Buybacks, & '!AF:AF,MATCH($B7,'Federal Tax, Stock Buybacks, & '!$E:$E,0))} -> 56 | AF7: =Y7/R7 -> -0.080076004 | AG7: =Z7/S7 -> -0.0098425197 | AH7: =AA7/T7 -> -0.23184777 | AI7: =AB7/U7 -> -0.046153846 | AJ7: =AC7/V7 -> 0.2475442 | AK7: =AD7/W7 -> 0.11789474 | AM7: =SUM(AN7:AR7) -> 4540 | AN7: {=INDEX('Federal Tax, Stock Buybacks, & '!AP:AP,MATCH($B7,'Federal Tax, Stock Buybacks, & '!$E:$E,0))} -> 750 | AO7: {=INDEX('Federal Tax, Stock Buybacks, & '!AQ:AQ,MATCH($B7,'Federal Tax, Stock Buybacks, & '!$E:$E,0))} -> 1113 | AP7: {=INDEX('Federal Tax, Stock Buybacks, & '!AR:AR,MATCH($B7,'Federal Tax, Stock Buybacks, & '!$E:$E,0))} -> 516 | AQ7: {=INDEX('Federal Tax, Stock Buybacks, & '!AS:AS,MATCH($B7,'Federal Tax, Stock Buybacks, & '!$E:$E,0))} -> 1136 | AR7: {=INDEX('Federal Tax, Stock Buybacks, & '!AT:AT,MATCH($B7,'Federal Tax, Stock Buybacks, & '!$E:$E,0))} -> 1025 | AT7: =SUM(AU7:AY7) -> 425 | AU7: {=INDEX('Federal Tax, Stock Buybacks, & '!AW:AW,MATCH($B7,'Federal Tax, Stock Buybacks, & '!$E:$E,0))} -> 119 | AV7: {=INDEX('Federal Tax, Stock Buybacks, & '!AX:AX,MATCH($B7,'Federal Tax, Stock Buybacks, & '!$E:$E,0))} -> 116 | AW7: {=INDEX('Federal Tax, Stock Buybacks, & '!AY:AY,MATCH($B7,'Federal Tax, Stock Buybacks, & '!$E:$E,0))} -> 112 | AX7: {=INDEX('Federal Tax, Stock Buybacks, & '!AZ:AZ,MATCH($B7,'Federal Tax, Stock Buybacks, & '!$E:$E,0))} -> 72 | AY7: {=INDEX('Federal Tax, Stock Buybacks, & '!BA:BA,MATCH($B7,'Federal Tax, Stock Buybacks, & '!$E:$E,0))} -> 6 | BA7: =AVERAGE(BC7:BG7) -> 114405.6 | BB7: =sum(BC7:BG7) -> 572028 | BC7: 106866 | BD7: 121489 | BE7: 117545 | BF7: 127400 | BG7: 98728 | BJ7: Link
A8: {=INDEX('Federal Tax, Stock Buybacks, & '!D:D,match(B8,'Federal Tax, Stock Buybacks, & '!E:E,0))} -> 236 | B8: Principal Financial | C8: Iowa | D8: =SUMIF('Executive Pay Breakdown'!B:B,$B8,'Executive Pay Breakdown'!M:M)+SUMIF('Executive Pay Breakdown'!B:B,$B8,'Executive Pay Breakdown'!Q:Q)+SUMIF('Executive Pay Breakdown'!B:B,$B8,'Executive Pay Breakdown'!U:U)+SUMIF('Executive Pay Breakdown'!B:B,$B8,'Executive Pay Breakdown'!Y:Y)+SUMIF('Executive Pay Breakdown'!B:B,$B8,'Executive Pay Breakdown'!AC:AC) -> 170202177 | E8: =SUMIF('Executive Pay Breakdown'!B:B,$B8,'Executive Pay Breakdown'!M:M) -> 32592472 | F8: =SUMIF('Executive Pay Breakdown'!B:B,$B8,'Executive Pay Breakdown'!Q:Q) -> 38436273 | G8: =SUMIF('Executive Pay Breakdown'!B:B,$B8,'Executive Pay Breakdown'!U:U) -> 33646602 | H8: =SUMIF('Executive Pay Breakdown'!B:B,$B8,'Executive Pay Breakdown'!Y:Y) -> 33690305 | I8: =SUMIF('Executive Pay Breakdown'!B:B,$B8,'Executive Pay Breakdown'!AC:AC) -> 31836525 | K8: YES | L8: =(E8/1000000)>(Z8) -> TRUE | N8: =(G8/1000000)>(AB8) -> TRUE | O8: =(H8/1000000)>(AC8) -> TRUE | P8: =(I8/1000000)>(AD8) -> TRUE | R8: =SUM(S8:W8) -> 11976.3 | S8: {=INDEX('Federal Tax, Stock Buybacks, & '!U:U,MATCH($B8,'Federal Tax, Stock Buybacks, & '!$E:$E,0))} -> 5800.8 | T8: {=INDEX('Federal Tax, Stock Buybacks, & '!V:V,MATCH($B8,'Federal Tax, Stock Buybacks, & '!$E:$E,0))} -> 1869.7 | U8: {=INDEX('Federal Tax, Stock Buybacks, & '!W:W,MATCH($B8,'Federal Tax, Stock Buybacks, & '!$E:$E,0))} -> 1318.2 | V8: {=INDEX('Federal Tax, Stock Buybacks, & '!X:X,MATCH($B8,'Federal Tax, Stock Buybacks, & '!$E:$E,0))} -> 1347 | W8: {=INDEX('Federal Tax, Stock Buybacks, & '!Y:Y,MATCH($B8,'Federal Tax, Stock Buybacks, & '!$E:$E,0))} -> 1640.6 | Y8: =SUM(Z8:AD8) -> 45.9 | Z8: {=INDEX('Federal Tax, Stock Buybacks, & '!AB:AB,MATCH($B8,'Federal Tax, Stock Buybacks, & '!$E:$E,0))} -> -57.3 | AA8: {=INDEX('Federal Tax, Stock Buybacks, & '!AC:AC,MATCH($B8,'Federal Tax, Stock Buybacks, & '!$E:$E,0))} -> 110.3 | AB8: {=INDEX('Federal Tax, Stock Buybacks, & '!AD:AD,MATCH($B8,'Federal Tax, Stock Buybacks, & '!$E:$E,0))} -> 15.8 | AC8: {=INDEX('Federal Tax, Stock Buybacks, & '!AE:AE,MATCH($B8,'Federal Tax, Stock Buybacks, & '!$E:$E,0))} -> 31.9 | AD8: {=INDEX('Federal Tax, Stock Buybacks, & '!AF:AF,MATCH($B8,'Federal Tax, Stock Buybacks, & '!$E:$E,0))} -> -54.8 | AF8: =Y8/R8 -> 0.0038325693 | AG8: =Z8/S8 -> -0.0098779479 | AH8: =AA8/T8 -> 0.058993421 | AI8: =AB8/U8 -> 0.011986042 | AJ8: =AC8/V8 -> 0.023682257 | AK8: =AD8/W8 -> -0.033402414 | AM8: =SUM(AN8:AR8) -> 3892 | AN8: {=INDEX('Federal Tax, Stock Buybacks, & '!AP:AP,MATCH($B8,'Federal Tax, Stock Buybacks, & '!$E:$E,0))} -> 1695 | AO8: {=INDEX('Federal Tax, Stock Buybacks, & '!AQ:AQ,MATCH($B8,'Federal Tax, Stock Buybacks, & '!$E:$E,0))} -> 937 | AP8: {=INDEX('Federal Tax, Stock Buybacks, & '!AR:AR,MATCH($B8,'Federal Tax, Stock Buybacks, & '!$E:$E,0))} -> 307 | AQ8: {=INDEX('Federal Tax, Stock Buybacks, & '!AS:AS,MATCH($B8,'Federal Tax, Stock Buybacks, & '!$E:$E,0))} -> 281 | AR8: {=INDEX('Federal Tax, Stock Buybacks, & '!AT:AT,MATCH($B8,'Federal Tax, Stock Buybacks, & '!$E:$E,0))} -> 672 | AT8: =SUM(AU8:AY8) -> 3115.5 | AU8: {=INDEX('Federal Tax, Stock Buybacks, & '!AW:AW,MATCH($B8,'Federal Tax, Stock Buybacks, & '!$E:$E,0))} -> 642.3 | AV8: {=INDEX('Federal Tax, Stock Buybacks, & '!AX:AX,MATCH($B8,'Federal Tax, Stock Buybacks, & '!$E:$E,0))} -> 654.1 | AW8: {=INDEX('Federal Tax, Stock Buybacks, & '!AY:AY,MATCH($B8,'Federal Tax, Stock Buybacks, & '!$E:$E,0))} -> 614.5 | AX8: {=INDEX('Federal Tax, Stock Buybacks, & '!AZ:AZ,MATCH($B8,'Federal Tax, Stock Buybacks, & '!$E:$E,0))} -> 606 | AY8: {=INDEX('Federal Tax, Stock Buybacks, & '!BA:BA,MATCH($B8,'Federal Tax, Stock Buybacks, & '!$E:$E,0))} -> 598.6 | BA8: =AVERAGE(BC8:BG8) -> 86353.4 | BB8: =sum(BC8:BG8) -> 431767 | BC8: 75463 | BD8: 75348 | BE8: 81523 | BF8: 116561 | BG8: 82872 | BJ8: Link
A9: {=INDEX('Federal Tax, Stock Buybacks, & '!D:D,match(B9,'Federal Tax, Stock Buybacks, & '!E:E,0))} -> 257 | B9: Reinsurance Group of America | C9: Missouri | D9: =SUMIF('Executive Pay Breakdown'!B:B,$B9,'Executive Pay Breakdown'!M:M)+SUMIF('Executive Pay Breakdown'!B:B,$B9,'Executive Pay Breakdown'!Q:Q)+SUMIF('Executive Pay Breakdown'!B:B,$B9,'Executive Pay Breakdown'!U:U)+SUMIF('Executive Pay Breakdown'!B:B,$B9,'Executive Pay Breakdown'!Y:Y)+SUMIF('Executive Pay Breakdown'!B:B,$B9,'Executive Pay Breakdown'!AC:AC) -> 115808255 | E9: =SUMIF('Executive Pay Breakdown'!B:B,$B9,'Executive Pay Breakdown'!M:M) -> 23812117 | F9: =SUMIF('Executive Pay Breakdown'!B:B,$B9,'Executive Pay Breakdown'!Q:Q) -> 32358770 | G9: =SUMIF('Executive Pay Breakdown'!B:B,$B9,'Executive Pay Breakdown'!U:U) -> 21501807 | H9: =SUMIF('Executive Pay Breakdown'!B:B,$B9,'Executive Pay Breakdown'!Y:Y) -> 21986263 | I9: =SUMIF('Executive Pay Breakdown'!B:B,$B9,'Executive Pay Breakdown'!AC:AC) -> 16149298 | K9: 2 of 5 | L9: =(E9/1000000)>(Z9) -> TRUE | O9: =(H9/1000000)>(AC9) -> TRUE | R9: =SUM(S9:W9) -> 2302.2 | S9: {=INDEX('Federal Tax, Stock Buybacks, & '!U:U,MATCH($B9,'Federal Tax, Stock Buybacks, & '!$E:$E,0))} -> 399 | T9: {=INDEX('Federal Tax, Stock Buybacks, & '!V:V,MATCH($B9,'Federal Tax, Stock Buybacks, & '!$E:$E,0))} -> 327 | U9: {=INDEX('Federal Tax, Stock Buybacks, & '!W:W,MATCH($B9,'Federal Tax, Stock Buybacks, & '!$E:$E,0))} -> 79 | V9: {=INDEX('Federal Tax, Stock Buybacks, & '!X:X,MATCH($B9,'Federal Tax, Stock Buybacks, & '!$E:$E,0))} -> 871 | W9: {=INDEX('Federal Tax, Stock Buybacks, & '!Y:Y,MATCH($B9,'Federal Tax, Stock Buybacks, & '!$E:$E,0))} -> 626.2 | Y9: =SUM(Z9:AD9) -> 189.43 | Z9: {=INDEX('Federal Tax, Stock Buybacks, & '!AB:AB,MATCH($B9,'Federal Tax, Stock Buybacks, & '!$E:$E,0))} -> -12 | AA9: {=INDEX('Federal Tax, Stock Buybacks, & '!AC:AC,MATCH($B9,'Federal Tax, Stock Buybacks, & '!$E:$E,0))} -> 80 | AB9: {=INDEX('Federal Tax, Stock Buybacks, & '!AD:AD,MATCH($B9,'Federal Tax, Stock Buybacks, & '!$E:$E,0))} -> 62 | AC9: {=INDEX('Federal Tax, Stock Buybacks, & '!AE:AE,MATCH($B9,'Federal Tax, Stock Buybacks, & '!$E:$E,0))} -> -9 | AD9: {=INDEX('Federal Tax, Stock Buybacks, & '!AF:AF,MATCH($B9,'Federal Tax, Stock Buybacks, & '!$E:$E,0))} -> 68.43 | AF9: =Y9/R9 -> 0.082282165 | AG9: =Z9/S9 -> -0.030075188 | AH9: =AA9/T9 -> 0.24464832 | AI9: =AB9/U9 -> 0.78481013 | AJ9: =AC9/V9 -> -0.010332951 | AK9: =AD9/W9 -> 0.10927819 | AM9: =SUM(AN9:AR9) -> 743.679 | AN9: {=INDEX('Federal Tax, Stock Buybacks, & '!AP:AP,MATCH($B9,'Federal Tax, Stock Buybacks, & '!$E:$E,0))} -> 81 | AO9: {=INDEX('Federal Tax, Stock Buybacks, & '!AQ:AQ,MATCH($B9,'Federal Tax, Stock Buybacks, & '!$E:$E,0))} -> 99 | AP9: {=INDEX('Federal Tax, Stock Buybacks, & '!AR:AR,MATCH($B9,'Federal Tax, Stock Buybacks, & '!$E:$E,0))} -> 163 | AQ9: {=INDEX('Federal Tax, Stock Buybacks, & '!AS:AS,MATCH($B9,'Federal Tax, Stock Buybacks, & '!$E:$E,0))} -> 101 | AR9: {=INDEX('Federal Tax, Stock Buybacks, & '!AT:AT,MATCH($B9,'Federal Tax, Stock Buybacks, & '!$E:$E,0))} -> 299.679 | AT9: =SUM(AU9:AY9) -> 884 | AU9: {=INDEX('Federal Tax, Stock Buybacks, & '!AW:AW,MATCH($B9,'Federal Tax, Stock Buybacks, & '!$E:$E,0))} -> 205 | AV9: {=INDEX('Federal Tax, Stock Buybacks, & '!AX:AX,MATCH($B9,'Federal Tax, Stock Buybacks, & '!$E:$E,0))} -> 194 | AW9: {=INDEX('Federal Tax, Stock Buybacks, & '!AY:AY,MATCH($B9,'Federal Tax, Stock Buybacks, & '!$E:$E,0))} -> 182 | AX9: {=INDEX('Federal Tax, Stock Buybacks, & '!AZ:AZ,MATCH($B9,'Federal Tax, Stock Buybacks, & '!$E:$E,0))} -> 163 | AY9: {=INDEX('Federal Tax, Stock Buybacks, & '!BA:BA,MATCH($B9,'Federal Tax, Stock Buybacks, & '!$E:$E,0))} -> 140 | BA9: =AVERAGE(BC9:BG9) -> 118653 | BB9: =sum(BC9:BG9) -> 593265 | BC9: 129302 | BD9: 125152 | BE9: 117324 | BF9: 113479 | BG9: 108008 | BJ9: Link
A10: {=INDEX('Federal Tax, Stock Buybacks, & '!D:D,match(B10,'Federal Tax, Stock Buybacks, & '!E:E,0))} -> 174 | B10: Hartford Financial Services | C10: Connecticut | D10: =SUMIF('Executive Pay Breakdown'!B:B,$B10,'Executive Pay Breakdown'!M:M)+SUMIF('Executive Pay Breakdown'!B:B,$B10,'Executive Pay Breakdown'!Q:Q)+SUMIF('Executive Pay Breakdown'!B:B,$B10,'Executive Pay Breakdown'!U:U)+SUMIF('Executive Pay Breakdown'!B:B,$B10,'Executive Pay Breakdown'!Y:Y)+SUMIF('Executive Pay Breakdown'!B:B,$B10,'Executive Pay Breakdown'!AC:AC) -> 180325187 | E10: =SUMIF('Executive Pay Breakdown'!B:B,$B10,'Executive Pay Breakdown'!M:M) -> 37723286 | F10: =SUMIF('Executive Pay Breakdown'!B:B,$B10,'Executive Pay Breakdown'!Q:Q) -> 39792977 | G10: =SUMIF('Executive Pay Breakdown'!B:B,$B10,'Executive Pay Breakdown'!U:U) -> 31445575 | H10: =SUMIF('Executive Pay Breakdown'!B:B,$B10,'Executive Pay Breakdown'!Y:Y) -> 36379015 | I10: =SUMIF('Executive Pay Breakdown'!B:B,$B10,'Executive Pay Breakdown'!AC:AC) -> 34984334 | K10: 2 of 5 | O10: =(H10/1000000)>(AC10) -> TRUE | P10: =(I10/1000000)>(AD10) -> TRUE | R10: =SUM(S10:W10) -> 11761 | S10: {=INDEX('Federal Tax, Stock Buybacks, & '!U:U,MATCH($B10,'Federal Tax, Stock Buybacks, & '!$E:$E,0))} -> 2252 | T10: {=INDEX('Federal Tax, Stock Buybacks, & '!V:V,MATCH($B10,'Federal Tax, Stock Buybacks, & '!$E:$E,0))} -> 2910 | U10: {=INDEX('Federal Tax, Stock Buybacks, & '!W:W,MATCH($B10,'Federal Tax, Stock Buybacks, & '!$E:$E,0))} -> 2222 | V10: {=INDEX('Federal Tax, Stock Buybacks, & '!X:X,MATCH($B10,'Federal Tax, Stock Buybacks, & '!$E:$E,0))} -> 2624 | W10: {=INDEX('Federal Tax, Stock Buybacks, & '!Y:Y,MATCH($B10,'Federal Tax, Stock Buybacks, & '!$E:$E,0))} -> 1753 | Y10: =SUM(Z10:AD10) -> 1436 | Z10: {=INDEX('Federal Tax, Stock Buybacks, & '!AB:AB,MATCH($B10,'Federal Tax, Stock Buybacks, & '!$E:$E,0))} -> 550 | AA10: {=INDEX('Federal Tax, Stock Buybacks, & '!AC:AC,MATCH($B10,'Federal Tax, Stock Buybacks, & '!$E:$E,0))} -> 486 | AB10: {=INDEX('Federal Tax, Stock Buybacks, & '!AD:AD,MATCH($B10,'Federal Tax, Stock Buybacks, & '!$E:$E,0))} -> 410 | AC10: {=INDEX('Federal Tax, Stock Buybacks, & '!AE:AE,MATCH($B10,'Federal Tax, Stock Buybacks, & '!$E:$E,0))} -> 8 | AD10: {=INDEX('Federal Tax, Stock Buybacks, & '!AF:AF,MATCH($B10,'Federal Tax, Stock Buybacks, & '!$E:$E,0))} -> -18 | AF10: =Y10/R10 -> 0.12209846 | AG10: =Z10/S10 -> 0.24422735 | AH10: =AA10/T10 -> 0.16701031 | AI10: =AB10/U10 -> 0.18451845 | AJ10: =AC10/V10 -> 0.0030487805 | AK10: =AD10/W10 -> -0.010268112 | AM10: =SUM(AN10:AR10) -> 3602 | AN10: {=INDEX('Federal Tax, Stock Buybacks, & '!AP:AP,MATCH($B10,'Federal Tax, Stock Buybacks, & '!$E:$E,0))} -> 1550 | AO10: {=INDEX('Federal Tax, Stock Buybacks, & '!AQ:AQ,MATCH($B10,'Federal Tax, Stock Buybacks, & '!$E:$E,0))} -> 1702 | AP10: {=INDEX('Federal Tax, Stock Buybacks, & '!AR:AR,MATCH($B10,'Federal Tax, Stock Buybacks, & '!$E:$E,0))} -> 150 | AQ10: {=INDEX('Federal Tax, Stock Buybacks, & '!AS:AS,MATCH($B10,'Federal Tax, Stock Buybacks, & '!$E:$E,0))} -> 200 | AR10: {=INDEX('Federal Tax, Stock Buybacks, & '!AT:AT,MATCH($B10,'Federal Tax, Stock Buybacks, & '!$E:$E,0))} -> 0 | AT10: =SUM(AU10:AY10) -> 2344 | AU10: {=INDEX('Federal Tax, Stock Buybacks, & '!AW:AW,MATCH($B10,'Federal Tax, Stock Buybacks, & '!$E:$E,0))} -> 527 | AV10: {=INDEX('Federal Tax, Stock Buybacks, & '!AX:AX,MATCH($B10,'Federal Tax, Stock Buybacks, & '!$E:$E,0))} -> 506 | AW10: {=INDEX('Federal Tax, Stock Buybacks, & '!AY:AY,MATCH($B10,'Federal Tax, Stock Buybacks, & '!$E:$E,0))} -> 478 | AX10: {=INDEX('Federal Tax, Stock Buybacks, & '!AZ:AZ,MATCH($B10,'Federal Tax, Stock Buybacks, & '!$E:$E,0))} -> 454 | AY10: {=INDEX('Federal Tax, Stock Buybacks, & '!BA:BA,MATCH($B10,'Federal Tax, Stock Buybacks, & '!$E:$E,0))} -> 379 | BA10: =AVERAGE(BC10:BG10) -> 103768.6 | BB10: =sum(BC10:BG10) -> 518843 | BC10: 117472 | BD10: 106940 | BE10: 92639 | BF10: 96867 | BG10: 104925 | BJ10: Link
A11: {=INDEX('Federal Tax, Stock Buybacks, & '!D:D,match(B11,'Federal Tax, Stock Buybacks, & '!E:E,0))} -> 51.5 | B11: T-Mobile US | C11: Washington | D11: =SUMIF('Executive Pay Breakdown'!B:B,$B11,'Executive Pay Breakdown'!M:M)+SUMIF('Executive Pay Breakdown'!B:B,$B11,'Executive Pay Breakdown'!Q:Q)+SUMIF('Executive Pay Breakdown'!B:B,$B11,'Executive Pay Breakdown'!U:U)+SUMIF('Executive Pay Breakdown'!B:B,$B11,'Executive Pay Breakdown'!Y:Y)+SUMIF('Executive Pay Breakdown'!B:B,$B11,'Executive Pay Breakdown'!AC:AC) -> 675159996 | E11: =SUMIF('Executive Pay Breakdown'!B:B,$B11,'Executive Pay Breakdown'!M:M) -> 81368544 | F11: =SUMIF('Executive Pay Breakdown'!B:B,$B11,'Executive Pay Breakdown'!Q:Q) -> 71060115 | G11: =SUMIF('Executive Pay Breakdown'!B:B,$B11,'Executive Pay Breakdown'!U:U) -> 284954500 | H11: =SUMIF('Executive Pay Breakdown'!B:B,$B11,'Executive Pay Breakdown'!Y:Y) -> 85493859 | I11: =SUMIF('Executive Pay Breakdown'!B:B,$B11,'Executive Pay Breakdown'!AC:AC) -> 152282978 | K11: YES | L11: =(E11/1000000)>(Z11) -> TRUE | M11: =(F11/1000000)>(AA11) -> TRUE | N11: =(G11/1000000)>(AB11) -> TRUE | O11: =(H11/1000000)>(AC11) -> TRUE | P11: =(I11/1000000)>(AD11) -> TRUE | R11: =SUM(S11:W11) -> 17916.13 | S11: {=INDEX('Federal Tax, Stock Buybacks, & '!U:U,MATCH($B11,'Federal Tax, Stock Buybacks, & '!$E:$E,0))} -> 3052 | T11: {=INDEX('Federal Tax, Stock Buybacks, & '!V:V,MATCH($B11,'Federal Tax, Stock Buybacks, & '!$E:$E,0))} -> 3312 | U11: {=INDEX('Federal Tax, Stock Buybacks, & '!W:W,MATCH($B11,'Federal Tax, Stock Buybacks, & '!$E:$E,0))} -> 3428.86 | V11: {=INDEX('Federal Tax, Stock Buybacks, & '!X:X,MATCH($B11,'Federal Tax, Stock Buybacks, & '!$E:$E,0))} -> 4493.22 | W11: {=INDEX('Federal Tax, Stock Buybacks, & '!Y:Y,MATCH($B11,'Federal Tax, Stock Buybacks, & '!$E:$E,0))} -> 3630.05 | Y11: =SUM(Z11:AD11) -> -80 | Z11: {=INDEX('Federal Tax, Stock Buybacks, & '!AB:AB,MATCH($B11,'Federal Tax, Stock Buybacks, & '!$E:$E,0))} -> -22 | AA11: {=INDEX('Federal Tax, Stock Buybacks, & '!AC:AC,MATCH($B11,'Federal Tax, Stock Buybacks, & '!$E:$E,0))} -> 22 | AB11: {=INDEX('Federal Tax, Stock Buybacks, & '!AD:AD,MATCH($B11,'Federal Tax, Stock Buybacks, & '!$E:$E,0))} -> -17 | AC11: {=INDEX('Federal Tax, Stock Buybacks, & '!AE:AE,MATCH($B11,'Federal Tax, Stock Buybacks, & '!$E:$E,0))} -> -24 | AD11: {=INDEX('Federal Tax, Stock Buybacks, & '!AF:AF,MATCH($B11,'Federal Tax, Stock Buybacks, & '!$E:$E,0))} -> -39 | AF11: =Y11/R11 -> -0.00446525 | AG11: =Z11/S11 -> -0.0072083879 | AH11: =AA11/T11 -> 0.0066425121 | AI11: =AB11/U11 -> -0.004957916 | AJ11: =AC11/V11 -> -0.005341381 | AK11: =AD11/W11 -> -0.010743654 | AM11: =SUM(AN11:AR11) -> 23607 | AN11: {=INDEX('Federal Tax, Stock Buybacks, & '!AP:AP,MATCH($B11,'Federal Tax, Stock Buybacks, & '!$E:$E,0))} -> 3000 | AO11: {=INDEX('Federal Tax, Stock Buybacks, & '!AQ:AQ,MATCH($B11,'Federal Tax, Stock Buybacks, & '!$E:$E,0))} -> 0 | AP11: {=INDEX('Federal Tax, Stock Buybacks, & '!AR:AR,MATCH($B11,'Federal Tax, Stock Buybacks, & '!$E:$E,0))} -> 19536 | AQ11: {=INDEX('Federal Tax, Stock Buybacks, & '!AS:AS,MATCH($B11,'Federal Tax, Stock Buybacks, & '!$E:$E,0))} -> 0 | AR11: {=INDEX('Federal Tax, Stock Buybacks, & '!AT:AT,MATCH($B11,'Federal Tax, Stock Buybacks, & '!$E:$E,0))} -> 1071 | AT11: =SUM(AU11:AY11) -> 0 | AU11: {=INDEX('Federal Tax, Stock Buybacks, & '!AW:AW,MATCH($B11,'Federal Tax, Stock Buybacks, & '!$E:$E,0))} -> 0 | AV11: {=INDEX('Federal Tax, Stock Buybacks, & '!AX:AX,MATCH($B11,'Federal Tax, Stock Buybacks, & '!$E:$E,0))} -> 0 | AW11: {=INDEX('Federal Tax, Stock Buybacks, & '!AY:AY,MATCH($B11,'Federal Tax, Stock Buybacks, & '!$E:$E,0))} -> 0 | AX11: {=INDEX('Federal Tax, Stock Buybacks, & '!AZ:AZ,MATCH($B11,'Federal Tax, Stock Buybacks, & '!$E:$E,0))} -> 0 | AY11: {=INDEX('Federal Tax, Stock Buybacks, & '!BA:BA,MATCH($B11,'Federal Tax, Stock Buybacks, & '!$E:$E,0))} -> 0 | BA11: =AVERAGE(BC11:BG11) -> 65940.4 | BB11: =sum(BC11:BG11) -> 329702 | BC11: 71333 | BD11: 72572 | BE11: 63949 | BF11: 62195 | BG11: 59653 | BJ11: Link
A12: {=INDEX('Federal Tax, Stock Buybacks, & '!D:D,match(B12,'Federal Tax, Stock Buybacks, & '!E:E,0))} -> 129 | B12: Netflix | C12: California | D12: =SUMIF('Executive Pay Breakdown'!B:B,$B12,'Executive Pay Breakdown'!M:M)+SUMIF('Executive Pay Breakdown'!B:B,$B12,'Executive Pay Breakdown'!Q:Q)+SUMIF('Executive Pay Breakdown'!B:B,$B12,'Executive Pay Breakdown'!U:U)+SUMIF('Executive Pay Breakdown'!B:B,$B12,'Executive Pay Breakdown'!Y:Y)+SUMIF('Executive Pay Breakdown'!B:B,$B12,'Executive Pay Breakdown'!AC:AC) -> 651925175 | E12: =SUMIF('Executive Pay Breakdown'!B:B,$B12,'Executive Pay Breakdown'!M:M) -> 166718443 | F12: =SUMIF('Executive Pay Breakdown'!B:B,$B12,'Executive Pay Breakdown'!Q:Q) -> 127444969 | G12: =SUMIF('Executive Pay Breakdown'!B:B,$B12,'Executive Pay Breakdown'!U:U) -> 132114867 | H12: =SUMIF('Executive Pay Breakdown'!B:B,$B12,'Executive Pay Breakdown'!Y:Y) -> 126378740 | I12: =SUMIF('Executive Pay Breakdown'!B:B,$B12,'Executive Pay Breakdown'!AC:AC) -> 99268156 | K12: YES | L12: =(E12/1000000)>(Z12) -> TRUE | M12: =(F12/1000000)>(AA12) -> TRUE | N12: =(G12/1000000)>(AB12) -> TRUE | O12: =(H12/1000000)>(AC12) -> TRUE | P12: =(I12/1000000)>(AD12) -> TRUE | R12: =SUM(S12:W12) -> 15079.54 | S12: {=INDEX('Federal Tax, Stock Buybacks, & '!U:U,MATCH($B12,'Federal Tax, Stock Buybacks, & '!$E:$E,0))} -> 4570.65 | T12: {=INDEX('Federal Tax, Stock Buybacks, & '!V:V,MATCH($B12,'Federal Tax, Stock Buybacks, & '!$E:$E,0))} -> 5255.91 | U12: {=INDEX('Federal Tax, Stock Buybacks, & '!W:W,MATCH($B12,'Federal Tax, Stock Buybacks, & '!$E:$E,0))} -> 2723.24 | V12: {=INDEX('Federal Tax, Stock Buybacks, & '!X:X,MATCH($B12,'Federal Tax, Stock Buybacks, & '!$E:$E,0))} -> 1674.1 | W12: {=INDEX('Federal Tax, Stock Buybacks, & '!Y:Y,MATCH($B12,'Federal Tax, Stock Buybacks, & '!$E:$E,0))} -> 855.64 | Y12: =SUM(Z12:AD12) -> 235.98 | Z12: {=INDEX('Federal Tax, Stock Buybacks, & '!AB:AB,MATCH($B12,'Federal Tax, Stock Buybacks, & '!$E:$E,0))} -> 109.91 | AA12: {=INDEX('Federal Tax, Stock Buybacks, & '!AC:AC,MATCH($B12,'Federal Tax, Stock Buybacks, & '!$E:$E,0))} -> 57.53 | AB12: {=INDEX('Federal Tax, Stock Buybacks, & '!AD:AD,MATCH($B12,'Federal Tax, Stock Buybacks, & '!$E:$E,0))} -> 24.22 | AC12: {=INDEX('Federal Tax, Stock Buybacks, & '!AE:AE,MATCH($B12,'Federal Tax, Stock Buybacks, & '!$E:$E,0))} -> 21.5 | AD12: {=INDEX('Federal Tax, Stock Buybacks, & '!AF:AF,MATCH($B12,'Federal Tax, Stock Buybacks, & '!$E:$E,0))} -> 22.82 | AF12: =Y12/R12 -> 0.015649018 | AG12: =Z12/S12 -> 0.024046908 | AH12: =AA12/T12 -> 0.010945773 | AI12: =AB12/U12 -> 0.0088938177 | AJ12: =AC12/V12 -> 0.012842721 | AK12: =AD12/W12 -> 0.026670095 | AM12: =SUM(AN12:AR12) -> 600.022 | AN12: {=INDEX('Federal Tax, Stock Buybacks, & '!AP:AP,MATCH($B12,'Federal Tax, Stock Buybacks, & '!$E:$E,0))} -> 0 | AO12: {=INDEX('Federal Tax, Stock Buybacks, & '!AQ:AQ,MATCH($B12,'Federal Tax, Stock Buybacks, & '!$E:$E,0))} -> 600.022 | AP12: {=INDEX('Federal Tax, Stock Buybacks, & '!AR:AR,MATCH($B12,'Federal Tax, Stock Buybacks, & '!$E:$E,0))} -> 0 | AQ12: {=INDEX('Federal Tax, Stock Buybacks, & '!AS:AS,MATCH($B12,'Federal Tax, Stock Buybacks, & '!$E:$E,0))} -> 0 | AR12: {=INDEX('Federal Tax, Stock Buybacks, & '!AT:AT,MATCH($B12,'Federal Tax, Stock Buybacks, & '!$E:$E,0))} -> 0 | AT12: =SUM(AU12:AY12) -> 0 | AU12: {=INDEX('Federal Tax, Stock Buybacks, & '!AW:AW,MATCH($B12,'Federal Tax, Stock Buybacks, & '!$E:$E,0))} -> 0 | AV12: {=INDEX('Federal Tax, Stock Buybacks, & '!AX:AX,MATCH($B12,'Federal Tax, Stock Buybacks, & '!$E:$E,0))} -> 0 | AW12: {=INDEX('Federal Tax, Stock Buybacks, & '!AY:AY,MATCH($B12,'Federal Tax, Stock Buybacks, & '!$E:$E,0))} -> 0 | AX12: {=INDEX('Federal Tax, Stock Buybacks, & '!AZ:AZ,MATCH($B12,'Federal Tax, Stock Buybacks, & '!$E:$E,0))} -> 0 | AY12: {=INDEX('Federal Tax, Stock Buybacks, & '!BA:BA,MATCH($B12,'Federal Tax, Stock Buybacks, & '!$E:$E,0))} -> 0 | BA12: =AVERAGE(BC12:BG12) -> 208997.2 | BB12: =sum(BC12:BG12) -> 1044986 | BC12: 218400 | BD12: 201743 | BE12: 219577 | BF12: 202931 | BG12: 202335 | BJ12: Link
A13: {=INDEX('Federal Tax, Stock Buybacks, & '!D:D,match(B13,'Federal Tax, Stock Buybacks, & '!E:E,0))} -> 133 | B13: Salesforce | C13: California | D13: =SUMIF('Executive Pay Breakdown'!B:B,$B13,'Executive Pay Breakdown'!M:M)+SUMIF('Executive Pay Breakdown'!B:B,$B13,'Executive Pay Breakdown'!Q:Q)+SUMIF('Executive Pay Breakdown'!B:B,$B13,'Executive Pay Breakdown'!U:U)+SUMIF('Executive Pay Breakdown'!B:B,$B13,'Executive Pay Breakdown'!Y:Y)+SUMIF('Executive Pay Breakdown'!B:B,$B13,'Executive Pay Breakdown'!AC:AC) -> 508220520 | E13: =SUMIF('Executive Pay Breakdown'!B:B,$B13,'Executive Pay Breakdown'!M:M) -> 120356167 | F13: =SUMIF('Executive Pay Breakdown'!B:B,$B13,'Executive Pay Breakdown'!Q:Q) -> 107574337 | G13: =SUMIF('Executive Pay Breakdown'!B:B,$B13,'Executive Pay Breakdown'!U:U) -> 94938850 | H13: =SUMIF('Executive Pay Breakdown'!B:B,$B13,'Executive Pay Breakdown'!Y:Y) -> 94064898 | I13: =SUMIF('Executive Pay Breakdown'!B:B,$B13,'Executive Pay Breakdown'!AC:AC) -> 91286268 | K13: YES | M13: =(F13/1000000)>(AA13) -> TRUE | N13: =(G13/1000000)>(AB13) -> TRUE | O13: =(H13/1000000)>(AC13) -> TRUE | P13: =(I13/1000000)>(AD13) -> TRUE | R13: =SUM(S13:W13) -> 6031.73 | S13: {=INDEX('Federal Tax, Stock Buybacks, & '!U:U,MATCH($B13,'Federal Tax, Stock Buybacks, & '!$E:$E,0))} -> 594.73 | T13: {=INDEX('Federal Tax, Stock Buybacks, & '!V:V,MATCH($B13,'Federal Tax, Stock Buybacks, & '!$E:$E,0))} -> 1354 | U13: {=INDEX('Federal Tax, Stock Buybacks, & '!W:W,MATCH($B13,'Federal Tax, Stock Buybacks, & '!$E:$E,0))} -> 2630 | V13: {=INDEX('Federal Tax, Stock Buybacks, & '!X:X,MATCH($B13,'Federal Tax, Stock Buybacks, & '!$E:$E,0))} -> 653 | W13: {=INDEX('Federal Tax, Stock Buybacks, & '!Y:Y,MATCH($B13,'Federal Tax, Stock Buybacks, & '!$E:$E,0))} -> 800 | Y13: =SUM(Z13:AD13) -> 175 | Z13: {=INDEX('Federal Tax, Stock Buybacks, & '!AB:AB,MATCH($B13,'Federal Tax, Stock Buybacks, & '!$E:$E,0))} -> 173 | AA13: {=INDEX('Federal Tax, Stock Buybacks, & '!AC:AC,MATCH($B13,'Federal Tax, Stock Buybacks, & '!$E:$E,0))} -> 6 | AB13: {=INDEX('Federal Tax, Stock Buybacks, & '!AD:AD,MATCH($B13,'Federal Tax, Stock Buybacks, & '!$E:$E,0))} -> -12 | AC13: {=INDEX('Federal Tax, Stock Buybacks, & '!AE:AE,MATCH($B13,'Federal Tax, Stock Buybacks, & '!$E:$E,0))} -> 8 | AD13: {=INDEX('Federal Tax, Stock Buybacks, & '!AF:AF,MATCH($B13,'Federal Tax, Stock Buybacks, & '!$E:$E,0))} -> 0 | AF13: =Y13/R13 -> 0.029013235 | AG13: =Z13/S13 -> 0.2908883 | AH13: =AA13/T13 -> 0.0044313146 | AI13: =AB13/U13 -> -0.0045627376 | AJ13: =AC13/V13 -> 0.012251149 | AK13: =AD13/W13 -> 0 | AM13: =SUM(AN13:AR13) -> 4000 | AN13: {=INDEX('Federal Tax, Stock Buybacks, & '!AP:AP,MATCH($B13,'Federal Tax, Stock Buybacks, & '!$E:$E,0))} -> 4000 | AO13: {=INDEX('Federal Tax, Stock Buybacks, & '!AQ:AQ,MATCH($B13,'Federal Tax, Stock Buybacks, & '!$E:$E,0))} -> 0 | AP13: {=INDEX('Federal Tax, Stock Buybacks, & '!AR:AR,MATCH($B13,'Federal Tax, Stock Buybacks, & '!$E:$E,0))} -> 0 | AQ13: {=INDEX('Federal Tax, Stock Buybacks, & '!AS:AS,MATCH($B13,'Federal Tax, Stock Buybacks, & '!$E:$E,0))} -> 0 | AR13: {=INDEX('Federal Tax, Stock Buybacks, & '!AT:AT,MATCH($B13,'Federal Tax, Stock Buybacks, & '!$E:$E,0))} -> 0 | AT13: =SUM(AU13:AY13) -> 0 | AU13: {=INDEX('Federal Tax, Stock Buybacks, & '!AW:AW,MATCH($B13,'Federal Tax, Stock Buybacks, & '!$E:$E,0))} -> 0 | AV13: {=INDEX('Federal Tax, Stock Buybacks, & '!AX:AX,MATCH($B13,'Federal Tax, Stock Buybacks, & '!$E:$E,0))} -> 0 | AW13: {=INDEX('Federal Tax, Stock Buybacks, & '!AY:AY,MATCH($B13,'Federal Tax, Stock Buybacks, & '!$E:$E,0))} -> 0 | AX13: {=INDEX('Federal Tax, Stock Buybacks, & '!AZ:AZ,MATCH($B13,'Federal Tax, Stock Buybacks, & '!$E:$E,0))} -> 0 | AY13: {=INDEX('Federal Tax, Stock Buybacks, & '!BA:BA,MATCH($B13,'Federal Tax, Stock Buybacks, & '!$E:$E,0))} -> 0 | BA13: =AVERAGE(BC13:BG13) -> 171049.2 | BB13: =sum(BC13:BG13) -> 855246 | BC13: 199130 | BD13: 181612 | BE13: 154799 | BF13: 167750 | BG13: 151955 | BJ13: Link
A14: {=INDEX('Federal Tax, Stock Buybacks, & '!D:D,match(B14,'Federal Tax, Stock Buybacks, & '!E:E,0))} -> 30 | B14: AT&T | C14: Texas | D14: =SUMIF('Executive Pay Breakdown'!B:B,$B14,'Executive Pay Breakdown'!M:M)+SUMIF('Executive Pay Breakdown'!B:B,$B14,'Executive Pay Breakdown'!Q:Q)+SUMIF('Executive Pay Breakdown'!B:B,$B14,'Executive Pay Breakdown'!U:U)+SUMIF('Executive Pay Breakdown'!B:B,$B14,'Executive Pay Breakdown'!Y:Y)+SUMIF('Executive Pay Breakdown'!B:B,$B14,'Executive Pay Breakdown'!AC:AC) -> 506156354 | E14: =SUMIF('Executive Pay Breakdown'!B:B,$B14,'Executive Pay Breakdown'!M:M) -> 69022399 | F14: =SUMIF('Executive Pay Breakdown'!B:B,$B14,'Executive Pay Breakdown'!Q:Q) -> 87438524 | G14: =SUMIF('Executive Pay Breakdown'!B:B,$B14,'Executive Pay Breakdown'!U:U) -> 145666023 | H14: =SUMIF('Executive Pay Breakdown'!B:B,$B14,'Executive Pay Breakdown'!Y:Y) -> 115280938 | I14: =SUMIF('Executive Pay Breakdown'!B:B,$B14,'Executive Pay Breakdown'!AC:AC) -> 88748470 | K14: 2 of 5 | M14: =(F14/1000000)>(AA14) -> TRUE | N14: =(G14/1000000)>(AB14) -> TRUE | R14: =SUM(S14:W14) -> 96279.52 | S14: {=INDEX('Federal Tax, Stock Buybacks, & '!U:U,MATCH($B14,'Federal Tax, Stock Buybacks, & '!$E:$E,0))} -> 18954.52 | T14: {=INDEX('Federal Tax, Stock Buybacks, & '!V:V,MATCH($B14,'Federal Tax, Stock Buybacks, & '!$E:$E,0))} -> 24036 | U14: {=INDEX('Federal Tax, Stock Buybacks, & '!W:W,MATCH($B14,'Federal Tax, Stock Buybacks, & '!$E:$E,0))} -> 10621 | V14: {=INDEX('Federal Tax, Stock Buybacks, & '!X:X,MATCH($B14,'Federal Tax, Stock Buybacks, & '!$E:$E,0))} -> 21797 | W14: {=INDEX('Federal Tax, Stock Buybacks, & '!Y:Y,MATCH($B14,'Federal Tax, Stock Buybacks, & '!$E:$E,0))} -> 20871 | Y14: =SUM(Z14:AD14) -> 2536 | Z14: {=INDEX('Federal Tax, Stock Buybacks, & '!AB:AB,MATCH($B14,'Federal Tax, Stock Buybacks, & '!$E:$E,0))} -> 579 | AA14: {=INDEX('Federal Tax, Stock Buybacks, & '!AC:AC,MATCH($B14,'Federal Tax, Stock Buybacks, & '!$E:$E,0))} -> -1198 | AB14: {=INDEX('Federal Tax, Stock Buybacks, & '!AD:AD,MATCH($B14,'Federal Tax, Stock Buybacks, & '!$E:$E,0))} -> -687 | AC14: {=INDEX('Federal Tax, Stock Buybacks, & '!AE:AE,MATCH($B14,'Federal Tax, Stock Buybacks, & '!$E:$E,0))} -> 584 | AD14: {=INDEX('Federal Tax, Stock Buybacks, & '!AF:AF,MATCH($B14,'Federal Tax, Stock Buybacks, & '!$E:$E,0))} -> 3258 | AF14: =Y14/R14 -> 0.026339973 | AG14: =Z14/S14 -> 0.030546804 | AH14: =AA14/T14 -> -0.049841904 | AI14: =AB14/U14 -> -0.064683175 | AJ14: =AC14/V14 -> 0.026792678 | AK14: =AD14/W14 -> 0.15610177 | AM14: =SUM(AN14:AR14) -> 9616 | AN14: {=INDEX('Federal Tax, Stock Buybacks, & '!AP:AP,MATCH($B14,'Federal Tax, Stock Buybacks, & '!$E:$E,0))} -> 890 | AO14: {=INDEX('Federal Tax, Stock Buybacks, & '!AQ:AQ,MATCH($B14,'Federal Tax, Stock Buybacks, & '!$E:$E,0))} -> 202 | AP14: {=INDEX('Federal Tax, Stock Buybacks, & '!AR:AR,MATCH($B14,'Federal Tax, Stock Buybacks, & '!$E:$E,0))} -> 5498 | AQ14: {=INDEX('Federal Tax, Stock Buybacks, & '!AS:AS,MATCH($B14,'Federal Tax, Stock Buybacks, & '!$E:$E,0))} -> 2417 | AR14: {=INDEX('Federal Tax, Stock Buybacks, & '!AT:AT,MATCH($B14,'Federal Tax, Stock Buybacks, & '!$E:$E,0))} -> 609 | AT14: =SUM(AU14:AY14) -> 68181 | AU14: {=INDEX('Federal Tax, Stock Buybacks, & '!AW:AW,MATCH($B14,'Federal Tax, Stock Buybacks, & '!$E:$E,0))} -> 9859 | AV14: {=INDEX('Federal Tax, Stock Buybacks, & '!AX:AX,MATCH($B14,'Federal Tax, Stock Buybacks, & '!$E:$E,0))} -> 15068 | AW14: {=INDEX('Federal Tax, Stock Buybacks, & '!AY:AY,MATCH($B14,'Federal Tax, Stock Buybacks, & '!$E:$E,0))} -> 14956 | AX14: {=INDEX('Federal Tax, Stock Buybacks, & '!AZ:AZ,MATCH($B14,'Federal Tax, Stock Buybacks, & '!$E:$E,0))} -> 14888 | AY14: {=INDEX('Federal Tax, Stock Buybacks, & '!BA:BA,MATCH($B14,'Federal Tax, Stock Buybacks, & '!$E:$E,0))} -> 13410 | BA14: =AVERAGE(BC14:BG14) -> 99184.4 | BB14: =sum(BC14:BG14) -> 495922 | BC14: 104509 | BD14: 107570 | BE14: 89399 | BF14: 98630 | BG14: 95814 | BJ14: Link
A15: {=INDEX('Federal Tax, Stock Buybacks, & '!D:D,match(B15,'Federal Tax, Stock Buybacks, & '!E:E,0))} -> 19 | B15: Ford Motor | C15: Michigan | D15: =SUMIF('Executive Pay Breakdown'!B:B,$B15,'Executive Pay Breakdown'!M:M)+SUMIF('Executive Pay Breakdown'!B:B,$B15,'Executive Pay Breakdown'!Q:Q)+SUMIF('Executive Pay Breakdown'!B:B,$B15,'Executive Pay Breakdown'!U:U)+SUMIF('Executive Pay Breakdown'!B:B,$B15,'Executive Pay Breakdown'!Y:Y)+SUMIF('Executive Pay Breakdown'!B:B,$B15,'Executive Pay Breakdown'!AC:AC) -> 354886022 | E15: =SUMIF('Executive Pay Breakdown'!B:B,$B15,'Executive Pay Breakdown'!M:M) -> 70514448 | F15: =SUMIF('Executive Pay Breakdown'!B:B,$B15,'Executive Pay Breakdown'!Q:Q) -> 85506594 | G15: =SUMIF('Executive Pay Breakdown'!B:B,$B15,'Executive Pay Breakdown'!U:U) -> 77047762 | H15: =SUMIF('Executive Pay Breakdown'!B:B,$B15,'Executive Pay Breakdown'!Y:Y) -> 70128449 | I15: =SUMIF('Executive Pay Breakdown'!B:B,$B15,'Executive Pay Breakdown'!AC:AC) -> 51688769 | K15: YES | L15: =(E15/1000000)>(Z15) -> TRUE | N15: =(G15/1000000)>(AB15) -> TRUE | O15: =(H15/1000000)>(AC15) -> TRUE | R15: =SUM(S15:W15) -> 7840 | S15: {=INDEX('Federal Tax, Stock Buybacks, & '!U:U,MATCH($B15,'Federal Tax, Stock Buybacks, & '!$E:$E,0))} -> -6671 | T15: {=INDEX('Federal Tax, Stock Buybacks, & '!V:V,MATCH($B15,'Federal Tax, Stock Buybacks, & '!$E:$E,0))} -> 10017 | U15: {=INDEX('Federal Tax, Stock Buybacks, & '!W:W,MATCH($B15,'Federal Tax, Stock Buybacks, & '!$E:$E,0))} -> -186 | V15: {=INDEX('Federal Tax, Stock Buybacks, & '!X:X,MATCH($B15,'Federal Tax, Stock Buybacks, & '!$E:$E,0))} -> 2623 | W15: {=INDEX('Federal Tax, Stock Buybacks, & '!Y:Y,MATCH($B15,'Federal Tax, Stock Buybacks, & '!$E:$E,0))} -> 2057 | Y15: =SUM(Z15:AD15) -> 121 | Z15: {=INDEX('Federal Tax, Stock Buybacks, & '!AB:AB,MATCH($B15,'Federal Tax, Stock Buybacks, & '!$E:$E,0))} -> 68 | AA15: {=INDEX('Federal Tax, Stock Buybacks, & '!AC:AC,MATCH($B15,'Federal Tax, Stock Buybacks, & '!$E:$E,0))} -> 102 | AB15: {=INDEX('Federal Tax, Stock Buybacks, & '!AD:AD,MATCH($B15,'Federal Tax, Stock Buybacks, & '!$E:$E,0))} -> -23 | AC15: {=INDEX('Federal Tax, Stock Buybacks, & '!AE:AE,MATCH($B15,'Federal Tax, Stock Buybacks, & '!$E:$E,0))} -> -101 | AD15: {=INDEX('Federal Tax, Stock Buybacks, & '!AF:AF,MATCH($B15,'Federal Tax, Stock Buybacks, & '!$E:$E,0))} -> 75 | AF15: =Y15/R15 -> 0.015433673 | AG15: =Z15/S15 -> -0.010193374 | AH15: =AA15/T15 -> 0.010182689 | AI15: =AB15/U15 -> 0.12365591 | AJ15: =AC15/V15 -> -0.038505528 | AK15: =AD15/W15 -> 0.036460865 | AM15: =SUM(AN15:AR15) -> 885 | AN15: {=INDEX('Federal Tax, Stock Buybacks, & '!AP:AP,MATCH($B15,'Federal Tax, Stock Buybacks, & '!$E:$E,0))} -> 484 | AO15: {=INDEX('Federal Tax, Stock Buybacks, & '!AQ:AQ,MATCH($B15,'Federal Tax, Stock Buybacks, & '!$E:$E,0))} -> 0 | AP15: {=INDEX('Federal Tax, Stock Buybacks, & '!AR:AR,MATCH($B15,'Federal Tax, Stock Buybacks, & '!$E:$E,0))} -> 0 | AQ15: {=INDEX('Federal Tax, Stock Buybacks, & '!AS:AS,MATCH($B15,'Federal Tax, Stock Buybacks, & '!$E:$E,0))} -> 237 | AR15: {=INDEX('Federal Tax, Stock Buybacks, & '!AT:AT,MATCH($B15,'Federal Tax, Stock Buybacks, & '!$E:$E,0))} -> 164 | AT15: =SUM(AU15:AY15) -> 8302 | AU15: {=INDEX('Federal Tax, Stock Buybacks, & '!AW:AW,MATCH($B15,'Federal Tax, Stock Buybacks, & '!$E:$E,0))} -> 2009 | AV15: {=INDEX('Federal Tax, Stock Buybacks, & '!AX:AX,MATCH($B15,'Federal Tax, Stock Buybacks, & '!$E:$E,0))} -> 403 | AW15: {=INDEX('Federal Tax, Stock Buybacks, & '!AY:AY,MATCH($B15,'Federal Tax, Stock Buybacks, & '!$E:$E,0))} -> 596 | AX15: {=INDEX('Federal Tax, Stock Buybacks, & '!AZ:AZ,MATCH($B15,'Federal Tax, Stock Buybacks, & '!$E:$E,0))} -> 2389 | AY15: {=INDEX('Federal Tax, Stock Buybacks, & '!BA:BA,MATCH($B15,'Federal Tax, Stock Buybacks, & '!$E:$E,0))} -> 2905 | BA15: =AVERAGE(BC15:BG15) -> 75098.8 | BB15: =sum(BC15:BG15) -> 375494 | BC15: 74691 | BD15: 64003 | BE15: 61778 | BF15: 110706 | BG15: 64316 | BJ15: Link
A16: {=INDEX('Federal Tax, Stock Buybacks, & '!D:D,match(B16,'Federal Tax, Stock Buybacks, & '!E:E,0))} -> 10 | B16: Chevron | C16: California | D16: =SUMIF('Executive Pay Breakdown'!B:B,$B16,'Executive Pay Breakdown'!M:M)+SUMIF('Executive Pay Breakdown'!B:B,$B16,'Executive Pay Breakdown'!Q:Q)+SUMIF('Executive Pay Breakdown'!B:B,$B16,'Executive Pay Breakdown'!U:U)+SUMIF('Executive Pay Breakdown'!B:B,$B16,'Executive Pay Breakdown'!Y:Y)+SUMIF('Executive Pay Breakdown'!B:B,$B16,'Executive Pay Breakdown'!AC:AC) -> 325651401 | E16: =SUMIF('Executive Pay Breakdown'!B:B,$B16,'Executive Pay Breakdown'!M:M) -> 55537320 | F16: =SUMIF('Executive Pay Breakdown'!B:B,$B16,'Executive Pay Breakdown'!Q:Q) -> 57227037 | G16: =SUMIF('Executive Pay Breakdown'!B:B,$B16,'Executive Pay Breakdown'!U:U) -> 65229188 | H16: =SUMIF('Executive Pay Breakdown'!B:B,$B16,'Executive Pay Breakdown'!Y:Y) -> 91811218 | I16: =SUMIF('Executive Pay Breakdown'!B:B,$B16,'Executive Pay Breakdown'!AC:AC) -> 55846638 | K16: 3 of 5 | N16: =(G16/1000000)>(AB16) -> TRUE | O16: =(H16/1000000)>(AC16) -> TRUE | P16: =(I16/1000000)>(AD16) -> TRUE | R16: =SUM(S16:W16) -> 23121 | S16: {=INDEX('Federal Tax, Stock Buybacks, & '!U:U,MATCH($B16,'Federal Tax, Stock Buybacks, & '!$E:$E,0))} -> 20523 | T16: {=INDEX('Federal Tax, Stock Buybacks, & '!V:V,MATCH($B16,'Federal Tax, Stock Buybacks, & '!$E:$E,0))} -> 9452 | U16: {=INDEX('Federal Tax, Stock Buybacks, & '!W:W,MATCH($B16,'Federal Tax, Stock Buybacks, & '!$E:$E,0))} -> -5765 | V16: {=INDEX('Federal Tax, Stock Buybacks, & '!X:X,MATCH($B16,'Federal Tax, Stock Buybacks, & '!$E:$E,0))} -> -5636 | W16: {=INDEX('Federal Tax, Stock Buybacks, & '!Y:Y,MATCH($B16,'Federal Tax, Stock Buybacks, & '!$E:$E,0))} -> 4547 | Y16: =SUM(Z16:AD16) -> 1461 | Z16: {=INDEX('Federal Tax, Stock Buybacks, & '!AB:AB,MATCH($B16,'Federal Tax, Stock Buybacks, & '!$E:$E,0))} -> 1723 | AA16: {=INDEX('Federal Tax, Stock Buybacks, & '!AC:AC,MATCH($B16,'Federal Tax, Stock Buybacks, & '!$E:$E,0))} -> 174 | AB16: {=INDEX('Federal Tax, Stock Buybacks, & '!AD:AD,MATCH($B16,'Federal Tax, Stock Buybacks, & '!$E:$E,0))} -> -182 | AC16: {=INDEX('Federal Tax, Stock Buybacks, & '!AE:AE,MATCH($B16,'Federal Tax, Stock Buybacks, & '!$E:$E,0))} -> -73 | AD16: {=INDEX('Federal Tax, Stock Buybacks, & '!AF:AF,MATCH($B16,'Federal Tax, Stock Buybacks, & '!$E:$E,0))} -> -181 | AF16: =Y16/R16 -> 0.063189308 | AG16: =Z16/S16 -> 0.083954588 | AH16: =AA16/T16 -> 0.018408802 | AI16: =AB16/U16 -> 0.031569818 | AJ16: =AC16/V16 -> 0.012952449 | AK16: =AD16/W16 -> -0.039806466 | AM16: =SUM(AN16:AR16) -> 10487 | AN16: {=INDEX('Federal Tax, Stock Buybacks, & '!AP:AP,MATCH($B16,'Federal Tax, Stock Buybacks, & '!$E:$E,0))} -> 5417 | AO16: {=INDEX('Federal Tax, Stock Buybacks, & '!AQ:AQ,MATCH($B16,'Federal Tax, Stock Buybacks, & '!$E:$E,0))} -> 0 | AP16: {=INDEX('Federal Tax, Stock Buybacks, & '!AR:AR,MATCH($B16,'Federal Tax, Stock Buybacks, & '!$E:$E,0))} -> 1531 | AQ16: {=INDEX('Federal Tax, Stock Buybacks, & '!AS:AS,MATCH($B16,'Federal Tax, Stock Buybacks, & '!$E:$E,0))} -> 2935 | AR16: {=INDEX('Federal Tax, Stock Buybacks, & '!AT:AT,MATCH($B16,'Federal Tax, Stock Buybacks, & '!$E:$E,0))} -> 604 | AT16: =SUM(AU16:AY16) -> 48259 | AU16: {=INDEX('Federal Tax, Stock Buybacks, & '!AW:AW,MATCH($B16,'Federal Tax, Stock Buybacks, & '!$E:$E,0))} -> 10968 | AV16: {=INDEX('Federal Tax, Stock Buybacks, & '!AX:AX,MATCH($B16,'Federal Tax, Stock Buybacks, & '!$E:$E,0))} -> 10179 | AW16: {=INDEX('Federal Tax, Stock Buybacks, & '!AY:AY,MATCH($B16,'Federal Tax, Stock Buybacks, & '!$E:$E,0))} -> 9651 | AX16: {=INDEX('Federal Tax, Stock Buybacks, & '!AZ:AZ,MATCH($B16,'Federal Tax, Stock Buybacks, & '!$E:$E,0))} -> 8959 | AY16: {=INDEX('Federal Tax, Stock Buybacks, & '!BA:BA,MATCH($B16,'Federal Tax, Stock Buybacks, & '!$E:$E,0))} -> 8502 | BA16: =AVERAGE(BC16:BG16) -> 157003.2 | BB16: =sum(BC16:BG16) -> 785016 | BC16: 161488 | BD16: 183531 | BE16: 157572 | BF16: 140063 | BG16: 142362 | BJ16: Link
A17: {=INDEX('Federal Tax, Stock Buybacks, & '!D:D,match(B17,'Federal Tax, Stock Buybacks, & '!E:E,0))} -> 187 | B17: NextEra Energy | C17: Florida | D17: =SUMIF('Executive Pay Breakdown'!B:B,$B17,'Executive Pay Breakdown'!M:M)+SUMIF('Executive Pay Breakdown'!B:B,$B17,'Executive Pay Breakdown'!Q:Q)+SUMIF('Executive Pay Breakdown'!B:B,$B17,'Executive Pay Breakdown'!U:U)+SUMIF('Executive Pay Breakdown'!B:B,$B17,'Executive Pay Breakdown'!Y:Y)+SUMIF('Executive Pay Breakdown'!B:B,$B17,'Executive Pay Breakdown'!AC:AC) -> 324823145 | E17: =SUMIF('Executive Pay Breakdown'!B:B,$B17,'Executive Pay Breakdown'!M:M) -> 94794812 | F17: =SUMIF('Executive Pay Breakdown'!B:B,$B17,'Executive Pay Breakdown'!Q:Q) -> 78603376 | G17: =SUMIF('Executive Pay Breakdown'!B:B,$B17,'Executive Pay Breakdown'!U:U) -> 49540467 | H17: =SUMIF('Executive Pay Breakdown'!B:B,$B17,'Executive Pay Breakdown'!Y:Y) -> 56574381 | I17: =SUMIF('Executive Pay Breakdown'!B:B,$B17,'Executive Pay Breakdown'!AC:AC) -> 45310109 | K17: YES | L17: =(E17/1000000)>(Z17) -> TRUE | M17: =(F17/1000000)>(AA17) -> TRUE | P17: =(I17/1000000)>(AD17) -> TRUE | R17: =SUM(S17:W17) -> 23965 | S17: {=INDEX('Federal Tax, Stock Buybacks, & '!U:U,MATCH($B17,'Federal Tax, Stock Buybacks, & '!$E:$E,0))} -> 4692 | T17: {=INDEX('Federal Tax, Stock Buybacks, & '!V:V,MATCH($B17,'Federal Tax, Stock Buybacks, & '!$E:$E,0))} -> 3983 | U17: {=INDEX('Federal Tax, Stock Buybacks, & '!W:W,MATCH($B17,'Federal Tax, Stock Buybacks, & '!$E:$E,0))} -> 2945 | V17: {=INDEX('Federal Tax, Stock Buybacks, & '!X:X,MATCH($B17,'Federal Tax, Stock Buybacks, & '!$E:$E,0))} -> 4194 | W17: {=INDEX('Federal Tax, Stock Buybacks, & '!Y:Y,MATCH($B17,'Federal Tax, Stock Buybacks, & '!$E:$E,0))} -> 8151 | Y17: =SUM(Z17:AD17) -> 287 | Z17: {=INDEX('Federal Tax, Stock Buybacks, & '!AB:AB,MATCH($B17,'Federal Tax, Stock Buybacks, & '!$E:$E,0))} -> 11 | AA17: {=INDEX('Federal Tax, Stock Buybacks, & '!AC:AC,MATCH($B17,'Federal Tax, Stock Buybacks, & '!$E:$E,0))} -> -26 | AB17: {=INDEX('Federal Tax, Stock Buybacks, & '!AD:AD,MATCH($B17,'Federal Tax, Stock Buybacks, & '!$E:$E,0))} -> 105 | AC17: {=INDEX('Federal Tax, Stock Buybacks, & '!AE:AE,MATCH($B17,'Federal Tax, Stock Buybacks, & '!$E:$E,0))} -> 167 | AD17: {=INDEX('Federal Tax, Stock Buybacks, & '!AF:AF,MATCH($B17,'Federal Tax, Stock Buybacks, & '!$E:$E,0))} -> 30 | AF17: =Y17/R17 -> 0.011975798 | AG17: =Z17/S17 -> 0.002344416 | AH17: =AA17/T17 -> -0.0065277429 | AI17: =AB17/U17 -> 0.03565365 | AJ17: =AC17/V17 -> 0.039818789 | AK17: =AD17/W17 -> 0.00368053 | AM17: =SUM(AN17:AR17) -> 0 | AN17: {=INDEX('Federal Tax, Stock Buybacks, & '!AP:AP,MATCH($B17,'Federal Tax, Stock Buybacks, & '!$E:$E,0))} -> 0 | AO17: {=INDEX('Federal Tax, Stock Buybacks, & '!AQ:AQ,MATCH($B17,'Federal Tax, Stock Buybacks, & '!$E:$E,0))} -> 0 | AP17: {=INDEX('Federal Tax, Stock Buybacks, & '!AR:AR,MATCH($B17,'Federal Tax, Stock Buybacks, & '!$E:$E,0))} -> 0 | AQ17: {=INDEX('Federal Tax, Stock Buybacks, & '!AS:AS,MATCH($B17,'Federal Tax, Stock Buybacks, & '!$E:$E,0))} -> 0 | AR17: {=INDEX('Federal Tax, Stock Buybacks, & '!AT:AT,MATCH($B17,'Federal Tax, Stock Buybacks, & '!$E:$E,0))} -> 0 | AT17: =SUM(AU17:AY17) -> 13628 | AU17: {=INDEX('Federal Tax, Stock Buybacks, & '!AW:AW,MATCH($B17,'Federal Tax, Stock Buybacks, & '!$E:$E,0))} -> 3352 | AV17: {=INDEX('Federal Tax, Stock Buybacks, & '!AX:AX,MATCH($B17,'Federal Tax, Stock Buybacks, & '!$E:$E,0))} -> 3024 | AW17: {=INDEX('Federal Tax, Stock Buybacks, & '!AY:AY,MATCH($B17,'Federal Tax, Stock Buybacks, & '!$E:$E,0))} -> 2743 | AX17: {=INDEX('Federal Tax, Stock Buybacks, & '!AZ:AZ,MATCH($B17,'Federal Tax, Stock Buybacks, & '!$E:$E,0))} -> 2408 | AY17: {=INDEX('Federal Tax, Stock Buybacks, & '!BA:BA,MATCH($B17,'Federal Tax, Stock Buybacks, & '!$E:$E,0))} -> 2101 | BA17: =AVERAGE(BC17:BG17) -> 132852.6 | BB17: =sum(BC17:BG17) -> 664263 | BC17: 141446 | BD17: 132798 | BE17: 134919 | BF17: 129735 | BG17: 125365 | BJ17: Link
A18: {=INDEX('Federal Tax, Stock Buybacks, & '!D:D,match(B18,'Federal Tax, Stock Buybacks, & '!E:E,0))} -> 21 | B18: General Motors | C18: Michigan | D18: =SUMIF('Executive Pay Breakdown'!B:B,$B18,'Executive Pay Breakdown'!M:M)+SUMIF('Executive Pay Breakdown'!B:B,$B18,'Executive Pay Breakdown'!Q:Q)+SUMIF('Executive Pay Breakdown'!B:B,$B18,'Executive Pay Breakdown'!U:U)+SUMIF('Executive Pay Breakdown'!B:B,$B18,'Executive Pay Breakdown'!Y:Y)+SUMIF('Executive Pay Breakdown'!B:B,$B18,'Executive Pay Breakdown'!AC:AC) -> 317606249 | E18: =SUMIF('Executive Pay Breakdown'!B:B,$B18,'Executive Pay Breakdown'!M:M) -> 71139291 | F18: =SUMIF('Executive Pay Breakdown'!B:B,$B18,'Executive Pay Breakdown'!Q:Q) -> 69066856 | G18: =SUMIF('Executive Pay Breakdown'!B:B,$B18,'Executive Pay Breakdown'!U:U) -> 70088071 | H18: =SUMIF('Executive Pay Breakdown'!B:B,$B18,'Executive Pay Breakdown'!Y:Y) -> 51327820 | I18: =SUMIF('Executive Pay Breakdown'!B:B,$B18,'Executive Pay Breakdown'!AC:AC) -> 55984211 | K18: 3 of 5 | M18: =(F18/1000000)>(AA18) -> TRUE | O18: =(H18/1000000)>(AC18) -> TRUE | P18: =(I18/1000000)>(AD18) -> TRUE | R18: =SUM(S18:W18) -> 33110 | S18: {=INDEX('Federal Tax, Stock Buybacks, & '!U:U,MATCH($B18,'Federal Tax, Stock Buybacks, & '!$E:$E,0))} -> 9086 | T18: {=INDEX('Federal Tax, Stock Buybacks, & '!V:V,MATCH($B18,'Federal Tax, Stock Buybacks, & '!$E:$E,0))} -> 9371 | U18: {=INDEX('Federal Tax, Stock Buybacks, & '!W:W,MATCH($B18,'Federal Tax, Stock Buybacks, & '!$E:$E,0))} -> 6609 | V18: {=INDEX('Federal Tax, Stock Buybacks, & '!X:X,MATCH($B18,'Federal Tax, Stock Buybacks, & '!$E:$E,0))} -> 3724 | W18: {=INDEX('Federal Tax, Stock Buybacks, & '!Y:Y,MATCH($B18,'Federal Tax, Stock Buybacks, & '!$E:$E,0))} -> 4320 | Y18: =SUM(Z18:AD18) -> 431 | Z18: {=INDEX('Federal Tax, Stock Buybacks, & '!AB:AB,MATCH($B18,'Federal Tax, Stock Buybacks, & '!$E:$E,0))} -> 389 | AA18: {=INDEX('Federal Tax, Stock Buybacks, & '!AC:AC,MATCH($B18,'Federal Tax, Stock Buybacks, & '!$E:$E,0))} -> 20 | AB18: {=INDEX('Federal Tax, Stock Buybacks, & '!AD:AD,MATCH($B18,'Federal Tax, Stock Buybacks, & '!$E:$E,0))} -> 84 | AC18: {=INDEX('Federal Tax, Stock Buybacks, & '!AE:AE,MATCH($B18,'Federal Tax, Stock Buybacks, & '!$E:$E,0))} -> 42 | AD18: {=INDEX('Federal Tax, Stock Buybacks, & '!AF:AF,MATCH($B18,'Federal Tax, Stock Buybacks, & '!$E:$E,0))} -> -104 | AF18: =Y18/R18 -> 0.013017215 | AG18: =Z18/S18 -> 0.042813119 | AH18: =AA18/T18 -> 0.0021342439 | AI18: =AB18/U18 -> 0.012709941 | AJ18: =AC18/V18 -> 0.011278195 | AK18: =AD18/W18 -> -0.024074074 | AM18: =SUM(AN18:AR18) -> 2690 | AN18: {=INDEX('Federal Tax, Stock Buybacks, & '!AP:AP,MATCH($B18,'Federal Tax, Stock Buybacks, & '!$E:$E,0))} -> 2500 | AO18: {=INDEX('Federal Tax, Stock Buybacks, & '!AQ:AQ,MATCH($B18,'Federal Tax, Stock Buybacks, & '!$E:$E,0))} -> 0 | AP18: {=INDEX('Federal Tax, Stock Buybacks, & '!AR:AR,MATCH($B18,'Federal Tax, Stock Buybacks, & '!$E:$E,0))} -> 90 | AQ18: {=INDEX('Federal Tax, Stock Buybacks, & '!AS:AS,MATCH($B18,'Federal Tax, Stock Buybacks, & '!$E:$E,0))} -> 0 | AR18: {=INDEX('Federal Tax, Stock Buybacks, & '!AT:AT,MATCH($B18,'Federal Tax, Stock Buybacks, & '!$E:$E,0))} -> 100 | AT18: =SUM(AU18:AY18) -> 5844 | AU18: {=INDEX('Federal Tax, Stock Buybacks, & '!AW:AW,MATCH($B18,'Federal Tax, Stock Buybacks, & '!$E:$E,0))} -> 397 | AV18: {=INDEX('Federal Tax, Stock Buybacks, & '!AX:AX,MATCH($B18,'Federal Tax, Stock Buybacks, & '!$E:$E,0))} -> 186 | AW18: {=INDEX('Federal Tax, Stock Buybacks, & '!AY:AY,MATCH($B18,'Federal Tax, Stock Buybacks, & '!$E:$E,0))} -> 669 | AX18: {=INDEX('Federal Tax, Stock Buybacks, & '!AZ:AZ,MATCH($B18,'Federal Tax, Stock Buybacks, & '!$E:$E,0))} -> 2350 | AY18: {=INDEX('Federal Tax, Stock Buybacks, & '!BA:BA,MATCH($B18,'Federal Tax, Stock Buybacks, & '!$E:$E,0))} -> 2242 | BA18: =AVERAGE(BC18:BG18) -> 90319.4 | BB18: =sum(BC18:BG18) -> 451597 | BC18: 80034 | BD18: 69433 | BE18: 117566 | BF18: 106715 | BG18: 77849 | BJ18: Link
A19: {=INDEX('Federal Tax, Stock Buybacks, & '!D:D,match(B19,'Federal Tax, Stock Buybacks, & '!E:E,0))} -> 79 | B19: Charter Communications | C19: Connecticut | D19: =SUMIF('Executive Pay Breakdown'!B:B,$B19,'Executive Pay Breakdown'!M:M)+SUMIF('Executive Pay Breakdown'!B:B,$B19,'Executive Pay Breakdown'!Q:Q)+SUMIF('Executive Pay Breakdown'!B:B,$B19,'Executive Pay Breakdown'!U:U)+SUMIF('Executive Pay Breakdown'!B:B,$B19,'Executive Pay Breakdown'!Y:Y)+SUMIF('Executive Pay Breakdown'!B:B,$B19,'Executive Pay Breakdown'!AC:AC) -> 313413516 | E19: =SUMIF('Executive Pay Breakdown'!B:B,$B19,'Executive Pay Breakdown'!M:M) -> 84769628 | F19: =SUMIF('Executive Pay Breakdown'!B:B,$B19,'Executive Pay Breakdown'!Q:Q) -> 82843548 | G19: =SUMIF('Executive Pay Breakdown'!B:B,$B19,'Executive Pay Breakdown'!U:U) -> 104461965 | H19: =SUMIF('Executive Pay Breakdown'!B:B,$B19,'Executive Pay Breakdown'!Y:Y) -> 21511198 | I19: =SUMIF('Executive Pay Breakdown'!B:B,$B19,'Executive Pay Breakdown'!AC:AC) -> 19827177 | K19: 3 of 5 | M19: =(F19/1000000)>(AA19) -> TRUE | N19: =(G19/1000000)>(AB19) -> TRUE | O19: =(H19/1000000)>(AC19) -> TRUE | R19: =SUM(S19:W19) -> 18849 | S19: {=INDEX('Federal Tax, Stock Buybacks, & '!U:U,MATCH($B19,'Federal Tax, Stock Buybacks, & '!$E:$E,0))} -> 6320 | T19: {=INDEX('Federal Tax, Stock Buybacks, & '!V:V,MATCH($B19,'Federal Tax, Stock Buybacks, & '!$E:$E,0))} -> 5492 | U19: {=INDEX('Federal Tax, Stock Buybacks, & '!W:W,MATCH($B19,'Federal Tax, Stock Buybacks, & '!$E:$E,0))} -> 3680 | V19: {=INDEX('Federal Tax, Stock Buybacks, & '!X:X,MATCH($B19,'Federal Tax, Stock Buybacks, & '!$E:$E,0))} -> 1994 | W19: {=INDEX('Federal Tax, Stock Buybacks, & '!Y:Y,MATCH($B19,'Federal Tax, Stock Buybacks, & '!$E:$E,0))} -> 1363 | Y19: =SUM(Z19:AD19) -> 1212 | Z19: {=INDEX('Federal Tax, Stock Buybacks, & '!AB:AB,MATCH($B19,'Federal Tax, Stock Buybacks, & '!$E:$E,0))} -> 1178 | AA19: {=INDEX('Federal Tax, Stock Buybacks, & '!AC:AC,MATCH($B19,'Federal Tax, Stock Buybacks, & '!$E:$E,0))} -> 12 | AB19: {=INDEX('Federal Tax, Stock Buybacks, & '!AD:AD,MATCH($B19,'Federal Tax, Stock Buybacks, & '!$E:$E,0))} -> -7 | AC19: {=INDEX('Federal Tax, Stock Buybacks, & '!AE:AE,MATCH($B19,'Federal Tax, Stock Buybacks, & '!$E:$E,0))} -> 6 | AD19: {=INDEX('Federal Tax, Stock Buybacks, & '!AF:AF,MATCH($B19,'Federal Tax, Stock Buybacks, & '!$E:$E,0))} -> 23 | AF19: =Y19/R19 -> 0.064300493 | AG19: =Z19/S19 -> 0.18639241 | AH19: =AA19/T19 -> 0.0021849964 | AI19: =AB19/U19 -> -0.0019021739 | AJ19: =AC19/V19 -> 0.0030090271 | AK19: =AD19/W19 -> 0.016874541 | AM19: =SUM(AN19:AR19) -> 48197 | AN19: {=INDEX('Federal Tax, Stock Buybacks, & '!AP:AP,MATCH($B19,'Federal Tax, Stock Buybacks, & '!$E:$E,0))} -> 10277 | AO19: {=INDEX('Federal Tax, Stock Buybacks, & '!AQ:AQ,MATCH($B19,'Federal Tax, Stock Buybacks, & '!$E:$E,0))} -> 15431 | AP19: {=INDEX('Federal Tax, Stock Buybacks, & '!AR:AR,MATCH($B19,'Federal Tax, Stock Buybacks, & '!$E:$E,0))} -> 11217 | AQ19: {=INDEX('Federal Tax, Stock Buybacks, & '!AS:AS,MATCH($B19,'Federal Tax, Stock Buybacks, & '!$E:$E,0))} -> 6873 | AR19: {=INDEX('Federal Tax, Stock Buybacks, & '!AT:AT,MATCH($B19,'Federal Tax, Stock Buybacks, & '!$E:$E,0))} -> 4399 | AT19: =SUM(AU19:AY19) -> 0 | AU19: {=INDEX('Federal Tax, Stock Buybacks, & '!AW:AW,MATCH($B19,'Federal Tax, Stock Buybacks, & '!$E:$E,0))} -> 0 | AV19: {=INDEX('Federal Tax, Stock Buybacks, & '!AX:AX,MATCH($B19,'Federal Tax, Stock Buybacks, & '!$E:$E,0))} -> 0 | AW19: {=INDEX('Federal Tax, Stock Buybacks, & '!AY:AY,MATCH($B19,'Federal Tax, Stock Buybacks, & '!$E:$E,0))} -> 0 | AX19: {=INDEX('Federal Tax, Stock Buybacks, & '!AZ:AZ,MATCH($B19,'Federal Tax, Stock Buybacks, & '!$E:$E,0))} -> 0 | AY19: {=INDEX('Federal Tax, Stock Buybacks, & '!BA:BA,MATCH($B19,'Federal Tax, Stock Buybacks, & '!$E:$E,0))} -> 0 | BA19: =AVERAGE(BC19:BG19) -> 57037.8 | BB19: =sum(BC19:BG19) -> 285189 | BC19: 55429 | BD19: 60007 | BE19: 56568 | BF19: 57625 | BG19: 55560 | BJ19: Link
A20: {=INDEX('Federal Tax, Stock Buybacks, & '!D:D,match(B20,'Federal Tax, Stock Buybacks, & '!E:E,0))} -> 115 | B20: Honeywell International | C20: New Jersey | D20: =SUMIF('Executive Pay Breakdown'!B:B,$B20,'Executive Pay Breakdown'!M:M)+SUMIF('Executive Pay Breakdown'!B:B,$B20,'Executive Pay Breakdown'!Q:Q)+SUMIF('Executive Pay Breakdown'!B:B,$B20,'Executive Pay Breakdown'!U:U)+SUMIF('Executive Pay Breakdown'!B:B,$B20,'Executive Pay Breakdown'!Y:Y)+SUMIF('Executive Pay Breakdown'!B:B,$B20,'Executive Pay Breakdown'!AC:AC) -> 275600043 | E20: =SUMIF('Executive Pay Breakdown'!B:B,$B20,'Executive Pay Breakdown'!M:M) -> 58777935 | F20: =SUMIF('Executive Pay Breakdown'!B:B,$B20,'Executive Pay Breakdown'!Q:Q) -> 56056686 | G20: =SUMIF('Executive Pay Breakdown'!B:B,$B20,'Executive Pay Breakdown'!U:U) -> 43631159 | H20: =SUMIF('Executive Pay Breakdown'!B:B,$B20,'Executive Pay Breakdown'!Y:Y) -> 59441561 | I20: =SUMIF('Executive Pay Breakdown'!B:B,$B20,'Executive Pay Breakdown'!AC:AC) -> 57692702 | K20: 2 of 5 | O20: =(H20/1000000)>(AC20) -> TRUE | P20: =(I20/1000000)>(AD20) -> TRUE | R20: =SUM(S20:W20) -> 17194 | S20: {=INDEX('Federal Tax, Stock Buybacks, & '!U:U,MATCH($B20,'Federal Tax, Stock Buybacks, & '!$E:$E,0))} -> 3181 | T20: {=INDEX('Federal Tax, Stock Buybacks, & '!V:V,MATCH($B20,'Federal Tax, Stock Buybacks, & '!$E:$E,0))} -> 3809 | U20: {=INDEX('Federal Tax, Stock Buybacks, & '!W:W,MATCH($B20,'Federal Tax, Stock Buybacks, & '!$E:$E,0))} -> 3239 | V20: {=INDEX('Federal Tax, Stock Buybacks, & '!X:X,MATCH($B20,'Federal Tax, Stock Buybacks, & '!$E:$E,0))} -> 4135 | W20: {=INDEX('Federal Tax, Stock Buybacks, & '!Y:Y,MATCH($B20,'Federal Tax, Stock Buybacks, & '!$E:$E,0))} -> 2830 | Y20: =SUM(Z20:AD20) -> 1480 | Z20: {=INDEX('Federal Tax, Stock Buybacks, & '!AB:AB,MATCH($B20,'Federal Tax, Stock Buybacks, & '!$E:$E,0))} -> 653 | AA20: {=INDEX('Federal Tax, Stock Buybacks, & '!AC:AC,MATCH($B20,'Federal Tax, Stock Buybacks, & '!$E:$E,0))} -> 415 | AB20: {=INDEX('Federal Tax, Stock Buybacks, & '!AD:AD,MATCH($B20,'Federal Tax, Stock Buybacks, & '!$E:$E,0))} -> 475 | AC20: {=INDEX('Federal Tax, Stock Buybacks, & '!AE:AE,MATCH($B20,'Federal Tax, Stock Buybacks, & '!$E:$E,0))} -> 8 | AD20: {=INDEX('Federal Tax, Stock Buybacks, & '!AF:AF,MATCH($B20,'Federal Tax, Stock Buybacks, & '!$E:$E,0))} -> -71 | AF20: =Y20/R20 -> 0.086076538 | AG20: =Z20/S20 -> 0.20528136 | AH20: =AA20/T20 -> 0.10895248 | AI20: =AB20/U20 -> 0.1466502 | AJ20: =AC20/V20 -> 0.0019347037 | AK20: =AD20/W20 -> -0.025088339 | AM20: =SUM(AN20:AR20) -> 19694 | AN20: {=INDEX('Federal Tax, Stock Buybacks, & '!AP:AP,MATCH($B20,'Federal Tax, Stock Buybacks, & '!$E:$E,0))} -> 4200 | AO20: {=INDEX('Federal Tax, Stock Buybacks, & '!AQ:AQ,MATCH($B20,'Federal Tax, Stock Buybacks, & '!$E:$E,0))} -> 3380 | AP20: {=INDEX('Federal Tax, Stock Buybacks, & '!AR:AR,MATCH($B20,'Federal Tax, Stock Buybacks, & '!$E:$E,0))} -> 3714 | AQ20: {=INDEX('Federal Tax, Stock Buybacks, & '!AS:AS,MATCH($B20,'Federal Tax, Stock Buybacks, & '!$E:$E,0))} -> 4400 | AR20: {=INDEX('Federal Tax, Stock Buybacks, & '!AT:AT,MATCH($B20,'Federal Tax, Stock Buybacks, & '!$E:$E,0))} -> 4000 | AT20: =SUM(AU20:AY20) -> 12651 | AU20: {=INDEX('Federal Tax, Stock Buybacks, & '!AW:AW,MATCH($B20,'Federal Tax, Stock Buybacks, & '!$E:$E,0))} -> 2719 | AV20: {=INDEX('Federal Tax, Stock Buybacks, & '!AX:AX,MATCH($B20,'Federal Tax, Stock Buybacks, & '!$E:$E,0))} -> 2626 | AW20: {=INDEX('Federal Tax, Stock Buybacks, & '!AY:AY,MATCH($B20,'Federal Tax, Stock Buybacks, & '!$E:$E,0))} -> 2592 | AX20: {=INDEX('Federal Tax, Stock Buybacks, & '!AZ:AZ,MATCH($B20,'Federal Tax, Stock Buybacks, & '!$E:$E,0))} -> 2442 | AY20: {=INDEX('Federal Tax, Stock Buybacks, & '!BA:BA,MATCH($B20,'Federal Tax, Stock Buybacks, & '!$E:$E,0))} -> 2272 | BA20: =AVERAGE(BC20:BG20) -> 70864.8 | BB20: =sum(BC20:BG20) -> 354324 | BC20: 78095 | BD20: 75529 | BE20: 64438 | BF20: 69513 | BG20: 66749 | BJ20: Link
